Workbook
Name balance: #REF!
Name balance: #REF!
Name balance: #REF!
Name balance: #REF!
Name cashrisk: #REF!
Name cashrisk: #REF!
Name cashrisk: #REF!
Name cashrisk: #REF!
Name fees: #REF!
Name fees: #REF!
Name fees: #REF!
Name fees: #REF!
Name feespd: #REF!
Name feespd: #REF!
Name feespd: #REF!
Name feespd: #REF!
Name interest: #REF!
Name interest: #REF!
Name interest: #REF!
Name interest: #REF!
Name payments: #REF!
Name payments: #REF!
Name payments: #REF!
Name payments: #REF!
Name points: #REF!
Name points: #REF!
Name points: #REF!
Name points: #REF!
Name Principal: #REF!
Name Principal: #REF!
Name Principal: #REF!
Name Principal: #REF!
Name principaloutstd: #REF!
Name principaloutstd: #REF!
Name principaloutstd: #REF!
Name principaloutstd: #REF!
Name projectdays: #REF!
Name projectdays: #REF!
Name projectdays: #REF!
Name projectdays: #REF!
Name riskcash: #REF!
Name riskcash: #REF!
Name riskcash: #REF!
Name riskcash: #REF!
Name riskcash2: #REF!
Name riskcash2: #REF!
Name riskcash2: #REF!
Name riskcash2: #REF!

Sheet Version Control
B2: Please note modifications to DD files
F4: Mezzanine | G4: Entitled | H4: Horizontal | I4: Vertical
B5: Date | C5: Modifications | D5: Version # | F5: LTC | G5: 0.85 | H5: 0.95 | I5: 0.98
C6: Conducted Intake on items on Deal Details Page | D6: 1.1 | F6: LTV | G6: 0.72 | H6: 0.76 | I6: 0.8
B8: Date | C8: Modifications | D8: Version # | F8: Product Types:
F9: Single Family
F10: Townhomes
B11: Date | C11: Modifications | D11: Version # | F11: Mixed-Use
F12: Commercial
F13: Multifamily
B14: Date | C14: Modifications | D14: Version # | F14: Single Family & Townhomes
B17: Date | C17: Modifications | D17: Version #
B20: Date | C20: Modifications | D20: Version #
B23: Date | C23: Modifications | D23: Version #
B26: Date | C26: Modifications | D26: Version #
B29: Date | C29: Modifications | D29: Version #
B32: Date | C32: Modifications | D32: Version #
B35: Date | C35: Modifications | D35: Version #
B38: Date | C38: Modifications | D38: Version #

Sheet LOI
B2: Primary:
B4: =TODAY() -> 46105
B5: ='Deal Details'!C16 -> 0
B6: ='Deal Details'!C15 -> 0
B7: ="RE: Non-binding Loan Term Sheet to provide financing for a "&'Deal Details'!C11&" project in "&'Deal Details'!C5&", "&'Deal Details'!C4 -> RE: Non-binding Loan Term Sheet to provide financing for a project in ,
B9: ="Mesa Bridge Capital LLC has reviewed the preliminary information regarding the subject property and is interested in proceeding with a "&'Deal Details'!C13&" loan in accordance with the general terms discussed. Based on preliminary information, we would propose a loan as follows:" -> Mesa Bridge Capital LLC has reviewed the preliminary information regarding the subject property and is interested in proceeding with a loan in accordance with the general terms discussed. Based on preliminary information, we would propose a loan as follows:
B11: Proceeds: | C11: =IFERROR(ROUNDDOWN('Deal Details'!F20,-2),"") | E11: Funds Available for Refinance
E12: Funds Available for Construction
C13: =ProForma!D57 | E13: Interest Reserve
C14: ='Deal Details'!C24 -> 7500 | E14: Title Fees (Estimated)
C15: =IFERROR(SUM('Deal Details'!C22:C23),"") -> 13500 | E15: Closing Costs (Estimated)
C16: =ProForma!D56 | E16: =TEXT('Deal Details'!C20, "0%") & " Broker Fee" -> 1% Broker Fee
C17: =ProForma!D55 | E17: Origination Fee
C18: =SUM(C11:C17) -> 21000 | E18: Total Loan Amount
B20: Borrower: | D20: ='Deal Details'!C16 -> 0
B21: Term: | D21: =TEXT('Deal Details'!C27, "0") & " Months" -> 12 Months
B22: Lender: | D22: MBP Lending LLC
B23: Guarantor(s): | D23: ='Deal Details'!C15 -> 0
B24: Loan Recourse: | D24: Limited Recourse (standard “bad boy” carveouts) to Guarantors
B25: Primary Collateral: | D25: ="First security position on property located:"&'Deal Details'!C6&"" -> First security position on property located:
B26: Interest Rate: | D26: 12% annual rate, simple interest paid monthly in arrears
B27: Interest Reserve: | D27: =TEXT('Deal Details'!C27, "0") & " months interest reserve, paid at close from loan proceeds" -> 12 months interest reserve, paid at close from loan proceeds
B28: Origination Fee: | D28: 3% to Mesa Bridge Primary Investments II, paid at close from loan proceeds
B29: Due Diligence Fee: | D29: $4,500 to Mesa Bridge Capital, paid prior to closing the loan
B30: Processing Fee: | D30: $3,500 to Mesa Bridge Primary Investments II, paid at closing of the loan

Sheet Deal Details
A1: =MAX('Version Control'!D6:D64) -> 1.1
B2: Property | F2: Deal Summary:
B3: Project Name | K3: Best Practices:
B4: State | K4: * Link all numbers to data sources
B5: City | K5: *Avoid all hardcoding
B6: Address | K6: *Provide frequent comments, especially when working outside template
B7: Cross Streets | K7: *Black = formula or unchanging value, Blue = hardcoded driver
B8: Project County
B9: Acres
B10: Units
B11: Product Type
B12: Current State | N12: Senior LTV Sensitivity Analysis:
B13: Project Type | E13: Total Value: | F13: =C36*C10*(1-C38) -> 0 | H13: Total Costs | I13: =H23 -> 0 | K13: Cash Breakdown:
B14: Borrower | E14: 65% LTV Limit | F14: =F13*0.65 -> 0 | H14: 75% LTC Limit | I14: =I13*0.75 -> 0 | K14: Spent to Date: | L14: 0 | N14: Value/Unit: | O14: Value: | P14: Difference: | Q14: % Value & Loan Term | R14: =S14-2 -> 8 | S14: =T14-2 -> 10 | T14: =C27 -> 12 | U14: =T14+2 -> 14 | V14: =U14+2 -> 16
B15: Sponsor | E15: 60% LTV Limit | F15: =F13*0.6 -> 0 | H15: 65% LTC Limit | I15: =I13*0.65 -> 0 | K15: Additional: | L15: 0 | N15: =O15/$C$10 -> #DIV/0! | O15: =$F$13*(1+Q15) -> 0 | P15: =O15-$F$13 -> 0 | Q15: =Q16*2 -> 0.05 | R15: =_xlfn.XLOOKUP(R$14*30,'Senior Amort'!$B$33:$B$2180,'Senior Amort'!$I$33:$I$2180)/$O15 -> #VALUE! | S15: =_xlfn.XLOOKUP(S$14*30,'Senior Amort'!$B$33:$B$2180,'Senior Amort'!$I$33:$I$2180)/$O15 -> #VALUE! | T15: =_xlfn.XLOOKUP(T$14*30,'Senior Amort'!$B$33:$B$2180,'Senior Amort'!$I$33:$I$2180)/$O15 -> #VALUE! | U15: =_xlfn.XLOOKUP(U$14*30,'Senior Amort'!$B$33:$B$2180,'Senior Amort'!$I$33:$I$2180)/$O15 -> #VALUE! | V15: =_xlfn.XLOOKUP(V$14*30,'Senior Amort'!$B$33:$B$2180,'Senior Amort'!$I$33:$I$2180)/$O15 -> #VALUE!
B16: Project Entity | E16: 50% LTV Limit | F16: =F13*0.5 -> 0 | H16: 50% LTC Limit | I16: =I13*0.5 -> 0 | N16: =O16/$C$10 -> #DIV/0! | O16: =$F$13*(1+Q16) -> 0 | P16: =O16-$F$13 -> 0 | Q16: =C39/4 -> 0.025 | R16: =_xlfn.XLOOKUP(R$14*30,'Senior Amort'!$B$33:$B$2180,'Senior Amort'!$I$33:$I$2180)/$O16 -> #VALUE! | S16: =_xlfn.XLOOKUP(S$14*30,'Senior Amort'!$B$33:$B$2180,'Senior Amort'!$I$33:$I$2180)/$O16 -> #VALUE! | T16: =_xlfn.XLOOKUP(T$14*30,'Senior Amort'!$B$33:$B$2180,'Senior Amort'!$I$33:$I$2180)/$O16 -> #VALUE! | U16: =_xlfn.XLOOKUP(U$14*30,'Senior Amort'!$B$33:$B$2180,'Senior Amort'!$I$33:$I$2180)/$O16 -> #VALUE! | V16: =_xlfn.XLOOKUP(V$14*30,'Senior Amort'!$B$33:$B$2180,'Senior Amort'!$I$33:$I$2180)/$O16 -> #VALUE!
B17: Deal Broker | N17: =O17/$C$10 -> #DIV/0! | O17: =$F$13*(1+Q17) -> 0 | P17: =O17-$F$13 -> 0 | Q17: =0% -> 0 | R17: =_xlfn.XLOOKUP(R$14*30,'Senior Amort'!$B$33:$B$2180,'Senior Amort'!$I$33:$I$2180)/$O17 -> #VALUE! | S17: =_xlfn.XLOOKUP(S$14*30,'Senior Amort'!$B$33:$B$2180,'Senior Amort'!$I$33:$I$2180)/$O17 -> #VALUE! | T17: =_xlfn.XLOOKUP(T$14*30,'Senior Amort'!$B$33:$B$2180,'Senior Amort'!$I$33:$I$2180)/$O17 -> #VALUE! | U17: =_xlfn.XLOOKUP(U$14*30,'Senior Amort'!$B$33:$B$2180,'Senior Amort'!$I$33:$I$2180)/$O17 -> #VALUE! | V17: =_xlfn.XLOOKUP(V$14*30,'Senior Amort'!$B$33:$B$2180,'Senior Amort'!$I$33:$I$2180)/$O17 -> #VALUE!
B18: Liquidity | N18: =O18/$C$10 -> #DIV/0! | O18: =$F$13*(1+Q18) -> 0 | P18: =O18-$F$13 -> 0 | Q18: =Q17-C39/4 -> -0.025 | R18: =_xlfn.XLOOKUP(R$14*30,'Senior Amort'!$B$33:$B$2180,'Senior Amort'!$I$33:$I$2180)/$O18 -> #VALUE! | S18: =_xlfn.XLOOKUP(S$14*30,'Senior Amort'!$B$33:$B$2180,'Senior Amort'!$I$33:$I$2180)/$O18 -> #VALUE! | T18: =_xlfn.XLOOKUP(T$14*30,'Senior Amort'!$B$33:$B$2180,'Senior Amort'!$I$33:$I$2180)/$O18 -> #VALUE! | U18: =_xlfn.XLOOKUP(U$14*30,'Senior Amort'!$B$33:$B$2180,'Senior Amort'!$I$33:$I$2180)/$O18 -> #VALUE! | V18: =_xlfn.XLOOKUP(V$14*30,'Senior Amort'!$B$33:$B$2180,'Senior Amort'!$I$33:$I$2180)/$O18 -> #VALUE!
B19: Loan | E19: Sources: | G19: Uses: | J19: Spent to Date: | K19: Remaining: | N19: =O19/$C$10 -> #DIV/0! | O19: =$F$13*(1+Q19) -> 0 | P19: =O19-$F$13 -> 0 | Q19: =Q18*2 -> -0.05 | R19: =_xlfn.XLOOKUP(R$14*30,'Senior Amort'!$B$33:$B$2180,'Senior Amort'!$I$33:$I$2180)/$O19 -> #VALUE! | S19: =_xlfn.XLOOKUP(S$14*30,'Senior Amort'!$B$33:$B$2180,'Senior Amort'!$I$33:$I$2180)/$O19 -> #VALUE! | T19: =_xlfn.XLOOKUP(T$14*30,'Senior Amort'!$B$33:$B$2180,'Senior Amort'!$I$33:$I$2180)/$O19 -> #VALUE! | U19: =_xlfn.XLOOKUP(U$14*30,'Senior Amort'!$B$33:$B$2180,'Senior Amort'!$I$33:$I$2180)/$O19 -> #VALUE! | V19: =_xlfn.XLOOKUP(V$14*30,'Senior Amort'!$B$33:$B$2180,'Senior Amort'!$I$33:$I$2180)/$O19 -> #VALUE!
B20: MB Broker Fee | C20: 0.01 | E20: Senior Debt (Net) | F20: =ProForma!C63 | G20: Land Cost | H20: =J20+K20 -> 0 | J20: 0 | K20: 0
B21: Inspection Reserve | C21: 3500 | E21: Mezzanine Debt | F21: =C32 -> $0 | G21: Soft Cost | H21: =J21+K21 -> 0 | J21: 0 | K21: 0 | Q21: Value Spread: | R21: =C39 -> 0.1
B22: Processing Fee | C22: 3500 | E22: Sponsor Cash | F22: =SUM(L14:L15) -> 0 | G22: Construction Cost | H22: =J22+K22 -> 0 | J22: 0 | K22: 0 | Q22: Loan Term Spread: | R22: =V14-R14 -> 8
B23: Legal Fees | C23: 10000 | E23: Total | F23: =SUM(F20:F22) -> 0 | G23: Total | H23: =SUM(H20:H22) -> 0 | J23: =SUM(J20:J22) -> 0 | K23: =SUM(K20:K22) -> 0
B24: Title and Closing Costs | C24: 7500 | Q24: Value Comparison
B25: Senior % | C25: 0.12 | Q25: Our Per Unit: | R25: =C36 -> 0 | S25: % Difference
B26: Senior points | C26: 0.03 | E26: Project Value | F26: =F13 -> 0 | G26: Land | H26: Improvements | Q26: Borrower's Per Unit: | R26: =C35 -> #DIV/0! | S26: =(R26-$R$25)/$R$25 -> #DIV/0!
B27: Senior Length | C27: 12 | E27: Project Costs | F27: =G27+H27 -> 0 | G27: =H20 -> 0 | H27: =SUM(H21:H22) -> 0 | Q27: Appraisal Per Unit: | R27: =C35 -> #DIV/0! | S27: =(R27-$R$25)/$R$25 -> #DIV/0!
B28: Loan Request | E28: Sponsor Contribution | F28: =ProForma!$H$53 -> 0
B29: Senior Loan Amount | E29: Implied Equity
B30: Senior Lender | C30: MBC | E30: Lenders Contribution | F30: =IFERROR(ProForma!$C$63+ProForma!$H$54,0) -> 0
B31: Start Date | C31: =TODAY() -> 46105 | E31: Senior Lender | F31: =C30 -> MBC | G31: Mezz Loan | J31: Blended Rate:
B32: Additional Cash Required | C32: =ProForma!H54 -> $0 | E32: Loan Amount | F32: =C29 -> 0 | G32: Loan Amount | H32: =IFERROR('Mezz Amort'!$I$10,0) -> 35000 | K32: =IFERROR(SUMPRODUCT(J33:J34,K33:K34)/SUM(F32,H32),"") -> 0.24
B33: Value | E33: Origination Fee | F33: ='Deal Details'!$C$26 -> 0.03 | G33: Origination Fee | H33: ='Mezz Amort'!$C$5 -> 0.03 | J33: =F32 -> 0 | K33: 0.12
B34: Borrower's Value | E34: Interest Rate | F34: ='Deal Details'!$C$25 -> 0.12 | G34: Interest Rate | H34: ='Mezz Amort'!$C$6 -> 0.24 | J34: =H32 -> 35000 | K34: 0.24
B35: Per Unit | C35: =C34/C10 -> #DIV/0! | E35: Duration | F35: ='Deal Details'!$C$27&" Months" -> 12 Months | G35: Duration | H35: ='Mezz Amort'!C10&" Months" -> 12 Months
B36: Per Unit Sales Price | C36: 0 | E36: Senior Gross LTV | F36: =IFERROR(F32/F26,"") | G36: Junior Gross LTV | H36: =IFERROR((F32+H32)/F26,"")
B37: % Difference | C37: =IFERROR((F13-C34)/C34,"") | E37: Senior Gross LTC | F37: =IFERROR(F32/ProForma!$C$39,"") | G37: Junior Gross LTC | H37: =IFERROR((F32+H32)/ProForma!$C$39,"")
B38: Sales Cost | C38: 0 | E38: Impairment Date | F38: {=INDEX('Senior Amort'!A33:A2180,MATCH(TRUE, ('Senior Amort'!I33:I2180+'Mezz Amort'!J15:J2187)>'Deal Details'!F26,0))} -> #N/A
B39: Risk Spread: | C39: 0.1 | E39: CLTV (Gross) | F39: =H36
E40: Senior Net LTV | F40: =IFERROR((ProForma!$C$63)/F26,"") | G40: Junior Net LTV | H40: =IFERROR((F32+ProForma!$H$54)/F26,"")
E41: Senior Net LTC | F41: =IFERROR((ProForma!$C$63)/F27,"") | G41: Junior Net LTC | H41: =IFERROR((F32+ProForma!$H$54)/F27,"")
E42: Value Amount to Reach LTV Guidence:

Sheet Drawn
A1: *No Construction Reserves or Paydowns on first or last day
B2: Loan Amount | C2: =C4+C6+C7+C9+C10+C11 -> 217857.14 | J2: Draw Schedule | K2: Construction Res | N2: Paydown Schedule | Q2: IRR Calc | R2: =XIRR(R4:R56,Q4:Q56) -> 2.7053874e+16 | W2: Paydown
B3: Interest Rate | C3: 0.11 | I3: 1 | J3: 46053 | L3: =IF(K3>0,"CR","") | M3: 1 | N3: 46053 | W3: Absorption | X3: 0 | Y3: Units/Month | AA3: Build Time | AB3: ='Deal Details'!C27 -> 12 | AC3: months
B4: Interest Reserve | C4: 200000 | I4: =I3+1 -> 2 | J4: 46081 | L4: =IF(K4>0,"CR","") | M4: =M3+1 -> 2 | N4: 46081 | Q4: =+C12 -> 46023 | R4: =-C2 -> -217857.14 | S4: Gross Loan | W4: Value | X4: =X10 -> 0 | Y4: Per Unit
B5: Ending Int Res. | C5: =+SUMIF(B:B,C13,G:G) -> 175636.31 | D5: =C5/C4 -> 0.87818155 | I5: =I4+1 -> 3 | J5: 46112 | L5: =IF(K5>0,"CR","") | M5: =M4+1 -> 3 | N5: 46112 | Q5: =+C12 -> 46023 | R5: =+C4 -> 200000 | S5: Int Res. | W5: Release | X5: =(X4*X12) -> #DIV/0! | Y5: Per Unit | AA5: Mezz Paydown
B6: Origination Fee | C6: =D6*C2 -> 4357.1429 | D6: 0.02 | I6: =I5+1 -> 4 | J6: 46142 | L6: =IF(K6>0,"CR","") | M6: =M5+1 -> 4 | N6: 46142 | Q6: =+C12 -> 46023 | R6: =+C6+C9 -> 17857.143 | S6: Orig&Cl Fee
B7: Construction Res. | C7: ='Deal Details'!K22 -> 0 | I7: =I6+1 -> 5 | J7: 46173 | L7: =IF(K7>0,"CR","") | M7: =M6+1 -> 5 | N7: 46173 | Q7: =+C12 -> 46023 | R7: =+C7 -> 0 | S7: Constr. Res.
B8: Term (months) | C8: ='Deal Details'!C27 -> 12 | I8: =I7+1 -> 6 | J8: 46203 | L8: =IF(K8>0,"CR","") | M8: =M7+1 -> 6 | N8: 46203 | Q8: =+J3 -> 46053 | R8: =-K3 -> 0 | S8: Constr Res | W8: Value
B9: Closing Fees | C9: ='Deal Details'!C22+'Deal Details'!C23 -> 13500 | I9: =I8+1 -> 7 | J9: 46234 | L9: =IF(K9>0,"CR","") | M9: =M8+1 -> 7 | N9: 46234 | Q9: =+J4 -> 46081 | R9: =-K4 -> 0 | S9: =+L4 | T9: CR Draws: | W9: Property Mix | X9: Value | Y9: Units | Z9: Total
B10: Land Payoff | C10: ='Deal Details'!K20 -> 0 | I10: =I9+1 -> 8 | J10: 46265 | L10: =IF(K10>0,"CR","") | M10: =M9+1 -> 8 | N10: 46265 | Q10: =+J5 -> 46112 | R10: =-K5 -> 0 | S10: =+L5 | W10: Lots | X10: ='Deal Details'!C36 -> 0 | Y10: ='Deal Details'!C10 -> 0 | Z10: =Y10*X10 -> 0
B11: Broker Fee | C11: 0 | D11: ='Deal Details'!C20 -> 0.01 | I11: =I10+1 -> 9 | J11: 46295 | L11: =IF(K11>0,"CR","") | M11: =M10+1 -> 9 | N11: 46295 | Q11: =+J6 -> 46142 | R11: =-K6 -> 0 | S11: =+L6
B12: Start Date | C12: 46023 | I12: =I11+1 -> 10 | J12: 46326 | L12: =IF(K12>0,"CR","") | M12: =M11+1 -> 10 | N12: 46326 | Q12: =+J7 -> 46173 | R12: =-K7 -> 0 | S12: =+L7 | W12: LTV | X12: =C2/(Z10*0.94) -> #DIV/0!
B13: Maturity Date | C13: =EDATE(C12,C8) -> 46388 | I13: =I12+1 -> 11 | J13: 46356 | L13: =IF(K13>0,"CR","") | M13: =M12+1 -> 11 | N13: 46356 | Q13: =+J8 -> 46203 | R13: =-K8 -> 0 | S13: =+L8
I14: =I13+1 -> 12 | J14: 46387 | L14: =IF(K14>0,"CR","") | M14: =M13+1 -> 12 | N14: 46387 | Q14: =+J9 -> 46234 | R14: =-K9 -> 0 | S14: =+L9
I15: =I14+1 -> 13 | J15: 46418 | L15: =IF(K15>0,"CR","") | M15: =M14+1 -> 13 | N15: 46418 | Q15: =+J10 -> 46265 | R15: =-K10 -> 0 | S15: =+L10
I16: =I15+1 -> 14 | J16: 46446 | L16: =IF(K16>0,"CR","") | M16: =M15+1 -> 14 | N16: 46446 | Q16: =+J11 -> 46295 | R16: =-K11 -> 0 | S16: =+L11
I17: =I16+1 -> 15 | J17: 46477 | L17: =IF(K17>0,"CR","") | M17: =M16+1 -> 15 | N17: 46477 | Q17: =+J12 -> 46326 | R17: =-K12 -> 0 | S17: =+L12
I18: =I17+1 -> 16 | J18: 46507 | L18: =IF(K18>0,"CR","") | M18: =M17+1 -> 16 | N18: 46507 | Q18: =+J13 -> 46356 | R18: =-K13 -> 0 | S18: =+L13
I19: =I18+1 -> 17 | J19: 46538 | L19: =IF(K19>0,"CR","") | M19: =M18+1 -> 17 | N19: 46538 | Q19: =+J14 -> 46387 | R19: =-K14 -> 0 | S19: =+L14
I20: =I19+1 -> 18 | J20: 46568 | L20: =IF(K20>0,"CR","") | M20: =M19+1 -> 18 | N20: 46568 | Q20: =+J15 -> 46418 | R20: =-K15 -> 0 | S20: =+L15
I21: =I20+1 -> 19 | J21: 46599 | L21: =IF(K21>0,"CR","") | M21: =M20+1 -> 19 | N21: 46599 | Q21: =+J16 -> 46446 | R21: =-K16 -> 0 | S21: =+L16
I22: =I21+1 -> 20 | J22: 46630 | L22: =IF(K22>0,"CR","") | M22: =M21+1 -> 20 | N22: 46630 | Q22: =+J17 -> 46477 | R22: =-K17 -> 0 | S22: =+L17
I23: =I22+1 -> 21 | J23: 46660 | L23: =IF(K23>0,"CR","") | M23: =M22+1 -> 21 | N23: 46660 | Q23: =+J18 -> 46507 | R23: =-K18 -> 0 | S23: =+L18
I24: =I23+1 -> 22 | J24: 46691 | L24: =IF(K24>0,"CR","") | M24: =M23+1 -> 22 | N24: 46691 | Q24: =+J19 -> 46538 | R24: =-K19 -> 0 | S24: =+L19
I25: =I24+1 -> 23 | J25: 46721 | L25: =IF(K25>0,"CR","") | M25: =M24+1 -> 23 | N25: 46721 | Q25: =+J20 -> 46568 | R25: =-K20 -> 0 | S25: =+L20
I26: =I25+1 -> 24 | J26: 46752 | L26: =IF(K26>0,"CR","") | M26: =M25+1 -> 24 | N26: 46752 | Q26: =+J21 -> 46599 | R26: =-K21 -> 0 | S26: =+L21 | W26: Max Amount Out
K27: =C7-SUM(K3:K26) -> 0 | L27: check | Q27: =+J22 -> 46630 | R27: =-K22 -> 0 | S27: =+L22 | W27: =MAX(C29:C394) -> 217857.14
C28: Loan Drawn Balance | D28: CR Draw | E28: Paydown | F28: Interest | G28: IR Balance | H28: Payoff | Q28: =+J23 -> 46660 | R28: =-K23 -> 0 | S28: =+L23
B29: =C12 -> 46023 | C29: =C2-C7 -> 217857.14 | E29: =O3 -> 0 | F29: =+C29*$C$3/360 -> 66.56746 | G29: =+C$4-F29 -> 199933.43 | H29: =+C29+G29 -> 417790.58 | Q29: =+J24 -> 46691 | R29: =-K24 -> 0 | S29: =+L24
B30: =+B29+1 -> 46024 | C30: =+C29+D29+E29 -> 217857.14 | D30: =SUMIF($J$3:$J$26,B30,$K$3:$K$26) -> 0 | E30: =-SUMIF($N$3:$N$26,B30,$O$3:$O$26) -> 0 | F30: =+C30*$C$3/360 -> 66.56746 | G30: =+G29-F30 -> 199866.87 | H30: =+C30+G30 -> 417724.01 | Q30: =+J25 -> 46721 | R30: =-K25 -> 0 | S30: =+L25
B31: =+B30+1 -> 46025 | C31: =+C30+D30+E30 -> 217857.14 | D31: =SUMIF($J$3:$J$26,B31,$K$3:$K$26) -> 0 | E31: =-SUMIF($N$3:$N$26,B31,$O$3:$O$26) -> 0 | F31: =+C31*$C$3/360 -> 66.56746 | G31: =+G30-F31 -> 199800.3 | H31: =+C31+G31 -> 417657.44 | Q31: =+J26 -> 46752 | R31: =-K26 -> 0 | S31: =+L26
B32: =+B31+1 -> 46026 | C32: =+C31+D31+E31 -> 217857.14 | D32: =SUMIF($J$3:$J$26,B32,$K$3:$K$26) -> 0 | E32: =-SUMIF($N$3:$N$26,B32,$O$3:$O$26) -> 0 | F32: =+C32*$C$3/360 -> 66.56746 | G32: =+G31-F32 -> 199733.73 | H32: =+C32+G32 -> 417590.87 | Q32: =+N3 -> 46053 | R32: =+O3 -> 0 | T32: Paydowns
B33: =+B32+1 -> 46027 | C33: =+C32+D32+E32 -> 217857.14 | D33: =SUMIF($J$3:$J$26,B33,$K$3:$K$26) -> 0 | E33: =-SUMIF($N$3:$N$26,B33,$O$3:$O$26) -> 0 | F33: =+C33*$C$3/360 -> 66.56746 | G33: =+G32-F33 -> 199667.16 | H33: =+C33+G33 -> 417524.31 | Q33: =+N4 -> 46081 | R33: =+O4 -> 0
B34: =+B33+1 -> 46028 | C34: =+C33+D33+E33 -> 217857.14 | D34: =SUMIF($J$3:$J$26,B34,$K$3:$K$26) -> 0 | E34: =-SUMIF($N$3:$N$26,B34,$O$3:$O$26) -> 0 | F34: =+C34*$C$3/360 -> 66.56746 | G34: =+G33-F34 -> 199600.6 | H34: =+C34+G34 -> 417457.74 | Q34: =+N5 -> 46112 | R34: =+O5 -> 0
B35: =+B34+1 -> 46029 | C35: =+C34+D34+E34 -> 217857.14 | D35: =SUMIF($J$3:$J$26,B35,$K$3:$K$26) -> 0 | E35: =-SUMIF($N$3:$N$26,B35,$O$3:$O$26) -> 0 | F35: =+C35*$C$3/360 -> 66.56746 | G35: =+G34-F35 -> 199534.03 | H35: =+C35+G35 -> 417391.17 | Q35: =+N6 -> 46142 | R35: =+O6 -> 0
B36: =+B35+1 -> 46030 | C36: =+C35+D35+E35 -> 217857.14 | D36: =SUMIF($J$3:$J$26,B36,$K$3:$K$26) -> 0 | E36: =-SUMIF($N$3:$N$26,B36,$O$3:$O$26) -> 0 | F36: =+C36*$C$3/360 -> 66.56746 | G36: =+G35-F36 -> 199467.46 | H36: =+C36+G36 -> 417324.6 | Q36: =+N7 -> 46173 | R36: =+O7 -> 0
B37: =+B36+1 -> 46031 | C37: =+C36+D36+E36 -> 217857.14 | D37: =SUMIF($J$3:$J$26,B37,$K$3:$K$26) -> 0 | E37: =-SUMIF($N$3:$N$26,B37,$O$3:$O$26) -> 0 | F37: =+C37*$C$3/360 -> 66.56746 | G37: =+G36-F37 -> 199400.89 | H37: =+C37+G37 -> 417258.04 | Q37: =+N8 -> 46203 | R37: =+O8 -> 0
B38: =+B37+1 -> 46032 | C38: =+C37+D37+E37 -> 217857.14 | D38: =SUMIF($J$3:$J$26,B38,$K$3:$K$26) -> 0 | E38: =-SUMIF($N$3:$N$26,B38,$O$3:$O$26) -> 0 | F38: =+C38*$C$3/360 -> 66.56746 | G38: =+G37-F38 -> 199334.33 | H38: =+C38+G38 -> 417191.47 | Q38: =+N9 -> 46234 | R38: =+O9 -> 0
B39: =+B38+1 -> 46033 | C39: =+C38+D38+E38 -> 217857.14 | D39: =SUMIF($J$3:$J$26,B39,$K$3:$K$26) -> 0 | E39: =-SUMIF($N$3:$N$26,B39,$O$3:$O$26) -> 0 | F39: =+C39*$C$3/360 -> 66.56746 | G39: =+G38-F39 -> 199267.76 | H39: =+C39+G39 -> 417124.9 | Q39: =+N10 -> 46265 | R39: =+O10 -> 0
B40: =+B39+1 -> 46034 | C40: =+C39+D39+E39 -> 217857.14 | D40: =SUMIF($J$3:$J$26,B40,$K$3:$K$26) -> 0 | E40: =-SUMIF($N$3:$N$26,B40,$O$3:$O$26) -> 0 | F40: =+C40*$C$3/360 -> 66.56746 | G40: =+G39-F40 -> 199201.19 | H40: =+C40+G40 -> 417058.33 | Q40: =+N11 -> 46295 | R40: =+O11 -> 0
B41: =+B40+1 -> 46035 | C41: =+C40+D40+E40 -> 217857.14 | D41: =SUMIF($J$3:$J$26,B41,$K$3:$K$26) -> 0 | E41: =-SUMIF($N$3:$N$26,B41,$O$3:$O$26) -> 0 | F41: =+C41*$C$3/360 -> 66.56746 | G41: =+G40-F41 -> 199134.62 | H41: =+C41+G41 -> 416991.77 | Q41: =+N12 -> 46326 | R41: =+O12 -> 0
B42: =+B41+1 -> 46036 | C42: =+C41+D41+E41 -> 217857.14 | D42: =SUMIF($J$3:$J$26,B42,$K$3:$K$26) -> 0 | E42: =-SUMIF($N$3:$N$26,B42,$O$3:$O$26) -> 0 | F42: =+C42*$C$3/360 -> 66.56746 | G42: =+G41-F42 -> 199068.06 | H42: =+C42+G42 -> 416925.2 | Q42: =+N13 -> 46356 | R42: =+O13 -> 0
B43: =+B42+1 -> 46037 | C43: =+C42+D42+E42 -> 217857.14 | D43: =SUMIF($J$3:$J$26,B43,$K$3:$K$26) -> 0 | E43: =-SUMIF($N$3:$N$26,B43,$O$3:$O$26) -> 0 | F43: =+C43*$C$3/360 -> 66.56746 | G43: =+G42-F43 -> 199001.49 | H43: =+C43+G43 -> 416858.63 | Q43: =+N14 -> 46387 | R43: =+O14 -> 0
B44: =+B43+1 -> 46038 | C44: =+C43+D43+E43 -> 217857.14 | D44: =SUMIF($J$3:$J$26,B44,$K$3:$K$26) -> 0 | E44: =-SUMIF($N$3:$N$26,B44,$O$3:$O$26) -> 0 | F44: =+C44*$C$3/360 -> 66.56746 | G44: =+G43-F44 -> 198934.92 | H44: =+C44+G44 -> 416792.06 | Q44: =+N15 -> 46418 | R44: =+O15 -> 0
... B55: =+B54+1 -> 46049 | C55: =+C54+D54+E54 -> 217857.14 | D55: =SUMIF($J$3:$J$26,B55,$K$3:$K$26) -> 0 | E55: =-SUMIF($N$3:$N$26,B55,$O$3:$O$26) -> 0 | F55: =+C55*$C$3/360 -> 66.56746 | G55: =+G54-F55 -> 198202.68 | H55: =+C55+G55 -> 416059.82 | Q55: =+N26 -> 46752 | R55: =+O26 -> 0
B56: =+B55+1 -> 46050 | C56: =+C55+D55+E55 -> 217857.14 | D56: =SUMIF($J$3:$J$26,B56,$K$3:$K$26) -> 0 | E56: =-SUMIF($N$3:$N$26,B56,$O$3:$O$26) -> 0 | F56: =+C56*$C$3/360 -> 66.56746 | G56: =+G55-F56 -> 198136.11 | H56: =+C56+G56 -> 415993.25 | Q56: =+C13 -> 46388 | R56: =SUMIF(B:B,Q56,H:H) -> 393493.45 | S56: Payoff at Maturity
B57: =+B56+1 -> 46051 | C57: =+C56+D56+E56 -> 217857.14 | D57: =SUMIF($J$3:$J$26,B57,$K$3:$K$26) -> 0 | E57: =-SUMIF($N$3:$N$26,B57,$O$3:$O$26) -> 0 | F57: =+C57*$C$3/360 -> 66.56746 | G57: =+G56-F57 -> 198069.54 | H57: =+C57+G57 -> 415926.69
B58: =+B57+1 -> 46052 | C58: =+C57+D57+E57 -> 217857.14 | D58: =SUMIF($J$3:$J$26,B58,$K$3:$K$26) -> 0 | E58: =-SUMIF($N$3:$N$26,B58,$O$3:$O$26) -> 0 | F58: =+C58*$C$3/360 -> 66.56746 | G58: =+G57-F58 -> 198002.98 | H58: =+C58+G58 -> 415860.12
B59: =+B58+1 -> 46053 | C59: =+C58+D58+E58 -> 217857.14 | D59: =SUMIF($J$3:$J$26,B59,$K$3:$K$26) -> 0 | E59: =-SUMIF($N$3:$N$26,B59,$O$3:$O$26) -> 0 | F59: =+C59*$C$3/360 -> 66.56746 | G59: =+G58-F59 -> 197936.41 | H59: =+C59+G59 -> 415793.55
B60: =+B59+1 -> 46054 | C60: =+C59+D59+E59 -> 217857.14 | D60: =SUMIF($J$3:$J$26,B60,$K$3:$K$26) -> 0 | E60: =-SUMIF($N$3:$N$26,B60,$O$3:$O$26) -> 0 | F60: =+C60*$C$3/360 -> 66.56746 | G60: =+G59-F60 -> 197869.84 | H60: =+C60+G60 -> 415726.98
B61: =+B60+1 -> 46055 | C61: =+C60+D60+E60 -> 217857.14 | D61: =SUMIF($J$3:$J$26,B61,$K$3:$K$26) -> 0 | E61: =-SUMIF($N$3:$N$26,B61,$O$3:$O$26) -> 0 | F61: =+C61*$C$3/360 -> 66.56746 | G61: =+G60-F61 -> 197803.27 | H61: =+C61+G61 -> 415660.42
B62: =+B61+1 -> 46056 | C62: =+C61+D61+E61 -> 217857.14 | D62: =SUMIF($J$3:$J$26,B62,$K$3:$K$26) -> 0 | E62: =-SUMIF($N$3:$N$26,B62,$O$3:$O$26) -> 0 | F62: =+C62*$C$3/360 -> 66.56746 | G62: =+G61-F62 -> 197736.71 | H62: =+C62+G62 -> 415593.85
B63: =+B62+1 -> 46057 | C63: =+C62+D62+E62 -> 217857.14 | D63: =SUMIF($J$3:$J$26,B63,$K$3:$K$26) -> 0 | E63: =-SUMIF($N$3:$N$26,B63,$O$3:$O$26) -> 0 | F63: =+C63*$C$3/360 -> 66.56746 | G63: =+G62-F63 -> 197670.14 | H63: =+C63+G63 -> 415527.28
B64: =+B63+1 -> 46058 | C64: =+C63+D63+E63 -> 217857.14 | D64: =SUMIF($J$3:$J$26,B64,$K$3:$K$26) -> 0 | E64: =-SUMIF($N$3:$N$26,B64,$O$3:$O$26) -> 0 | F64: =+C64*$C$3/360 -> 66.56746 | G64: =+G63-F64 -> 197603.57 | H64: =+C64+G64 -> 415460.71
B65: =+B64+1 -> 46059 | C65: =+C64+D64+E64 -> 217857.14 | D65: =SUMIF($J$3:$J$26,B65,$K$3:$K$26) -> 0 | E65: =-SUMIF($N$3:$N$26,B65,$O$3:$O$26) -> 0 | F65: =+C65*$C$3/360 -> 66.56746 | G65: =+G64-F65 -> 197537 | H65: =+C65+G65 -> 415394.15
B66: =+B65+1 -> 46060 | C66: =+C65+D65+E65 -> 217857.14 | D66: =SUMIF($J$3:$J$26,B66,$K$3:$K$26) -> 0 | E66: =-SUMIF($N$3:$N$26,B66,$O$3:$O$26) -> 0 | F66: =+C66*$C$3/360 -> 66.56746 | G66: =+G65-F66 -> 197470.44 | H66: =+C66+G66 -> 415327.58
B67: =+B66+1 -> 46061 | C67: =+C66+D66+E66 -> 217857.14 | D67: =SUMIF($J$3:$J$26,B67,$K$3:$K$26) -> 0 | E67: =-SUMIF($N$3:$N$26,B67,$O$3:$O$26) -> 0 | F67: =+C67*$C$3/360 -> 66.56746 | G67: =+G66-F67 -> 197403.87 | H67: =+C67+G67 -> 415261.01
B68: =+B67+1 -> 46062 | C68: =+C67+D67+E67 -> 217857.14 | D68: =SUMIF($J$3:$J$26,B68,$K$3:$K$26) -> 0 | E68: =-SUMIF($N$3:$N$26,B68,$O$3:$O$26) -> 0 | F68: =+C68*$C$3/360 -> 66.56746 | G68: =+G67-F68 -> 197337.3 | H68: =+C68+G68 -> 415194.44
... B759: =+B758+1 -> 46753 | C759: =+C758+D758+E758 -> 217857.14 | D759: =SUMIF($J$3:$J$26,B759,$K$3:$K$26) -> 0 | E759: =-SUMIF($N$3:$N$26,B759,$O$3:$O$26) -> 0 | F759: =+C759*$C$3/360 -> 66.56746 | G759: =+G758-F759 -> 151339.19 | H759: =+C759+G759 -> 369196.33

Sheet Notes

Sheet Deal Tracker
C3: Intake Date | D3: Project Name | E3: Next Steps/To do | F3: Borrower/Ownership Entity | G3: Contact Name | H3: Location (City) | I3: Location (State) | J3: Address | K3: 1st or *2nd | L3: Proposed Net Loan Amount | M3: Gross Loan Amount | N3: Borrower Contribution | O3: Points | P3: Rate | Q3: Term | R3: Est. Funding Date | S3: Project Type | T3: Intended Loan Use | U3: Current Constr. Status | V3: Source of Deal | W3: EOI | X3: DD List Sent | Y3: LOI Issued Date | Z3: DD Money Received | AA3: Signed LOI Received Date | AB3: Board Approval | AC3: Site Visit Done | AD3: Communication Status | AE3: Additional Comments | AF3: *First Position Lender & General Terms
B4: Senior | C4: =TODAY() -> 46105 | D4: ='Deal Details'!C3 -> 0 | F4: ='Deal Details'!C15 -> 0 | G4: =IF('Deal Details'!C17 = "",'Deal Details'!C15,'Deal Details'!C17) -> 0 | H4: ='Deal Details'!C5 -> 0 | I4: ='Deal Details'!C4 -> 0 | J4: =IF('Deal Details'!C7="",'Deal Details'!C6,'Deal Details'!C7) -> 0 | K4: 1st | L4: ='Deal Details'!C28 -> 0 | M4: =L4*(O4/100)+((L4*P4)*(Q4/12))+L4 -> 0 | N4: ='Deal Details'!F22 -> 0 | O4: ='Deal Details'!C26 -> 0.03 | P4: ='Deal Details'!C25 -> 0.12 | Q4: ='Deal Details'!C27 -> 12 | R4: ='Deal Details'!C31 -> 46105 | S4: ='Deal Details'!C11 -> 0 | T4: ='Deal Details'!C13 -> 0 | U4: ='Deal Details'!C12 -> 0 | V4: ='Deal Details'!C17 -> 0
B5: Mezz | C5: =TODAY() -> 46105 | D5: ='Deal Details'!C3 -> 0 | F5: ='Deal Details'!C15 -> 0 | G5: =IF('Deal Details'!C17 = "",'Deal Details'!C15,'Deal Details'!C17) -> 0 | H5: ='Deal Details'!C5 -> 0 | I5: ='Deal Details'!C4 -> 0 | J5: =IF('Deal Details'!C7="",'Deal Details'!C6,'Deal Details'!C7) -> 0 | K5: 2nd | L5: ='Deal Details'!F21 -> $0 | M5: =L5*(O5/100)+((L5*P5)*(Q5/12))+L5 -> 0 | N5: ='Deal Details'!F22 -> 0 | O5: ='Deal Details'!C26 -> 0.03 | P5: ='Deal Details'!K34 -> 0.24 | Q5: ='Mezz Amort'!C10 -> 12 | R5: ='Deal Details'!C31 -> 46105 | S5: ='Deal Details'!C11 -> 0 | T5: ='Deal Details'!C13 -> 0 | U5: ='Deal Details'!C12 -> 0 | V5: ='Deal Details'!C17 -> 0
C6: Intake Date | D6: Project Name | E6: Next Steps/To do | F6: Borrower/Ownership Entity | G6: Contact Name | H6: Location (City) | I6: Location (State) | J6: Address | K6: 1st or *2nd | L6: Proposed Net Mezz Loan Amount | M6: Gross Loan Amount | N6: Borrower Contribution | O6: Points | P6: Rate | Q6: Term | R6: Est. Funding Date | S6: Project Type | T6: Intended Loan Use | U6: Current Constr. Status | V6: Source of Deal | W6: EOI | X6: DD List Sent | Y6: LOI Issued Date | Z6: DD Money Received | AA6: Signed LOI Received Date | AB6: Board Approval | AC6: Site Visit Done | AD6: Communication Status | AE6: Additional Comments | AF6: *First Position Lender & General Terms

Sheet Visuals

Sheet Data
B1: Property Data Per Unit
B2: Avg Price
B4: Avg SF
B6: Avg Price/SF
B8: Avg Acre | C8: ='Deal Details'!C9/'Deal Details'!C10 -> #DIV/0!
B10: Avg Price/Acre | C10: =C2/C8 -> #DIV/0!
B12: Est. % Horizontal | E12: Insert Comp Sales Tables Below This Line

Sheet Valuation
A1: Property Mix | B1: Value | C1: Lots | D1: Total | E1: As-Is | K1: Townhomes | Q1: Townhomes
D2: =C2*B2 -> 0 | K2: Comp Sales | N2: Reduce by selling price | Q2: Comp Home Sales | R2: =R3/0.3 -> 516666.67
D3: =C3*B3 -> 0 | K3: Residual Lot Value | L3: =M3*L2 -> 0 | M3: 0.23 | N3: 23-25% | Q3: Residual Lot Value | R3: =R7-R4-R6 -> 155000
D4: =C4*B4 -> 0 | K4: Costs to Finish Lot | L4: -35000 | Q4: Costs to Finish Lot | R4: =L4 -> -35000
D5: =C5*B5 -> 0
C6: =SUM(C2:C5) -> 0 | D6: =SUM(D2:D5) -> 0 | K6: EI | L6: =SUM(L3:L4)*-M6 -> 7000 | M6: 0.2 | N6: 15-25% | Q6: EI | R6: =-R7*0.2 -> -20000
K7: Papered Lot | L7: =SUM(L3:L6) -> -28000 | Q7: Papered Lot | R7: =R10-R8-R9 -> 100000
D8: =D6/C6 -> #DIV/0! | K8: EI | L8: =IFERROR(-M8*(L7+L9),"") -> 25600 | M8: 0.2 | N8: 15-25% | Q8: EI | R8: =-R10*0.2 -> 0
K9: Engineering/Surveys | L9: =-100000 -> -100000 | N9: 100k (divide by # lots) | Q9: Engineering/Surveys | R9: =L9 -> -100000
A10: Town Home Value | B10: =B11*Data!C4 -> 0 | K10: Land | L10: =SUM(L7:L9) -> -102400 | Q10: Land
A11: SF
K12: Single Family | Q12: Single Family
K13: Comp Sales | L13: =ROUNDDOWN(B14,-3) -> 0 | N13: Reduce by selling price | Q13: Comp Home Sales | R13: =R14/0.3 -> 600000
A14: Single Family Value | B14: =B15*Data!C4 -> 0 | K14: Residual Lot Value | L14: =M14*L13 -> 0 | M14: 0.28 | N14: 28-32% | Q14: Residual Lot Value | R14: =R17-R15-R16 -> 180000
A15: SF | K15: Costs to Finish Lot | L15: =-'Deal Details'!I22 -> 0 | Q15: Costs to Finish Lot | R15: =L15 -> 0
K16: EI | L16: =SUM(L14:L15)*-M16 -> 0 | M16: 0.2 | N16: 15-25% | Q16: EI | R16: =-R17*0.2 -> -30000
K17: Papered Lot | L17: =SUM(L14:L16) -> 0 | Q17: Papered Lot | R17: =R20-R18-R19 -> 150000
A18: Multifamily Value | B18: =L36 | K18: EI | L18: =IFERROR(-M18*(L17+L19),"") -> 30000 | M18: 0.2 | N18: 15-25% | Q18: EI | R18: =-R20*0.2 -> 0
A19: Units | B19: =M28 -> 0 | K19: Engineering/Surveys | L19: =-150000 -> -150000 | N19: 150k (divide by # lots) | Q19: Engineering/Surveys | R19: =L19 -> -150000
K20: Land | L20: =SUM(L17:L19) -> -120000 | Q20: Land
K22: Multifamily
K23: Unit Type | L23: SF | M23: Units | N23: Rent/SF | O23: Gross Rents | P23: Rent/Unit
K24: Studio | N24: =IFERROR(AVERAGEIFS(Data!#REF!,Data!#REF!,Valuation!K24)*L24,"") | O24: =IFERROR(P24*M24*12,"") -> 0 | P24: 0 | R24: Guidelines | U24: Types of projects
K25: 1 Bed | N25: =IFERROR(P25/L25,"") | O25: =IFERROR(P25*M25*12,"") -> 0 | P25: 0 | R25: Operating Expenses | S25: 0.3 | U25: Raw Land
K26: 2 Bed | N26: =IFERROR(P26/L26,"") | O26: =IFERROR(P26*M26*12,"") -> 0 | P26: 0 | R26: Entrepreneurial Incentive | S26: 0.2 | U26: Entitled
K27: 3 Bed | N27: =IFERROR(P27/L27,"") | O27: =IFERROR(P27*M27*12,"") -> 0 | P27: 0 | R27: Cost to Finish a lot | S27: 50000 | U27: Horizontal
L28: =IFERROR(AVERAGE(L24:L27),"") | M28: =SUM(M24:M27) -> 0 | N28: =IFERROR(AVERAGEIF(N24:N27,">0"),0) -> 0 | O28: =SUM(O24:O27) -> 0 | P28: =SUM(P24:P27) -> 0 | R28: Residual Value of a finished lot | S28: 28-32% | U28: Vertical
K29: Cap Rate | R29: Builder's Margin | S29: 0.1 | U29: Built
K30: Gross Rents | L30: =O28*(1-M30) -> 0 | M30: 0.05 | N30: Vacancy | R30: Cap Rates | S30: *******
K31: Other Income | L31: =M31*L30 -> 0 | M31: 0.1 | N31: Parking, fees, etc.
K32: Gross Profit | L32: =SUM(L30:L31) -> 0 | R32: Affordability Guidelines (as percent of median income)
L33: =L32*M34 -> 0
K34: NOI | L34: =L32-L33 -> 0 | M34: 0.35 | N34: Operating Expense
K36: Value at Cap | L36: =IFERROR(L34/L29,"")
K38: Value/Unit | L38: =IFERROR(L36/'Deal Details'!C10,"")

Sheet ProForma
B1: ='Deal Details'!C3 -> 0
B3: Summary and Exit Strategy | G3: Notes
B14: Parties Involved | C14: Name/Company | G14: Project Information
B15: Sponsor | C15: ='Deal Details'!C15 -> 0 | G15: Project Number
B16: Seller | G16: Project Name
B17: 1st Position Lender | C17: ='Deal Details'!C30 -> MBC | G17: Project Type | H17: ='Deal Details'!C13 -> 0
B18: Deal Broker | G18: Closing Date
B19: Builder/Developer | C19: ='Deal Details'!C16 -> 0 | G19: Address
B20: Guarantor(s) | G20: City/State/Zip | H20: ='Deal Details'!C6 -> 0
G21: County | H21: ='Deal Details'!C8 -> 0
G22: Jurisdiction
B25: Project P&L - without MB Investment | G25: P&L - With MB Investment
B26: Revenue | C26: Amount | D26: Per Unit | E26: Source | G26: Revenue | H26: Amount | I26: Per Unit | J26: Source
B27: Number of Units/Lots | C27: ='Deal Details'!C10 -> 0 | G27: Number of Units/Lots | H27: =C27 -> 0
B28: Total Exit Price/Value | C28: =C27*'Deal Details'!C36 -> 0 | D28: ='Deal Details'!C36 -> 0 | G28: Total Exit Price/Value | H28: =C28 -> 0 | I28: =IFERROR(H28/$H$27,"")
B29: Gross Income from Rents | C29: 0 | D29: 0 | G29: Gross Income from Rents | H29: =C29 -> 0 | I29: =IFERROR(H29/$H$27,"")
B30: Total Revenue | C30: =SUM(C28:C29) -> 0 | D30: 0 | G30: Total Revenue | H30: =SUM(H28:H29) -> 0 | I30: =IFERROR(H30/$H$27,"")
B32: Project Costs | C32: Amount | D32: Per Unit | G32: Project Costs | H32: Amount | I32: Per Unit
B33: Acquisition | C33: ='Deal Details'!H20 -> 0 | D33: =IFERROR(C33/$C$27,"") | G33: Acquisition | H33: =C33 -> 0 | I33: =IFERROR(H33/$H$27,"")
B34: Land Development | C34: ='Deal Details'!H22 -> 0 | D34: =IFERROR(C34/$C$27,"") | G34: Land Development | H34: =C34 -> 0 | I34: =IFERROR(H34/$H$27,"")
B35: Soft Costs/city fees/Taxes | C35: ='Deal Details'!H21 -> 0 | D35: =IFERROR(C35/$C$27,"") | G35: =B35 -> Soft Costs/city fees/Taxes | H35: =C35 -> 0 | I35: =IFERROR(H35/$H$27,"")
B36: 1st Position Lender Costs | C36: =C64 -> 0 | D36: =IFERROR(C36/$C$27,"") | G36: 1st Position Lender Costs | H36: =C36 -> 0 | I36: =IFERROR(H36/$H$27,"")
B37: Sales and Closing | C37: =C28*E37 -> 0 | D37: =IFERROR(C37/$C$27,"") | E37: ='Deal Details'!C38 -> 0 | G37: WB Cost of Capital | H37: =IFERROR(H67,0) -> 9490.1625 | I37: =IFERROR(H37/$H$27,"")
B38: Acq. + Dev. | C38: =SUM(C33:C35) -> 0 | D38: =IFERROR(C38/$C$27,"") | G38: Sales and Closing | H38: =C37 -> 0 | I38: =IFERROR(H38/$H$27,"") | J38: =E37 -> 0
B39: Acq. + Dev. + Con. | C39: =SUM(C33:C35) -> 0 | D39: =IFERROR(C39/$C$27,"") | G39: Acq. + Dev. | H39: =SUM(H33:H34) -> 0 | I39: =IFERROR(H39/$H$27,"")
B40: Acq. + Dev. + Con. + Cost of Debt | C40: =SUM(C33:C36) -> 0 | D40: =IFERROR(C40/$C$27,"") | G40: Acq. + Dev. + Con. | H40: =C39 -> 0 | I40: =IFERROR(H40/$H$27,0) -> 0
B41: Total Costs | C41: =SUM(C33:C37) -> 0 | D41: =IFERROR(C41/$C$27,"") | G41: Acq. + Dev. + Con. + Cost of Debt | H41: =SUM(H33:H37) -> 9490.1625 | I41: =IFERROR(H41/$H$27,0) -> 0
G42: Total Costs | H42: =SUM(H33:H38) -> 9490.1625 | I42: =IFERROR(H42/$H$27,0) -> 0
B43: Profit | C43: Amount | D43: Per Unit
B44: Total Revenue | C44: =C30 -> 0 | D44: =IFERROR(C44/$C$27,"") | G44: Profit | H44: Amount | I44: Per Unit
B45: Total Cost | C45: =C41 -> 0 | D45: =IFERROR(C45/$C$27,"") | G45: Total Revenue | H45: =H30 -> 0 | I45: =IFERROR(H45/$H$27,"")
B46: Total Profit | C46: =C44-C45 -> 0 | D46: =IFERROR(D44-D45,"") | G46: Total Cost | H46: =H42 -> 9490.1625 | I46: =IFERROR(H46/$H$27,"")
B47: Margin/Unit | C47: =IFERROR(C46/C44,0) -> 0 | G47: Total Profit | H47: =H45-H46 -> -9490.1625 | I47: =IFERROR(I45-I46,"")
G48: Margin/Unit | H48: =IFERROR(H47/H45,"")
B50: 1st Position Lender | C50: Terms | D50: Amount | G50: Mesa Bridge | H50: Terms | I50: Amount
B51: Total Cost/Total Value | C51: =C28 -> 0 | G51: Project Cash Need | H51: =C65
B52: Loan Amount | C52: ='Deal Details'!C29 -> 0 | G52: Annualized ROI | H52: 0.3
B53: Loan Maturity (months) | C53: ='Deal Details'!C27 -> 12 | G53: Sponsor Cash | H53: ='Deal Details'!F22 -> 0
B54: LTC/LTV | C54: =IFERROR(C52/C51,"") | D54: =IFERROR(C54*C51,"") | G54: Adusted Cash Need | H54: =IFERROR(C65-H53,"$0") -> $0
B55: Points | C55: ='Deal Details'!C26 -> 0.03 | D55: =IFERROR(C55*D54,"") | G55: Loan Maturity (months) | H55: ='Deal Details'!C27 -> 12 | I55: Days of loan | J55: =H55*30 -> 360
B56: Broker Points | C56: ='Deal Details'!C20 -> 0.01 | D56: =IFERROR(D54*C56,"") | G56: Preferred Return | H56: 0.24 | I56: =IFERROR('Mezz Amort'!I10*((1+(H56/360))^(360*(J55/360))-1),"") -> 9490.1625 | J56: compounding
B57: Interest | C57: ='Deal Details'!C25 -> 0.12 | D57: =IFERROR((D54*C57)*(C53/12),"") | E57: =IFERROR(D57/12,"") | G57: WB Points | H57: 0.03 | I57: =IFERROR((H54/(1-H57))-H54,"") -> 0
B58: Additional Fees | C58: 0 | D58: Closing Fees | G58: Broker Points | H58: 0 | I58: =IFERROR(H54*H58,"") -> 0
D59: =SUM('Deal Details'!C22:C24) -> 21000 | G59: Exit Fee (% of Investment) | H59: 0 | I59: =IFERROR('Mezz Amort'!I10*((1+(H59/360))^(360*(J55/360))-1),"") -> 0 | J59: compounding
B60: Points/Fees | C60: =IFERROR(D60+D59+D56,"") | D60: =D55 | G60: Monthly Escalator | H60: 0 | I60: =IFERROR((H64*H52)/12,0) -> 0
B61: Interest | C61: =D61 | D61: =D57 | G61: % of profits | H61: =IFERROR((I56+I59)/C46,"")
B62: Loan Amount | C62: =C52 -> 0 | G62: Legal and Processing Fee | H62: 3000
B63: Net Available at Closing | C63: =IFERROR(C62-C60-C61,"") | D63: =IFERROR(C63/$C$33,"") | E63: per unit/lot | G63: Closing Fees | H63: 1500
B64: Total Debt Finance Costs | C64: =SUM(D60:D61) -> 0 | D64: =IFERROR(C64/$C$33,"") | E64: per unit/lot | G64: Total Investment (principal) | H64: =H54 -> $0
B65: Equity Needed | C65: =IFERROR(C39-C63,"") | D65: =IFERROR(C65/$C$33,"") | E65: per unit/lot | G65: CLTV (loan principal) | H65: =IFERROR((H54+C62)/(C30-C37),"") | I65: =IFERROR(IF(H65>0.8, ((H65-0.8)*C30), 0),"") | J65: short fall
G66: CLTV (after all cost of capital) | H66: =IFERROR((H68+C62)/(C30-C37),"")
G67: Return | H67: =IFERROR(I56+I59+I57,"") -> 9490.1625
G68: Total Return | H68: =SUM(H67,H64) -> 9490.1625
G69: ROI | H69: =IFERROR(H67/$H$64,"")
G70: Annualized ROI | H70: =IFERROR(H69/(H55/12),"")

Sheet Senior Amort
B2: ='Deal Details'!C3 -> 0 | D2: Senior Lender | E2: Cambia Default Date | F2: Current LTV | G2: Senior Default Date | H2: Senior Default rate | I2: Cambia Default Date | J2: Default LTV | K2: 3 Month Default LTV | L2: 6 Month Default LTV | M2: 9 Month Default LTV
D3: ='Deal Details'!C30 -> MBC | E3: =C13 -> 46470 | F3: =(L9+F12)/D12 -> #DIV/0! | G3: =C28 -> 46470 | H3: 0.24 | I3: =C13 -> 46470 | J3: =G13 -> #DIV/0! | K3: =G14 -> #DIV/0! | L3: =G15 -> #DIV/0! | M3: =G16 -> #DIV/0!
F4: =(F12+E12+H22)/D12 -> #REF!
B5: Loan 1 | H5: Senior Loan Balance | I5: Cambia Balance | J5: Project Value
B6: Today | C6: Maturity | D6: Maturity + 90 | E6: Maturity + 180 | F6: Maturity + 270 | H6: =E12 -> 0 | I6: =F12 -> 29400 | J6: =D12 -> 0
B7: ='Mezz Amort'!Q36 -> 46105 | C7: ='Mezz Amort'!Q50 -> 46470 | D7: ='Mezz Amort'!R50 -> 46560 | E7: ='Mezz Amort'!S50 -> 46650 | F7: ='Mezz Amort'!T50 -> 46740 | G7: ='Mezz Amort'!U50 -> 23.333333 | K7: ="Senior Loan Information "&'Deal Details'!C3 -> Senior Loan Information | M7: Notes
B8: ='Mezz Amort'!P51 -> 29400 | C8: ='Mezz Amort'!Q51 -> 35140.234 | D8: ='Mezz Amort'!R51 -> 37312.438 | E8: ='Mezz Amort'!S51 -> 39618.919 | F8: ='Mezz Amort'!T51 -> 42067.975 | G8: ='Mezz Amort'!U51 -> 0 | K8: Institution | L8: ='Deal Details'!C16 -> 0 | M8: This note is not yet finalized. Assumptions were made on default interest rates.
K9: Total Amount | L9: =ProForma!C52 -> 0
K10: Rate | L10: =ProForma!C57 -> 0.12
D11: Value of total Collateral | E11: Senior Loan Amount | F11: Cambia Balance | G11: LTV | K11: Points | L11: ='Deal Details'!C26 -> 0.03
B12: Today | C12: =B7 -> 46105 | D12: =ProForma!$C$28-ProForma!$C$37 -> 0 | E12: =$L$9 -> 0 | F12: =B8 -> 29400 | G12: =(F12+E12)/D12 -> #DIV/0! | I12: 0.05 | K12: Origination Fee | L12: =L11*L9 -> 0
B13: Default | C13: =C7 -> 46470 | D13: =D12 -> 0 | E13: =$L$9 -> 0 | F13: =C8 -> 35140.234 | G13: =(F13+E13)/D13 -> #DIV/0! | I13: 0.11 | K13: Reserves | L13: =C22+SUM(P32:P42) -> 0
B14: Default +90 | C14: =D7 -> 46560 | D14: =D12 -> 0 | E14: =E13*1.05 -> 0 | F14: =D8 -> 37312.438 | G14: =(F14+E14)/D14 -> #DIV/0! | K14: Orig. Maturity Date | L14: =C28 -> 46470
B15: Default +180 | C15: =E7 -> 46650 | D15: =D12 -> 0 | E15: =E14*1.05 -> 0 | F15: =E8 -> 39618.919 | G15: =(F15+E15)/D15 -> #DIV/0! | I15: =SUM(I12:I14) -> 0.16 | K15: Extended Maturity | L15: NA
B16: Default +270 | C16: =F7 -> 46740 | D16: =D12 -> 0 | E16: =E15*1.05 -> 0 | F16: =F8 -> 42067.975 | G16: =(F16+E16)/D16 -> #DIV/0! | K16: Default Interest | L16: 0.24
K17: Extension Fees | M17: Current LTV
K18: Balance | L18: =H6 -> 0 | M18: =F3 -> #DIV/0!
A19: =CONCATENATE(A20," ","Senior") -> 0 Senior | K19: Left to Draw | L19: =H22 -> #REF!
A20: ='Deal Details'!C3 -> 0 | E20: Lots | F20: 19 | G20: Minimum Interest | H20: 0.7 | K20: Valuation | L20: =J6 -> 0
A21: Loan | C21: =L9 -> 0 | E21: Basis Per Lot | F21: =C23/F20 -> #VALUE! | G21: Minimum Balance | H21: =C21*H20 -> 0 | K21: Valuation Date | L21: 43125 | M21: Total Debt + Liabilities
A22: Construction holdback | C22: 0 | E22: Payoff Acceleration | F22: 1.2 | G22: Remaining Construction | H22: =C22-SUM(L34:L58) -> #REF! | K22: Method | L22: Comparable Sales | M22: =L18+B8 -> 29400
A23: dispersed at closing | C23: =C21-F24-C22-L12 -> #VALUE! | D23: 0 | E23: Lot Payoff Price | F23: =F21*F22 -> #VALUE! | G23: Construction Spent | H23: =C22-H22 -> #REF! | K23: Cambia Cost/Day | L23: =G7 -> 23.333333 | M23: Left to Draw
A24: Points | C24: ='Deal Details'!C26 -> 0.03 | E24: Interest Reserve | F24: =ProForma!C61 | K24: Senior Cost/Day | L24: =VLOOKUP(B7,A33:H630,4,FALSE) -> 0 | M24: =H22 -> #REF!
A25: Interest | C25: ='Deal Details'!C25 -> 0.12 | K25: Finance cost/Day | L25: =VLOOKUP(B7,A33:H630,4,FALSE) -> 0 | M25: Senior Note
A26: Loan start date | C26: ='Mezz Amort'!C8 -> 46105 | E26: Days of loan | F26: =C28-C26 -> 365
A27: Loan Term (Months) | C27: ='Deal Details'!C27 -> 12
A28: Loan Maturity | C28: =C26+365 -> 46470 | K28: Running Balance | O28: Draws
A29: Loan Exit | K29: Date | L29: Amount | M29: Type | O29: Date | P29: Amount | Q29: # Lots
K30: =K31 -> 46105 | L30: =-C21 -> 0 | M30: Principal | O30: =A33 -> 46105 | P30: =L30 -> 0 | Q30: Loan Principle
K31: =K32 -> 46105 | L31: =ProForma!D60 | M31: Points | O31: =A33 -> 46105 | P31: =D23 -> 0 | Q31: Points
A32: Period | C32: Balance | D32: Interest | E32: Interest Reserve Balance | F32: Sum of Interest | G32: Payment | H32: Balance | I32: Payoff | K32: =K33 -> 46105 | L32: =IF('Deal Details'!#REF!="Yes",F24,0) -> #REF! | M32: Reserve | Q32: insulation/rock
A33: =C26 -> 46105 | B33: 1 | C33: =C21 -> 0 | D33: =IF(C33>$H$21,C33*($C$25/360),$H$21*($C$25/360)) -> 0 | E33: =P53-D33 -> #VALUE! | F33: =SUM($D$33:D33) -> 0 | H33: =IF(E33>0,C33+G33,IF(E33<0,C33+G33+D33,C33+D33+G33)) -> #VALUE! | I33: =(C33+D33-E33) -> #VALUE! | K33: =C26 -> 46105 | Q33: cabinets
A34: =A33+1 -> 46106 | B34: 2 | C34: =H33 -> #VALUE! | D34: =IF(C34>$H$21,C34*($C$25/360),$H$21*($C$25/360)) -> #VALUE! | E34: =IF(E33>0,E33-D34,0) -> #VALUE! | F34: =SUM($D$33:D34) -> #VALUE! | G34: =IFERROR(-VLOOKUP(A34,$K$30:$M$36,2,FALSE),0) -> 0 | H34: =IF(E34>0,C34+G34,IF(E34<0,C34+G34+D34-E33,C34+D34+G34)) -> #VALUE! | I34: =(C34+D34-E34) -> #VALUE! | J34: 1 | K34: =EDATE(K33,1) -> 46136 | L34: {=_xlfn.IFS(J34>C$27,0,'Deal Details'!#REF!="Yes",0/$C$27,'Deal Details'!#REF!="No",$F$24/C$27)} -> #REF! | Q34: drywall/fireplace
A35: =A34+1 -> 46107 | B35: 3 | C35: =H34 -> #VALUE! | D35: =IF(C35>$H$21,C35*($C$25/360),$H$21*($C$25/360)) -> #VALUE! | E35: =IF(E34>0,E34-D35,0) -> #VALUE! | F35: =SUM($D$33:D35) -> #VALUE! | G35: =IFERROR(-VLOOKUP(A35,$K$30:$M$36,2,FALSE),0) -> 0 | H35: =IF(E35>0,C35+G35,IF(E35<0,C35+G35+D35-E34,C35+D35+G35)) -> #VALUE! | I35: =(C35+D35-E35) -> #VALUE! | J35: 2 | K35: =EDATE(K34,1) -> 46166 | L35: {=_xlfn.IFS(J35>C$27,0,'Deal Details'!#REF!="Yes",0/$C$27,'Deal Details'!#REF!="No",$F$24/C$27)} -> #REF!
A36: =A35+1 -> 46108 | B36: 4 | C36: =H35 -> #VALUE! | D36: =IF(C36>$H$21,C36*($C$25/360),$H$21*($C$25/360)) -> #VALUE! | E36: =IF(E35>0,E35-D36,0) -> #VALUE! | F36: =SUM($D$33:D36) -> #VALUE! | G36: =IFERROR(-VLOOKUP(A36,$K$30:$M$36,2,FALSE),0) -> 0 | H36: =IF(E36>0,C36+G36,IF(E36<0,C36+G36+D36-E35,C36+D36+G36)) -> #VALUE! | I36: =(C36+D36-E36) -> #VALUE! | J36: 3 | K36: =EDATE(K35,1) -> 46197 | L36: {=_xlfn.IFS(J36>C$27,0,'Deal Details'!#REF!="Yes",0/$C$27,'Deal Details'!#REF!="No",$F$24/C$27)} -> #REF!
A37: =A36+1 -> 46109 | B37: 5 | C37: =H36 -> #VALUE! | D37: =IF(C37>$H$21,C37*($C$25/360),$H$21*($C$25/360)) -> #VALUE! | E37: =IF(E36>0,E36-D37,0) -> #VALUE! | F37: =SUM($D$33:D37) -> #VALUE! | G37: =IFERROR(-VLOOKUP(A37,$K$30:$M$36,2,FALSE),0) -> 0 | H37: =IF(E37>0,C37+G37,IF(E37<0,C37+G37+D37-E36,C37+D37+G37)) -> #VALUE! | I37: =(C37+D37-E37) -> #VALUE! | J37: 4 | K37: =EDATE(K36,1) -> 46227 | L37: {=_xlfn.IFS(J37>C$27,0,'Deal Details'!#REF!="Yes",0/$C$27,'Deal Details'!#REF!="No",$F$24/C$27)} -> #REF!
A38: =A37+1 -> 46110 | B38: 6 | C38: =H37 -> #VALUE! | D38: =IF(C38>$H$21,C38*($C$25/360),$H$21*($C$25/360)) -> #VALUE! | E38: =IF(E37>0,E37-D38,0) -> #VALUE! | F38: =SUM($D$33:D38) -> #VALUE! | G38: =IFERROR(-VLOOKUP(A38,$K$30:$M$36,2,FALSE),0) -> 0 | H38: =IF(E38>0,C38+G38,IF(E38<0,C38+G38+D38-E37,C38+D38+G38)) -> #VALUE! | I38: =(C38+D38-E38) -> #VALUE! | J38: 5 | K38: =EDATE(K37,1) -> 46258 | L38: {=_xlfn.IFS(J38>C$27,0,'Deal Details'!#REF!="Yes",0/$C$27,'Deal Details'!#REF!="No",$F$24/C$27)} -> #REF!
A39: =A38+1 -> 46111 | B39: 7 | C39: =H38 -> #VALUE! | D39: =IF(C39>$H$21,C39*($C$25/360),$H$21*($C$25/360)) -> #VALUE! | E39: =IF(E38>0,E38-D39,0) -> #VALUE! | F39: =SUM($D$33:D39) -> #VALUE! | G39: =IFERROR(-VLOOKUP(A39,$K$30:$M$36,2,FALSE),0) -> 0 | H39: =IF(E39>0,C39+G39,IF(E39<0,C39+G39+D39-E38,C39+D39+G39)) -> #VALUE! | I39: =(C39+D39-E39) -> #VALUE! | J39: 6 | K39: =EDATE(K38,1) -> 46289 | L39: {=_xlfn.IFS(J39>C$27,0,'Deal Details'!#REF!="Yes",0/$C$27,'Deal Details'!#REF!="No",$F$24/C$27)} -> #REF!
A40: =A39+1 -> 46112 | B40: 8 | C40: =H39 -> #VALUE! | D40: =IF(C40>$H$21,C40*($C$25/360),$H$21*($C$25/360)) -> #VALUE! | E40: =IF(E39>0,E39-D40,0) -> #VALUE! | F40: =SUM($D$33:D40) -> #VALUE! | G40: =IFERROR(-VLOOKUP(A40,$K$30:$M$36,2,FALSE),0) -> 0 | H40: =IF(E40>0,C40+G40,IF(E40<0,C40+G40+D40-E39,C40+D40+G40)) -> #VALUE! | I40: =(C40+D40-E40) -> #VALUE! | J40: 7 | K40: =EDATE(K39,1) -> 46319 | L40: {=_xlfn.IFS(J40>C$27,0,'Deal Details'!#REF!="Yes",0/$C$27,'Deal Details'!#REF!="No",$F$24/C$27)} -> #REF!
A41: =A40+1 -> 46113 | B41: 9 | C41: =H40 -> #VALUE! | D41: =IF(C41>$H$21,C41*($C$25/360),$H$21*($C$25/360)) -> #VALUE! | E41: =IF(E40>0,E40-D41,0) -> #VALUE! | F41: =SUM($D$33:D41) -> #VALUE! | G41: =IFERROR(-VLOOKUP(A41,$K$30:$M$36,2,FALSE),0) -> 0 | H41: =IF(E41>0,C41+G41,IF(E41<0,C41+G41+D41-E40,C41+D41+G41)) -> #VALUE! | I41: =(C41+D41-E41) -> #VALUE! | J41: 8 | K41: =EDATE(K40,1) -> 46350 | L41: {=_xlfn.IFS(J41>C$27,0,'Deal Details'!#REF!="Yes",0/$C$27,'Deal Details'!#REF!="No",$F$24/C$27)} -> #REF!
A42: =A41+1 -> 46114 | B42: 10 | C42: =H41 -> #VALUE! | D42: =IF(C42>$H$21,C42*($C$25/360),$H$21*($C$25/360)) -> #VALUE! | E42: =IF(E41>0,E41-D42,0) -> #VALUE! | F42: =SUM($D$33:D42) -> #VALUE! | G42: =IFERROR(-VLOOKUP(A42,$K$30:$M$36,2,FALSE),0) -> 0 | H42: =IF(E42>0,C42+G42,IF(E42<0,C42+G42+D42-E41,C42+D42+G42)) -> #VALUE! | I42: =(C42+D42-E42) -> #VALUE! | J42: 9 | K42: =EDATE(K41,1) -> 46380 | L42: {=_xlfn.IFS(J42>C$27,0,'Deal Details'!#REF!="Yes",0/$C$27,'Deal Details'!#REF!="No",$F$24/C$27)} -> #REF!
A43: =A42+1 -> 46115 | B43: 11 | C43: =H42 -> #VALUE! | D43: =IF(C43>$H$21,C43*($C$25/360),$H$21*($C$25/360)) -> #VALUE! | E43: =IF(E42>0,E42-D43,0) -> #VALUE! | F43: =SUM($D$33:D43) -> #VALUE! | G43: =IFERROR(-VLOOKUP(A43,$K$30:$M$36,2,FALSE),0) -> 0 | H43: =IF(E43>0,C43+G43,IF(E43<0,C43+G43+D43-E42,C43+D43+G43)) -> #VALUE! | I43: =(C43+D43-E43) -> #VALUE! | J43: 10 | K43: =EDATE(K42,1) -> 46411 | L43: {=_xlfn.IFS(J43>C$27,0,'Deal Details'!#REF!="Yes",0/$C$27,'Deal Details'!#REF!="No",$F$24/C$27)} -> #REF! | O43: =P50 -> 0 | P43: =SUM(P30:P42) -> 0
A44: =A43+1 -> 46116 | B44: 12 | C44: =H43 -> #VALUE! | D44: =IF(C44>$H$21,C44*($C$25/360),$H$21*($C$25/360)) -> #VALUE! | E44: =IF(E43>0,E43-D44,0) -> #VALUE! | F44: =SUM($D$33:D44) -> #VALUE! | G44: =IFERROR(-VLOOKUP(A44,$K$30:$M$36,2,FALSE),0) -> 0 | H44: =IF(E44>0,C44+G44,IF(E44<0,C44+G44+D44-E43,C44+D44+G44)) -> #VALUE! | I44: =(C44+D44-E44) -> #VALUE! | J44: 11 | K44: =EDATE(K43,1) -> 46442 | L44: {=_xlfn.IFS(J44>C$27,0,'Deal Details'!#REF!="Yes",0/$C$27,'Deal Details'!#REF!="No",$F$24/C$27)} -> #REF! | O44: IRR if paid off today | P44: =XIRR(P30:P43,O30:O43) -> #NUM!
A45: =A44+1 -> 46117 | B45: 13 | C45: =H44 -> #VALUE! | D45: =IF(C45>$H$21,C45*($C$25/360),$H$21*($C$25/360)) -> #VALUE! | E45: =IF(E44>0,E44-D45,0) -> #VALUE! | F45: =SUM($D$33:D45) -> #VALUE! | G45: =IFERROR(-VLOOKUP(A45,$K$30:$M$36,2,FALSE),0) -> 0 | H45: =IF(E45>0,C45+G45,IF(E45<0,C45+G45+D45-E44,C45+D45+G45)) -> #VALUE! | I45: =(C45+D45-E45) -> #VALUE! | J45: 12 | K45: =EDATE(K44,1) -> 46470 | L45: {=_xlfn.IFS(J45>C$27,0,'Deal Details'!#REF!="Yes",0/$C$27,'Deal Details'!#REF!="No",$F$24/C$27)} -> #REF!
A46: =A45+1 -> 46118 | B46: 14 | C46: =H45 -> #VALUE! | D46: =IF(C46>$H$21,C46*($C$25/360),$H$21*($C$25/360)) -> #VALUE! | E46: =IF(E45>0,E45-D46,0) -> #VALUE! | F46: =SUM($D$33:D46) -> #VALUE! | G46: =IFERROR(-VLOOKUP(A46,$K$30:$M$36,2,FALSE),0) -> 0 | H46: =IF(E46>0,C46+G46,IF(E46<0,C46+G46+D46-E45,C46+D46+G46)) -> #VALUE! | I46: =(C46+D46-E46) -> #VALUE! | J46: 13 | K46: =EDATE(K45,1) -> 46501 | L46: {=_xlfn.IFS(J46>C$27,0,'Deal Details'!#REF!="Yes",0/$C$27,'Deal Details'!#REF!="No",$F$24/C$27)} -> 0
A47: =A46+1 -> 46119 | B47: 15 | C47: =H46 -> #VALUE! | D47: =IF(C47>$H$21,C47*($C$25/360),$H$21*($C$25/360)) -> #VALUE! | E47: =IF(E46>0,E46-D47,0) -> #VALUE! | F47: =SUM($D$33:D47) -> #VALUE! | G47: =IFERROR(-VLOOKUP(A47,$K$30:$M$36,2,FALSE),0) -> 0 | H47: =IF(E47>0,C47+G47,IF(E47<0,C47+G47+D47-E46,C47+D47+G47)) -> #VALUE! | I47: =(C47+D47-E47) -> #VALUE! | J47: 14 | K47: =EDATE(K46,1) -> 46531 | L47: {=_xlfn.IFS(J47>C$27,0,'Deal Details'!#REF!="Yes",0/$C$27,'Deal Details'!#REF!="No",$F$24/C$27)} -> 0
A48: =A47+1 -> 46120 | B48: 16 | C48: =H47 -> #VALUE! | D48: =IF(C48>$H$21,C48*($C$25/360),$H$21*($C$25/360)) -> #VALUE! | E48: =IF(E47>0,E47-D48,0) -> #VALUE! | F48: =SUM($D$33:D48) -> #VALUE! | G48: =IFERROR(-VLOOKUP(A48,$K$30:$M$36,2,FALSE),0) -> 0 | H48: =IF(E48>0,C48+G48,IF(E48<0,C48+G48+D48-E47,C48+D48+G48)) -> #VALUE! | I48: =(C48+D48-E48) -> #VALUE! | J48: 15 | K48: =EDATE(K47,1) -> 46562 | L48: {=_xlfn.IFS(J48>C$27,0,'Deal Details'!#REF!="Yes",0/$C$27,'Deal Details'!#REF!="No",$F$24/C$27)} -> 0 | O48: Today | P48: =C26 -> 46105
A49: =A48+1 -> 46121 | B49: 17 | C49: =H48 -> #VALUE! | D49: =IF(C49>$H$21,C49*($C$25/360),$H$21*($C$25/360)) -> #VALUE! | E49: =IF(E48>0,E48-D49,0) -> #VALUE! | F49: =SUM($D$33:D49) -> #VALUE! | G49: =IFERROR(-VLOOKUP(A49,$K$30:$M$36,2,FALSE),0) -> 0 | H49: =IF(E49>0,C49+G49,IF(E49<0,C49+G49+D49-E48,C49+D49+G49)) -> #VALUE! | I49: =(C49+D49-E49) -> #VALUE! | J49: 16 | K49: =EDATE(K48,1) -> 46592 | L49: {=_xlfn.IFS(J49>C$27,0,'Deal Details'!#REF!="Yes",0/$C$27,'Deal Details'!#REF!="No",$F$24/C$27)} -> 0 | O49: Days of Project | P49: =P48-A33+1 -> 1
A50: =A49+1 -> 46122 | B50: 18 | C50: =H49 -> #VALUE! | D50: =IF(C50>$H$21,C50*($C$25/360),$H$21*($C$25/360)) -> #VALUE! | E50: =IF(E49>0,E49-D50,0) -> #VALUE! | F50: =SUM($D$33:D50) -> #VALUE! | G50: =IFERROR(-VLOOKUP(A50,$K$30:$M$36,2,FALSE),0) -> 0 | H50: =IF(E50>0,C50+G50,IF(E50<0,C50+G50+D50-E49,C50+D50+G50)) -> #VALUE! | I50: =(C50+D50-E50) -> #VALUE! | J50: 17 | K50: =EDATE(K49,1) -> 46623 | L50: {=_xlfn.IFS(J50>C$27,0,'Deal Details'!#REF!="Yes",0/$C$27,'Deal Details'!#REF!="No",$F$24/C$27)} -> 0
A51: =A50+1 -> 46123 | B51: 19 | C51: =H50 -> #VALUE! | D51: =IF(C51>$H$21,C51*($C$25/360),$H$21*($C$25/360)) -> #VALUE! | E51: =IF(E50>0,E50-D51,0) -> #VALUE! | F51: =SUM($D$33:D51) -> #VALUE! | G51: =IFERROR(-VLOOKUP(A51,$K$30:$M$36,2,FALSE),0) -> 0 | H51: =IF(E51>0,C51+G51,IF(E51<0,C51+G51+D51-E50,C51+D51+G51)) -> #VALUE! | I51: =(C51+D51-E51) -> #VALUE! | J51: 18 | K51: =EDATE(K50,1) -> 46654 | L51: {=_xlfn.IFS(J51>C$27,0,'Deal Details'!#REF!="Yes",0/$C$27,'Deal Details'!#REF!="No",$F$24/C$27)} -> 0 | O51: Balance | P51: =$L$9-VLOOKUP(P48,$A$33:$H$835,5,FALSE)-H22 -> #VALUE!
A52: =A51+1 -> 46124 | B52: 20 | C52: =H51 -> #VALUE! | D52: =IF(C52>$H$21,C52*($C$25/360),$H$21*($C$25/360)) -> #VALUE! | E52: =IF(E51>0,E51-D52,0) -> #VALUE! | F52: =SUM($D$33:D52) -> #VALUE! | G52: =IFERROR(-VLOOKUP(A52,$K$30:$M$36,2,FALSE),0) -> 0 | H52: =IF(E52>0,C52+G52,IF(E52<0,C52+G52+D52-E51,C52+D52+G52)) -> #VALUE! | I52: =(C52+D52-E52) -> #VALUE! | J52: 19 | K52: =EDATE(K51,1) -> 46684 | L52: {=_xlfn.IFS(J52>C$27,0,'Deal Details'!#REF!="Yes",0/$C$27,'Deal Details'!#REF!="No",$F$24/C$27)} -> 0
A53: =A52+1 -> 46125 | B53: 21 | C53: =H52 -> #VALUE! | D53: =IF(C53>$H$21,C53*($C$25/360),$H$21*($C$25/360)) -> #VALUE! | E53: =IF(E52>0,E52-D53,0) -> #VALUE! | F53: =SUM($D$33:D53) -> #VALUE! | G53: =IFERROR(-VLOOKUP(A53,$K$30:$M$36,2,FALSE),0) -> 0 | H53: =IF(E53>0,C53+G53,IF(E53<0,C53+G53+D53-E52,C53+D53+G53)) -> #VALUE! | I53: =(C53+D53-E53) -> #VALUE! | J53: 20 | K53: =EDATE(K52,1) -> 46715 | L53: {=_xlfn.IFS(J53>C$27,0,'Deal Details'!#REF!="Yes",0/$C$27,'Deal Details'!#REF!="No",$F$24/C$27)} -> 0 | O53: Interest Reserve Start | P53: =F24
A54: =A53+1 -> 46126 | B54: 22 | C54: =H53 -> #VALUE! | D54: =IF(C54>$H$21,C54*($C$25/360),$H$21*($C$25/360)) -> #VALUE! | E54: =IF(E53>0,E53-D54,0) -> #VALUE! | F54: =SUM($D$33:D54) -> #VALUE! | G54: =IFERROR(-VLOOKUP(A54,$K$30:$M$36,2,FALSE),0) -> 0 | H54: =IF(E54>0,C54+G54,IF(E54<0,C54+G54+D54-E53,C54+D54+G54)) -> #VALUE! | I54: =(C54+D54-E54) -> #VALUE! | J54: 21 | K54: =EDATE(K53,1) -> 46745 | L54: {=_xlfn.IFS(J54>C$27,0,'Deal Details'!#REF!="Yes",0/$C$27,'Deal Details'!#REF!="No",$F$24/C$27)} -> 0 | O54: Minimum Interest | P54: 0
A55: =A54+1 -> 46127 | B55: 23 | C55: =H54 -> #VALUE! | D55: =IF(C55>$H$21,C55*($C$25/360),$H$21*($C$25/360)) -> #VALUE! | E55: =IF(E54>0,E54-D55,0) -> #VALUE! | F55: =SUM($D$33:D55) -> #VALUE! | G55: =IFERROR(-VLOOKUP(A55,$K$30:$M$36,2,FALSE),0) -> 0 | H55: =IF(E55>0,C55+G55,IF(E55<0,C55+G55+D55-E54,C55+D55+G55)) -> #VALUE! | I55: =(C55+D55-E55) -> #VALUE! | J55: 22 | K55: =EDATE(K54,1) -> 46776 | L55: {=_xlfn.IFS(J55>C$27,0,'Deal Details'!#REF!="Yes",0/$C$27,'Deal Details'!#REF!="No",$F$24/C$27)} -> 0 | O55: Total Interest at Date | P55: =IF(VLOOKUP($P$48,$A$33:$H$511,6,FALSE)>$P$54,VLOOKUP($P$48,$A$33:$H$511,6,FALSE),P54) -> 0
A56: =A55+1 -> 46128 | B56: 24 | C56: =H55 -> #VALUE! | D56: =IF(C56>$H$21,C56*($C$25/360),$H$21*($C$25/360)) -> #VALUE! | E56: =IF(E55>0,E55-D56,0) -> #VALUE! | F56: =SUM($D$33:D56) -> #VALUE! | G56: =IFERROR(-VLOOKUP(A56,$K$30:$M$36,2,FALSE),0) -> 0 | H56: =IF(E56>0,C56+G56,IF(E56<0,C56+G56+D56-E55,C56+D56+G56)) -> #VALUE! | I56: =(C56+D56-E56) -> #VALUE! | J56: 23 | K56: =EDATE(K55,1) -> 46807 | L56: {=_xlfn.IFS(J56>C$27,0,'Deal Details'!#REF!="Yes",0/$C$27,'Deal Details'!#REF!="No",$F$24/C$27)} -> 0 | O56: Interest Reserve Remaining | P56: =P53-P55 -> #VALUE!
A57: =A56+1 -> 46129 | B57: 25 | C57: =H56 -> #VALUE! | D57: =IF(C57>$H$21,C57*($C$25/360),$H$21*($C$25/360)) -> #VALUE! | E57: =IF(E56>0,E56-D57,0) -> #VALUE! | F57: =SUM($D$33:D57) -> #VALUE! | G57: =IFERROR(-VLOOKUP(A57,$K$30:$M$36,2,FALSE),0) -> 0 | H57: =IF(E57>0,C57+G57,IF(E57<0,C57+G57+D57-E56,C57+D57+G57)) -> #VALUE! | I57: =(C57+D57-E57) -> #VALUE! | J57: 24 | K57: =EDATE(K56,1) -> 46836 | L57: {=_xlfn.IFS(J57>C$27,0,'Deal Details'!#REF!="Yes",0/$C$27,'Deal Details'!#REF!="No",$F$24/C$27)} -> 0 | O57: Payoff Amount | P57: =C23-SUM(L35:L39)-P56 -> #VALUE! | Q57: (Total Loan)-(Payments)-(Interest Reserve Remaining)
A58: =A57+1 -> 46130 | B58: 26 | C58: =H57 -> #VALUE! | D58: =IF(C58>$H$21,C58*($C$25/360),$H$21*($C$25/360)) -> #VALUE! | E58: =IF(E57>0,E57-D58,0) -> #VALUE! | F58: =SUM($D$33:D58) -> #VALUE! | G58: =IFERROR(-VLOOKUP(A58,$K$30:$M$36,2,FALSE),0) -> 0 | H58: =IF(E58>0,C58+G58,IF(E58<0,C58+G58+D58-E57,C58+D58+G58)) -> #VALUE! | I58: =(C58+D58-E58) -> #VALUE! | K58: =C28 -> 46470 | L58: =(_xlfn.XLOOKUP(K58,A:A,I:I,0)) -> #VALUE! | M58: Payoff
A59: =A58+1 -> 46131 | B59: 27 | C59: =H58 -> #VALUE! | D59: =IF(C59>$H$21,C59*($C$25/360),$H$21*($C$25/360)) -> #VALUE! | E59: =IF(E58>0,E58-D59,0) -> #VALUE! | F59: =SUM($D$33:D59) -> #VALUE! | G59: =IFERROR(-VLOOKUP(A59,$K$30:$M$36,2,FALSE),0) -> 0 | H59: =IF(E59>0,C59+G59,IF(E59<0,C59+G59+D59-E58,C59+D59+G59)) -> #VALUE! | I59: =(C59+D59-E59) -> #VALUE! | K59: Total | L59: =SUM(L31:L58) -> #REF! | M59: =SUM(M33:M36) -> 0
A60: =A59+1 -> 46132 | B60: 28 | C60: =H59 -> #VALUE! | D60: =IF(C60>$H$21,C60*($C$25/360),$H$21*($C$25/360)) -> #VALUE! | E60: =IF(E59>0,E59-D60,0) -> #VALUE! | F60: =SUM($D$33:D60) -> #VALUE! | G60: =IFERROR(-VLOOKUP(A60,$K$30:$M$36,2,FALSE),0) -> 0 | H60: =IF(E60>0,C60+G60,IF(E60<0,C60+G60+D60-E59,C60+D60+G60)) -> #VALUE! | I60: =(C60+D60-E60) -> #VALUE! | K60: IRR | L60: =XIRR(L30:L58,K30:K58) -> #VALUE!
A61: =A60+1 -> 46133 | B61: 29 | C61: =H60 -> #VALUE! | D61: =IF(C61>$H$21,C61*($C$25/360),$H$21*($C$25/360)) -> #VALUE! | E61: =IF(E60>0,E60-D61,0) -> #VALUE! | F61: =SUM($D$33:D61) -> #VALUE! | G61: =IFERROR(-VLOOKUP(A61,$K$30:$M$36,2,FALSE),0) -> 0 | H61: =IF(E61>0,C61+G61,IF(E61<0,C61+G61+D61-E60,C61+D61+G61)) -> #VALUE! | I61: =(C61+D61-E61) -> #VALUE!
A62: =A61+1 -> 46134 | B62: 30 | C62: =H61 -> #VALUE! | D62: =IF(C62>$H$21,C62*($C$25/360),$H$21*($C$25/360)) -> #VALUE! | E62: =IF(E61>0,E61-D62,0) -> #VALUE! | F62: =SUM($D$33:D62) -> #VALUE! | G62: =IFERROR(-VLOOKUP(A62,$K$30:$M$36,2,FALSE),0) -> 0 | H62: =IF(E62>0,C62+G62,IF(E62<0,C62+G62+D62-E61,C62+D62+G62)) -> #VALUE! | I62: =(C62+D62-E62) -> #VALUE!
A63: =A62+1 -> 46135 | B63: 31 | C63: =H62 -> #VALUE! | D63: =IF(C63>$H$21,C63*($C$25/360),$H$21*($C$25/360)) -> #VALUE! | E63: =IF(E62>0,E62-D63,0) -> #VALUE! | F63: =SUM($D$33:D63) -> #VALUE! | G63: =IFERROR(-VLOOKUP(A63,$K$30:$M$36,2,FALSE),0) -> 0 | H63: =IF(E63>0,C63+G63,IF(E63<0,C63+G63+D63-E62,C63+D63+G63)) -> #VALUE! | I63: =(C63+D63-E63) -> #VALUE!
A64: =A63+1 -> 46136 | B64: 32 | C64: =H63 -> #VALUE! | D64: =IF(C64>$H$21,C64*($C$25/360),$H$21*($C$25/360)) -> #VALUE! | E64: =IF(E63>0,E63-D64,0) -> #VALUE! | F64: =SUM($D$33:D64) -> #VALUE! | G64: =IFERROR(-VLOOKUP(A64,$K$30:$M$36,2,FALSE),0) -> 0 | H64: =IF(E64>0,C64+G64,IF(E64<0,C64+G64+D64-E63,C64+D64+G64)) -> #VALUE! | I64: =(C64+D64-E64) -> #VALUE!
A65: =A64+1 -> 46137 | B65: 33 | C65: =H64 -> #VALUE! | D65: =IF(C65>$H$21,C65*($C$25/360),$H$21*($C$25/360)) -> #VALUE! | E65: =IF(E64>0,E64-D65,0) -> #VALUE! | F65: =SUM($D$33:D65) -> #VALUE! | G65: =IFERROR(-VLOOKUP(A65,$K$30:$M$36,2,FALSE),0) -> 0 | H65: =IF(E65>0,C65+G65,IF(E65<0,C65+G65+D65-E64,C65+D65+G65)) -> #VALUE! | I65: =(C65+D65-E65) -> #VALUE!
A66: =A65+1 -> 46138 | B66: 34 | C66: =H65 -> #VALUE! | D66: =IF(C66>$H$21,C66*($C$25/360),$H$21*($C$25/360)) -> #VALUE! | E66: =IF(E65>0,E65-D66,0) -> #VALUE! | F66: =SUM($D$33:D66) -> #VALUE! | G66: =IFERROR(-VLOOKUP(A66,$K$30:$M$36,2,FALSE),0) -> 0 | H66: =IF(E66>0,C66+G66,IF(E66<0,C66+G66+D66-E65,C66+D66+G66)) -> #VALUE! | I66: =(C66+D66-E66) -> #VALUE!
A67: =A66+1 -> 46139 | B67: 35 | C67: =H66 -> #VALUE! | D67: =IF(C67>$H$21,C67*($C$25/360),$H$21*($C$25/360)) -> #VALUE! | E67: =IF(E66>0,E66-D67,0) -> #VALUE! | F67: =SUM($D$33:D67) -> #VALUE! | G67: =IFERROR(-VLOOKUP(A67,$K$30:$M$36,2,FALSE),0) -> 0 | H67: =IF(E67>0,C67+G67,IF(E67<0,C67+G67+D67-E66,C67+D67+G67)) -> #VALUE! | I67: =(C67+D67-E67) -> #VALUE!
A68: =A67+1 -> 46140 | B68: 36 | C68: =H67 -> #VALUE! | D68: =IF(C68>$H$21,C68*($C$25/360),$H$21*($C$25/360)) -> #VALUE! | E68: =IF(E67>0,E67-D68,0) -> #VALUE! | F68: =SUM($D$33:D68) -> #VALUE! | G68: =IFERROR(-VLOOKUP(A68,$K$30:$M$36,2,FALSE),0) -> 0 | H68: =IF(E68>0,C68+G68,IF(E68<0,C68+G68+D68-E67,C68+D68+G68)) -> #VALUE! | I68: =(C68+D68-E68) -> #VALUE!
A69: =A68+1 -> 46141 | B69: 37 | C69: =H68 -> #VALUE! | D69: =IF(C69>$H$21,C69*($C$25/360),$H$21*($C$25/360)) -> #VALUE! | E69: =IF(E68>0,E68-D69,0) -> #VALUE! | F69: =SUM($D$33:D69) -> #VALUE! | G69: =IFERROR(-VLOOKUP(A69,$K$30:$M$36,2,FALSE),0) -> 0 | H69: =IF(E69>0,C69+G69,IF(E69<0,C69+G69+D69-E68,C69+D69+G69)) -> #VALUE! | I69: =(C69+D69-E69) -> #VALUE!
A70: =A69+1 -> 46142 | B70: 38 | C70: =H69 -> #VALUE! | D70: =IF(C70>$H$21,C70*($C$25/360),$H$21*($C$25/360)) -> #VALUE! | E70: =IF(E69>0,E69-D70,0) -> #VALUE! | F70: =SUM($D$33:D70) -> #VALUE! | G70: =IFERROR(-VLOOKUP(A70,$K$30:$M$36,2,FALSE),0) -> 0 | H70: =IF(E70>0,C70+G70,IF(E70<0,C70+G70+D70-E69,C70+D70+G70)) -> #VALUE! | I70: =(C70+D70-E70) -> #VALUE!
A71: =A70+1 -> 46143 | B71: 39 | C71: =H70 -> #VALUE! | D71: =IF(C71>$H$21,C71*($C$25/360),$H$21*($C$25/360)) -> #VALUE! | E71: =IF(E70>0,E70-D71,0) -> #VALUE! | F71: =SUM($D$33:D71) -> #VALUE! | G71: =IFERROR(-VLOOKUP(A71,$K$30:$M$36,2,FALSE),0) -> 0 | H71: =IF(E71>0,C71+G71,IF(E71<0,C71+G71+D71-E70,C71+D71+G71)) -> #VALUE! | I71: =(C71+D71-E71) -> #VALUE!
A72: =A71+1 -> 46144 | B72: 40 | C72: =H71 -> #VALUE! | D72: =IF(C72>$H$21,C72*($C$25/360),$H$21*($C$25/360)) -> #VALUE! | E72: =IF(E71>0,E71-D72,0) -> #VALUE! | F72: =SUM($D$33:D72) -> #VALUE! | G72: =IFERROR(-VLOOKUP(A72,$K$30:$M$36,2,FALSE),0) -> 0 | H72: =IF(E72>0,C72+G72,IF(E72<0,C72+G72+D72-E71,C72+D72+G72)) -> #VALUE! | I72: =(C72+D72-E72) -> #VALUE!
... A395: =A394+1 -> 46467 | B395: 363 | C395: =H394 -> #VALUE! | D395: =IF(C395>$H$21,C395*($C$25/360),$H$21*($C$25/360)) -> #VALUE! | E395: =IF(E394>0,E394-D395,0) -> #VALUE! | F395: =SUM($D$33:D395) -> #VALUE! | G395: =IFERROR(-VLOOKUP(A395,$K$30:$M$36,2,FALSE),0) -> 0 | H395: =IF(E395>0,C395+G395,IF(E395<0,C395+G395+D395-E394,C395+D395+G395)) -> #VALUE! | I395: =(C395+D395-E395) -> #VALUE!
A396: =A395+1 -> 46468 | B396: 364 | C396: =H395 -> #VALUE! | D396: =IF(C396>$H$21,C396*($L$16/360),$H$21*($L$16/360)) -> #VALUE! | E396: =IF(E395>0,E395-D396,0) -> #VALUE! | F396: =SUM($D$33:D396) -> #VALUE! | G396: =IFERROR(-VLOOKUP(A396,$K$30:$M$36,2,FALSE),0) -> 0 | H396: =IF(E396>0,C396+G396,IF(E396<0,C396+G396+D396-E395,C396+D396+G396)) -> #VALUE! | I396: =(C396+D396-E396) -> #VALUE! | J396: Default Interest Begins
A397: =A396+1 -> 46469 | B397: 365 | C397: =H396 -> #VALUE! | D397: =IF(C397>$H$21,C397*($L$16/360),$H$21*($L$16/360)) -> #VALUE! | E397: =IF(E396>0,E396-D397,0) -> #VALUE! | F397: =SUM($D$33:D397) -> #VALUE! | G397: =IFERROR(-VLOOKUP(A397,$K$30:$M$36,2,FALSE),0) -> 0 | H397: =IF(E397>0,C397+G397,IF(E397<0,C397+G397+D397-E396,C397+D397+G397)) -> #VALUE! | I397: =(C397+D397-E397) -> #VALUE!
A398: =A397+1 -> 46470 | B398: 366 | C398: =H397 -> #VALUE! | D398: =IF(C398>$H$21,C398*($L$16/360),$H$21*($L$16/360)) -> #VALUE! | E398: =IF(E397>0,E397-D398,0) -> #VALUE! | F398: =SUM($D$33:D398) -> #VALUE! | G398: =IFERROR(-VLOOKUP(A398,$K$30:$M$36,2,FALSE),0) -> 0 | H398: =IF(E398>0,C398+G398,IF(E398<0,C398+G398+D398-E397,C398+D398+G398)) -> #VALUE! | I398: =(C398+D398-E398) -> #VALUE!
A399: =A398+1 -> 46471 | B399: 367 | C399: =H398 -> #VALUE! | D399: =IF(C399>$H$21,C399*($L$16/360),$H$21*($L$16/360)) -> #VALUE! | E399: =IF(E398>0,E398-D399,0) -> #VALUE! | F399: =SUM($D$33:D399) -> #VALUE! | G399: =IFERROR(-VLOOKUP(A399,$K$30:$M$36,2,FALSE),0) -> 0 | H399: =IF(E399>0,C399+G399,IF(E399<0,C399+G399+D399-E398,C399+D399+G399)) -> #VALUE! | I399: =(C399+D399-E399) -> #VALUE!
A400: =A399+1 -> 46472 | B400: 368 | C400: =H399 -> #VALUE! | D400: =IF(C400>$H$21,C400*($L$16/360),$H$21*($L$16/360)) -> #VALUE! | E400: =IF(E399>0,E399-D400,0) -> #VALUE! | F400: =SUM($D$33:D400) -> #VALUE! | G400: =IFERROR(-VLOOKUP(A400,$K$30:$M$36,2,FALSE),0) -> 0 | H400: =IF(E400>0,C400+G400,IF(E400<0,C400+G400+D400-E399,C400+D400+G400)) -> #VALUE! | I400: =(C400+D400-E400) -> #VALUE!
A401: =A400+1 -> 46473 | B401: 369 | C401: =H400 -> #VALUE! | D401: =IF(C401>$H$21,C401*($L$16/360),$H$21*($L$16/360)) -> #VALUE! | E401: =IF(E400>0,E400-D401,0) -> #VALUE! | F401: =SUM($D$33:D401) -> #VALUE! | G401: =IFERROR(-VLOOKUP(A401,$K$30:$M$36,2,FALSE),0) -> 0 | H401: =IF(E401>0,C401+G401,IF(E401<0,C401+G401+D401-E400,C401+D401+G401)) -> #VALUE! | I401: =(C401+D401-E401) -> #VALUE!
A402: =A401+1 -> 46474 | B402: 370 | C402: =H401 -> #VALUE! | D402: =IF(C402>$H$21,C402*($L$16/360),$H$21*($L$16/360)) -> #VALUE! | E402: =IF(E401>0,E401-D402,0) -> #VALUE! | F402: =SUM($D$33:D402) -> #VALUE! | G402: =IFERROR(-VLOOKUP(A402,$K$30:$M$36,2,FALSE),0) -> 0 | H402: =IF(E402>0,C402+G402,IF(E402<0,C402+G402+D402-E401,C402+D402+G402)) -> #VALUE! | I402: =(C402+D402-E402) -> #VALUE!
A403: =A402+1 -> 46475 | B403: 371 | C403: =H402 -> #VALUE! | D403: =IF(C403>$H$21,C403*($L$16/360),$H$21*($L$16/360)) -> #VALUE! | E403: =IF(E402>0,E402-D403,0) -> #VALUE! | F403: =SUM($D$33:D403) -> #VALUE! | G403: =IFERROR(-VLOOKUP(A403,$K$30:$M$36,2,FALSE),0) -> 0 | H403: =IF(E403>0,C403+G403,IF(E403<0,C403+G403+D403-E402,C403+D403+G403)) -> #VALUE! | I403: =(C403+D403-E403) -> #VALUE!
A404: =A403+1 -> 46476 | B404: 372 | C404: =H403 -> #VALUE! | D404: =IF(C404>$H$21,C404*($L$16/360),$H$21*($L$16/360)) -> #VALUE! | E404: =IF(E403>0,E403-D404,0) -> #VALUE! | F404: =SUM($D$33:D404) -> #VALUE! | G404: =IFERROR(-VLOOKUP(A404,$K$30:$M$36,2,FALSE),0) -> 0 | H404: =IF(E404>0,C404+G404,IF(E404<0,C404+G404+D404-E403,C404+D404+G404)) -> #VALUE! | I404: =(C404+D404-E404) -> #VALUE!
A405: =A404+1 -> 46477 | B405: 373 | C405: =H404 -> #VALUE! | D405: =IF(C405>$H$21,C405*($L$16/360),$H$21*($L$16/360)) -> #VALUE! | E405: =IF(E404>0,E404-D405,0) -> #VALUE! | F405: =SUM($D$33:D405) -> #VALUE! | G405: =IFERROR(-VLOOKUP(A405,$K$30:$M$36,2,FALSE),0) -> 0 | H405: =IF(E405>0,C405+G405,IF(E405<0,C405+G405+D405-E404,C405+D405+G405)) -> #VALUE! | I405: =(C405+D405-E405) -> #VALUE!
A406: =A405+1 -> 46478 | B406: 374 | C406: =H405 -> #VALUE! | D406: =IF(C406>$H$21,C406*($L$16/360),$H$21*($L$16/360)) -> #VALUE! | E406: =IF(E405>0,E405-D406,0) -> #VALUE! | F406: =SUM($D$33:D406) -> #VALUE! | G406: =IFERROR(-VLOOKUP(A406,$K$30:$M$36,2,FALSE),0) -> 0 | H406: =IF(E406>0,C406+G406,IF(E406<0,C406+G406+D406-E405,C406+D406+G406)) -> #VALUE! | I406: =(C406+D406-E406) -> #VALUE!
A407: =A406+1 -> 46479 | B407: 375 | C407: =H406 -> #VALUE! | D407: =IF(C407>$H$21,C407*($L$16/360),$H$21*($L$16/360)) -> #VALUE! | E407: =IF(E406>0,E406-D407,0) -> #VALUE! | F407: =SUM($D$33:D407) -> #VALUE! | G407: =IFERROR(-VLOOKUP(A407,$K$30:$M$36,2,FALSE),0) -> 0 | H407: =IF(E407>0,C407+G407,IF(E407<0,C407+G407+D407-E406,C407+D407+G407)) -> #VALUE! | I407: =(C407+D407-E407) -> #VALUE!
A408: =A407+1 -> 46480 | B408: 376 | C408: =H407 -> #VALUE! | D408: =IF(C408>$H$21,C408*($L$16/360),$H$21*($L$16/360)) -> #VALUE! | E408: =IF(E407>0,E407-D408,0) -> #VALUE! | F408: =SUM($D$33:D408) -> #VALUE! | G408: =IFERROR(-VLOOKUP(A408,$K$30:$M$36,2,FALSE),0) -> 0 | H408: =IF(E408>0,C408+G408,IF(E408<0,C408+G408+D408-E407,C408+D408+G408)) -> #VALUE! | I408: =(C408+D408-E408) -> #VALUE!
... A2180: =A2179+1 -> 48252 | B2180: 2148 | C2180: =H2179 -> #VALUE! | D2180: =IF(C2180>$H$21,C2180*($L$16/360),$H$21*($L$16/360)) -> #VALUE! | E2180: =IF(E2179>0,E2179-D2180,0) -> #VALUE! | F2180: =SUM($D$33:D2180) -> #VALUE! | G2180: =IFERROR(-VLOOKUP(A2180,$K$30:$M$36,2,FALSE),0) -> 0 | H2180: =IF(E2180>0,C2180+G2180,IF(E2180<0,C2180+G2180+D2180-E2179,C2180+D2180+G2180)) -> #VALUE! | I2180: =(C2180+D2180-E2180) -> #VALUE!

Sheet Mezz Amort
A1: Mesa Bridge Capital | H1: Closing Costs | I1: =SUM(I3+I4+I7) -> 17000
A2: ='Deal Details'!C3 -> 0 | H2: Land Payoff | I2: =I10-SUM(I3:I9) -> 700 | M2: Legal Exp: | P2: =A2 -> 0 | T2: IRR if Paid off Today | X2: IRR if Paid off at Maturity | AB2: Loan Amount | AC2: =AC4+AC6+AC7+AC9+AC10+AC11 -> #REF!
H3: Processing Fee | I3: ='Deal Details'!C22 -> 3500 | K3: Total Fee income: | L3: =SUM(I3:I4,I9,I5,I7)-M3 -> 25550 | P3: Date | Q3: Amount | R3: Type | T3: Date | U3: Amount | V3: # Lots | X3: Date | Y3: Amount | Z3: # Lots | AB3: Interest Rate | AC3: ='Deal Details'!$H$34 -> 0.24
A4: Loan | C4: =I10 -> 35000 | H4: Legal Fees | I4: ='Deal Details'!C23 -> 10000 | P4: =C8 -> 46105 | Q4: =-C15 -> -35000 | R4: Principal | T4: =A15 -> 46105 | U4: =Q4 -> -35000 | V4: Loan principal | X4: =T4 -> 46105 | Y4: =U4 -> -35000 | Z4: Loan principal | AB4: Interest Reserve | AC4: =IF('Deal Details'!#REF!="Yes",'Mezz Amort'!$I$8,0) -> #REF!
A5: Points | C5: 0.03 | D5: =C5*C4 -> 1050 | E5: 1500 | H5: Title Fees (Estimated) | I5: ='Deal Details'!C24 -> 7500 | P5: =P4 -> 46105 | Q5: =I9 -> 1050 | R5: Points | T5: =T4 -> 46105 | U5: =D5 -> 1050 | V5: Points | X5: =X4 -> 46105 | Y5: =U5 -> 1050 | Z5: Points | AB5: Ending Int Res. | AC5: =+SUMIF(AB:AB,AC13,AG:AG) -> 0 | AD5: =AC5/AC4 -> #REF!
A6: Interest | C6: 0.24 | D6: Default | G6: ='Deal Details'!C20 -> 0.01 | H6: Broker Fee | I6: ='Deal Details'!C20*I10 -> 350 | O6: Month | P6: =P4 -> 46105 | Q6: =IF('Deal Details'!#REF!="Yes",I8,0) -> #REF! | R6: Reserve | T6: =P6 -> 46105 | U6: =Q6 -> #REF! | V6: =R6 -> Reserve | X6: =T6 -> 46105 | Y6: =U6 -> #REF! | Z6: =V6 -> Reserve | AB6: Origination Fee | AC6: ='Mezz Amort'!$I$9 -> 1050 | AD6: ='Deal Details'!AB26 -> 0
A7: Exit fee | C7: 0 | D7: 0.18 | H7: Inspection Fee | I7: ='Deal Details'!C21 -> 3500 | O7: 1 | P7: =EDATE(P6,1) -> 46136 | Q7: {=_xlfn.IFS(O7>AC$8,0,'Deal Details'!#REF!="Yes",0/C10,'Deal Details'!#REF!="No",'Mezz Amort'!I$8/C10)} -> #REF! | AB7: Construction Res.
A8: Loan start date | C8: ='Deal Details'!C31 -> 46105 | H8: Interest Reserve | I8: =I10*C6*(C10/12) -> 8400 | O8: 2 | P8: =EDATE(P7,1) -> 46166 | Q8: {=_xlfn.IFS(O8>AC$8,0,'Deal Details'!#REF!="Yes",0/12,'Deal Details'!#REF!="No",'Mezz Amort'!I$8/12)} -> #REF! | AB8: Term (months) | AC8: ='Deal Details'!$C$27 -> 12
A9: Total Interest | C9: =C6+C7 -> 0.24 | H9: Origination Fee | I9: =C5*I10 -> 1050 | O9: 3 | P9: =EDATE(P8,1) -> 46197 | Q9: {=_xlfn.IFS(O9>AC$8,0,'Deal Details'!#REF!="Yes",0/12,'Deal Details'!#REF!="No",'Mezz Amort'!I$8/12)} -> #REF! | AB9: Closing Fees | AC9: =SUM('Mezz Amort'!$I$3:$I$5,'Mezz Amort'!$I$7) -> 24500
A10: Loan Term (Months) | C10: ='Deal Details'!C27 -> 12 | H10: Total | I10: =ROUNDUP((ProForma!H54+'Deal Details'!C21+SUM('Deal Details'!C22:C24))/(1-C5-C6*(C10/12)-'Deal Details'!C20),-3) -> 35000 | O10: 4 | P10: =EDATE(P9,1) -> 46227 | Q10: {=_xlfn.IFS(O10>AC$8,0,'Deal Details'!#REF!="Yes",0/12,'Deal Details'!#REF!="No",'Mezz Amort'!I$8/12)} -> #REF! | AB10: Land Payoff | AC10: ='Mezz Amort'!$I$2 -> 700
A11: Loan Maturity | C11: =EDATE(C8,C10) -> 46470 | O11: 5 | P11: =EDATE(P10,1) -> 46258 | Q11: {=_xlfn.IFS(O11>AC$8,0,'Deal Details'!#REF!="Yes",0/12,'Deal Details'!#REF!="No",'Mezz Amort'!I$8/12)} -> #REF! | AB11: Broker Fee | AC11: ='Mezz Amort'!$I$6 -> 350 | AD11: ='Deal Details'!$C$20 -> 0.01
A12: Loan Exit | O12: 6 | P12: =EDATE(P11,1) -> 46289 | Q12: {=_xlfn.IFS(O12>AC$8,0,'Deal Details'!#REF!="Yes",0/12,'Deal Details'!#REF!="No",'Mezz Amort'!I$8/12)} -> #REF! | AB12: Start Date | AC12: ='Deal Details'!$C$31 -> 46105
O13: 7 | P13: =EDATE(P12,1) -> 46319 | Q13: {=_xlfn.IFS(O13>AC$8,0,'Deal Details'!#REF!="Yes",0/12,'Deal Details'!#REF!="No",'Mezz Amort'!I$8/12)} -> #REF! | AB13: Maturity Date | AC13: =AC12+(365*AC8/12) -> 46470
A14: Period | C14: Beginning | D14: Interest | E14: Exit fee | F14: Payments | G14: Interest Reserve | H14: Balance | I14: Misc. Fees | J14: Payoff | K14: Income from fees | L14: Cumulative Interest | M14: Recognized Income | N14: Total Income | O14: 8 | P14: =EDATE(P13,1) -> 46350 | Q14: {=_xlfn.IFS(O14>AC$8,0,'Deal Details'!#REF!="Yes",0/12,'Deal Details'!#REF!="No",'Mezz Amort'!I$8/12)} -> #REF!
A15: =C8 -> 46105 | B15: 1 | C15: =$C$4 -> 35000 | D15: =(B15*($C$6/360))*C15 -> 23.333333 | E15: 0 | F15: 0 | G15: =MAX(0,I8-D15-E15) -> 8376.6667 | H15: =IF(G15>0,C15+F15+I15,SUM(C15:F15)) -> 35000 | I15: 0 | J15: =H15-IF(I$8-G15<Q$42,I$8-Q$42,G15) -> 29400 | K15: =$L$3/($C$11-$C$8) -> 70 | L15: =D15 -> 23.333333 | M15: =IF($I$8>L15,L15,$I$8) -> 23.333333 | N15: =K15+D15+I15 -> 93.333333 | O15: 9 | P15: =EDATE(P14,1) -> 46380 | Q15: {=_xlfn.IFS(O15>AC$8,0,'Deal Details'!#REF!="Yes",0/12,'Deal Details'!#REF!="No",'Mezz Amort'!I$8/12)} -> #REF!
A16: =A15+1 -> 46106 | B16: 2 | C16: =H15 -> 35000 | D16: =(($C$6/360))*C16 -> 23.333333 | E16: 0 | F16: =IFERROR(-VLOOKUP(A16,$P$4:$R$12,2,FALSE),0) -> 0 | G16: =IF(G15-D16-E16>0,G15-D16-E16,0) -> 8353.3333 | H16: =IF(G16>0,C16+F16+I16,SUM(C16:F16)-G15) -> 35000 | I16: 0 | J16: =H16-IF(I$8-G16<Q$42,I$8-Q$42,G16) -> 29400 | K16: =$L$3/($C$11-$C$8) -> 70 | L16: =L15+D16 -> 46.666667 | M16: =IF($I$8>L16,L16,$I$8) -> 46.666667 | N16: =N15+D16+K16+I16 -> 186.66667 | O16: 10 | P16: =EDATE(P15,1) -> 46411 | Q16: {=_xlfn.IFS(O16>AC$8,0,'Deal Details'!#REF!="Yes",0/12,'Deal Details'!#REF!="No",'Mezz Amort'!I$8/12)} -> #REF!
A17: =A16+1 -> 46107 | B17: 3 | C17: =H16 -> 35000 | D17: =(($C$6/360))*C17 -> 23.333333 | E17: 0 | F17: =IFERROR(-VLOOKUP(A17,$P$4:$R$12,2,FALSE),0) -> 0 | G17: =IF(G16-D17-E17>0,G16-D17-E17,0) -> 8330 | H17: =IF(G17>0,C17+F17+I17,SUM(C17:F17)-G16) -> 35000 | I17: 0 | J17: =H17-IF(I$8-G17<Q$42,I$8-Q$42,G17) -> 29400 | K17: =$L$3/($C$11-$C$8) -> 70 | L17: =L16+D17 -> 70 | M17: =IF($I$8>L17,L17,$I$8) -> 70 | N17: =N16+D17+K17+I17 -> 280 | O17: 11 | P17: =EDATE(P16,1) -> 46442 | Q17: {=_xlfn.IFS(O17>AC$8,0,'Deal Details'!#REF!="Yes",0/12,'Deal Details'!#REF!="No",'Mezz Amort'!I$8/12)} -> #REF! | T17: =IF(Q38=0,C12,Q36) -> 46105 | U17: =Q38 -> 29400 | X17: =C11 -> 46470 | Y17: =VLOOKUP(X17,A14:H1785,8,TRUE) -> 35140.234
A18: =A17+1 -> 46108 | B18: 4 | C18: =H17 -> 35000 | D18: =(($C$6/360))*C18 -> 23.333333 | E18: 0 | F18: =IFERROR(-VLOOKUP(A18,$P$4:$R$12,2,FALSE),0) -> 0 | G18: =IF(G17-D18-E18>0,G17-D18-E18,0) -> 8306.6667 | H18: =IF(G18>0,C18+F18+I18,SUM(C18:F18)-G17) -> 35000 | I18: 0 | J18: =H18-IF(I$8-G18<Q$42,I$8-Q$42,G18) -> 29400 | K18: =$L$3/($C$11-$C$8) -> 70 | L18: =L17+D18 -> 93.333333 | M18: =IF($I$8>L18,L18,$I$8) -> 93.333333 | N18: =N17+D18+K18+I18 -> 373.33333 | O18: 12 | P18: =EDATE(P17,1) -> 46470 | Q18: {=_xlfn.IFS(O18>AC$8,0,'Deal Details'!#REF!="Yes",0/12,'Deal Details'!#REF!="No",'Mezz Amort'!I$8/12)} -> #REF! | T18: IRR if paid off today | U18: =IF(ISERROR(XIRR(U4:U17,T4:T17,0.35)),1,XIRR(U4:U17,T4:T17,0.35)) -> 1 | X18: IRR if paid off at Maturity | Y18: =XIRR(Y4:Y17,X4:X17) -> #REF! | Z18: =VLOOKUP(X17,A14:H478,7,0) -> 0
A19: =A18+1 -> 46109 | B19: 5 | C19: =H18 -> 35000 | D19: =(($C$6/360))*C19 -> 23.333333 | E19: 0 | F19: =IFERROR(-VLOOKUP(A19,$P$4:$R$12,2,FALSE),0) -> 0 | G19: =IF(G18-D19-E19>0,G18-D19-E19,0) -> 8283.3333 | H19: =IF(G19>0,C19+F19+I19,SUM(C19:F19)-G18) -> 35000 | I19: 0 | J19: =H19-IF(I$8-G19<Q$42,I$8-Q$42,G19) -> 29400 | K19: =$L$3/($C$11-$C$8) -> 70 | L19: =L18+D19 -> 116.66667 | M19: =IF($I$8>L19,L19,$I$8) -> 116.66667 | N19: =N18+D19+K19+I19 -> 466.66667 | O19: 13 | P19: =EDATE(P18,1) -> 46501 | Q19: {=_xlfn.IFS(O19>AC$8,0,'Deal Details'!#REF!="Yes",0/12,'Deal Details'!#REF!="No",'Mezz Amort'!I$8/12)} -> 0
A20: =A19+1 -> 46110 | B20: 6 | C20: =H19 -> 35000 | D20: =(($C$6/360))*C20 -> 23.333333 | E20: 0 | F20: =IFERROR(-VLOOKUP(A20,$P$4:$R$12,2,FALSE),0) -> 0 | G20: =IF(G19-D20-E20>0,G19-D20-E20,0) -> 8260 | H20: =IF(G20>0,C20+F20+I20,SUM(C20:F20)-G19) -> 35000 | I20: 0 | J20: =H20-IF(I$8-G20<Q$42,I$8-Q$42,G20) -> 29400 | K20: =$L$3/($C$11-$C$8) -> 70 | L20: =L19+D20 -> 140 | M20: =IF($I$8>L20,L20,$I$8) -> 140 | N20: =N19+D20+K20+I20 -> 560 | O20: 14 | P20: =EDATE(P19,1) -> 46531 | Q20: {=_xlfn.IFS(O20>AC$8,0,'Deal Details'!#REF!="Yes",0/12,'Deal Details'!#REF!="No",'Mezz Amort'!I$8/12)} -> 0
A21: =A20+1 -> 46111 | B21: 7 | C21: =H20 -> 35000 | D21: =(($C$6/360))*C21 -> 23.333333 | E21: 0 | F21: =IFERROR(-VLOOKUP(A21,$P$4:$R$12,2,FALSE),0) -> 0 | G21: =IF(G20-D21-E21>0,G20-D21-E21,0) -> 8236.6667 | H21: =IF(G21>0,C21+F21+I21,SUM(C21:F21)-G20) -> 35000 | I21: 0 | J21: =H21-IF(I$8-G21<Q$42,I$8-Q$42,G21) -> 29400 | K21: =$L$3/($C$11-$C$8) -> 70 | L21: =L20+D21 -> 163.33333 | M21: =IF($I$8>L21,L21,$I$8) -> 163.33333 | N21: =N20+D21+K21+I21 -> 653.33333 | O21: 15 | P21: =EDATE(P20,1) -> 46562 | Q21: {=_xlfn.IFS(O21>AC$8,0,'Deal Details'!#REF!="Yes",0/12,'Deal Details'!#REF!="No",'Mezz Amort'!I$8/12)} -> 0
A22: =A21+1 -> 46112 | B22: 8 | C22: =H21 -> 35000 | D22: =(($C$6/360))*C22 -> 23.333333 | E22: 0 | F22: =IFERROR(-VLOOKUP(A22,$P$4:$R$12,2,FALSE),0) -> 0 | G22: =IF(G21-D22-E22>0,G21-D22-E22,0) -> 8213.3333 | H22: =IF(G22>0,C22+F22+I22,SUM(C22:F22)-G21) -> 35000 | I22: 0 | J22: =H22-IF(I$8-G22<Q$42,I$8-Q$42,G22) -> 29400 | K22: =$L$3/($C$11-$C$8) -> 70 | L22: =L21+D22 -> 186.66667 | M22: =IF($I$8>L22,L22,$I$8) -> 186.66667 | N22: =N21+D22+K22+I22 -> 746.66667 | O22: 16 | P22: =EDATE(P21,1) -> 46592 | Q22: {=_xlfn.IFS(O22>AC$8,0,'Deal Details'!#REF!="Yes",0/12,'Deal Details'!#REF!="No",'Mezz Amort'!I$8/12)} -> 0
A23: =A22+1 -> 46113 | B23: 9 | C23: =H22 -> 35000 | D23: =(($C$6/360))*C23 -> 23.333333 | E23: 0 | F23: =IFERROR(-VLOOKUP(A23,$P$4:$R$12,2,FALSE),0) -> 0 | G23: =IF(G22-D23-E23>0,G22-D23-E23,0) -> 8190 | H23: =IF(G23>0,C23+F23+I23,SUM(C23:F23)-G22) -> 35000 | I23: 0 | J23: =H23-IF(I$8-G23<Q$42,I$8-Q$42,G23) -> 29400 | K23: =$L$3/($C$11-$C$8) -> 70 | L23: =L22+D23 -> 210 | M23: =IF($I$8>L23,L23,$I$8) -> 210 | N23: =N22+D23+K23+I23 -> 840 | O23: 17 | P23: =EDATE(P22,1) -> 46623 | Q23: {=_xlfn.IFS(O23>AC$8,0,'Deal Details'!#REF!="Yes",0/12,'Deal Details'!#REF!="No",'Mezz Amort'!I$8/12)} -> 0 | S23: Revenue | T23: Investment Date | U23: Maturity | V23: Balance | W23: Balance at Maturity | X23: Date of Exit | Y23: Earnings | Z23: principal | AA23: Misc. Fees | AB23: Misc. Fees Paid | AC23: Points | AD23: Cash at Risk | AE23: principal Repaid | AF23: Interest Payable | AG23: Interest Received | AH23: =P45 -> Return on Invesment | AI23: =P46 -> Annualized ROI | AJ23: IRR | AK23: IRR if Paid off Today | AL23: IRR if paid off at Maturity
A24: =A23+1 -> 46114 | B24: 10 | C24: =H23 -> 35000 | D24: =(($C$6/360))*C24 -> 23.333333 | E24: 0 | F24: =IFERROR(-VLOOKUP(A24,$P$4:$R$12,2,FALSE),0) -> 0 | G24: =IF(G23-D24-E24>0,G23-D24-E24,0) -> 8166.6667 | H24: =IF(G24>0,C24+F24+I24,SUM(C24:F24)-G23) -> 35000 | I24: 0 | J24: =H24-IF(I$8-G24<Q$42,I$8-Q$42,G24) -> 29400 | K24: =$L$3/($C$11-$C$8) -> 70 | L24: =L23+D24 -> 233.33333 | M24: =IF($I$8>L24,L24,$I$8) -> 233.33333 | N24: =N23+D24+K24+I24 -> 933.33333 | O24: 18 | P24: =EDATE(P23,1) -> 46654 | Q24: {=_xlfn.IFS(O24>AC$8,0,'Deal Details'!#REF!="Yes",0/12,'Deal Details'!#REF!="No",'Mezz Amort'!I$8/12)} -> 0 | S24: =IF(SUM(D14:OFFSET(D14,Q40,1))>Q6,Q6+Q5,SUM(D14:OFFSET(D14,Q40,1))+Q5) -> #REF! | T24: =P4 -> 46105 | U24: =C11 -> 46470 | V24: =Q38 -> 29400 | W24: =Y17 -> 35140.234 | X24: =IF(C12="","NA",C12) -> NA | Y24: =Q32-I8 -> #REF! | Z24: =-Q37 -> 35000 | AA24: =SUM(I14:OFFSET($I$14,Q40,,)) -> 0 | AB24: =IF(Y24-AC24-AE24>=AA24,AA24,Y24-AC24-AE24) -> #REF! | AC24: =D5 -> 1050 | AD24: =Q44 -> #REF! | AE24: =IF(Q43-AC24>=Z24,Z24,Y24-AC24) -> #REF! | AF24: =IF(Q47>0,I10,V24)-(AA24-AB24)-(Z24-AE24)-I7+I8-Q47 -> #REF! | AG24: =Y24-AC24-AE24-AB24 -> #REF! | AH24: =Q45 -> #REF! | AI24: =Q46 -> #REF! | AJ24: =IF(0<Q33<1,Q33,"NA") -> #REF! | AK24: =U18 -> 1 | AL24: =Y18 -> #REF!
A25: =A24+1 -> 46115 | B25: 11 | C25: =H24 -> 35000 | D25: =(($C$6/360))*C25 -> 23.333333 | E25: 0 | F25: =IFERROR(-VLOOKUP(A25,$P$4:$R$12,2,FALSE),0) -> 0 | G25: =IF(G24-D25-E25>0,G24-D25-E25,0) -> 8143.3333 | H25: =IF(G25>0,C25+F25+I25,SUM(C25:F25)-G24) -> 35000 | I25: 0 | J25: =H25-IF(I$8-G25<Q$42,I$8-Q$42,G25) -> 29400 | K25: =$L$3/($C$11-$C$8) -> 70 | L25: =L24+D25 -> 256.66667 | M25: =IF($I$8>L25,L25,$I$8) -> 256.66667 | N25: =N24+D25+K25+I25 -> 1026.6667 | O25: 19 | P25: =EDATE(P24,1) -> 46684 | Q25: {=_xlfn.IFS(O25>AC$8,0,'Deal Details'!#REF!="Yes",0/12,'Deal Details'!#REF!="No",'Mezz Amort'!I$8/12)} -> 0
A26: =A25+1 -> 46116 | B26: 12 | C26: =H25 -> 35000 | D26: =(($C$6/360))*C26 -> 23.333333 | E26: 0 | F26: =IFERROR(-VLOOKUP(A26,$P$4:$R$12,2,FALSE),0) -> 0 | G26: =IF(G25-D26-E26>0,G25-D26-E26,0) -> 8120 | H26: =IF(G26>0,C26+F26+I26,SUM(C26:F26)-G25) -> 35000 | I26: 0 | J26: =H26-IF(I$8-G26<Q$42,I$8-Q$42,G26) -> 29400 | K26: =$L$3/($C$11-$C$8) -> 70 | L26: =L25+D26 -> 280 | M26: =IF($I$8>L26,L26,$I$8) -> 280 | N26: =N25+D26+K26+I26 -> 1120 | O26: 20 | P26: =EDATE(P25,1) -> 46715 | Q26: {=_xlfn.IFS(O26>AC$8,0,'Deal Details'!#REF!="Yes",0/12,'Deal Details'!#REF!="No",'Mezz Amort'!I$8/12)} -> 0
A27: =A26+1 -> 46117 | B27: 13 | C27: =H26 -> 35000 | D27: =(($C$6/360))*C27 -> 23.333333 | E27: 0 | F27: =IFERROR(-VLOOKUP(A27,$P$4:$R$12,2,FALSE),0) -> 0 | G27: =IF(G26-D27-E27>0,G26-D27-E27,0) -> 8096.6667 | H27: =IF(G27>0,C27+F27+I27,SUM(C27:F27)-G26) -> 35000 | I27: 0 | J27: =H27-IF(I$8-G27<Q$42,I$8-Q$42,G27) -> 29400 | K27: =$L$3/($C$11-$C$8) -> 70 | L27: =L26+D27 -> 303.33333 | M27: =IF($I$8>L27,L27,$I$8) -> 303.33333 | N27: =N26+D27+K27+I27 -> 1213.3333 | O27: 21 | P27: =EDATE(P26,1) -> 46745 | Q27: {=_xlfn.IFS(O27>AC$8,0,'Deal Details'!#REF!="Yes",0/12,'Deal Details'!#REF!="No",'Mezz Amort'!I$8/12)} -> 0 | U27: Cambia Loan Information | W27: In Default? | X27: =IF(TODAY()>V28,"YES","NO") -> NO | Z27: revenues | AA27: Points | AB27: Principal Repaid | AC27: Misc. Fees | AD27: Realized Interest
A28: =A27+1 -> 46118 | B28: 14 | C28: =H27 -> 35000 | D28: =(($C$6/360))*C28 -> 23.333333 | E28: 0 | F28: =IFERROR(-VLOOKUP(A28,$P$4:$R$12,2,FALSE),0) -> 0 | G28: =IF(G27-D28-E28>0,G27-D28-E28,0) -> 8073.3333 | H28: =IF(G28>0,C28+F28+I28,SUM(C28:F28)-G27) -> 35000 | I28: 0 | J28: =H28-IF(I$8-G28<Q$42,I$8-Q$42,G28) -> 29400 | K28: =$L$3/($C$11-$C$8) -> 70 | L28: =L27+D28 -> 326.66667 | M28: =IF($I$8>L28,L28,$I$8) -> 326.66667 | N28: =N27+D28+K28+I28 -> 1306.6667 | O28: 22 | P28: =EDATE(P27,1) -> 46776 | Q28: {=_xlfn.IFS(O28>AC$8,0,'Deal Details'!#REF!="Yes",0/12,'Deal Details'!#REF!="No",'Mezz Amort'!I$8/12)} -> 0 | U28: Maturity Date | V28: =U24 -> 46470 | W28: Revenues to date | X28: =Q43 -> #REF! | AB28: =if((Revenues-points)>Principal,Principal,Principal-points)
A29: =A28+1 -> 46119 | B29: 15 | C29: =H28 -> 35000 | D29: =(($C$6/360))*C29 -> 23.333333 | E29: 0 | F29: =IFERROR(-VLOOKUP(A29,$P$4:$R$12,2,FALSE),0) -> 0 | G29: =IF(G28-D29-E29>0,G28-D29-E29,0) -> 8050 | H29: =IF(G29>0,C29+F29+I29,SUM(C29:F29)-G28) -> 35000 | I29: 0 | J29: =H29-IF(I$8-G29<Q$42,I$8-Q$42,G29) -> 29400 | K29: =$L$3/($C$11-$C$8) -> 70 | L29: =L28+D29 -> 350 | M29: =IF($I$8>L29,L29,$I$8) -> 350 | N29: =N28+D29+K29+I29 -> 1400 | O29: 23 | P29: =EDATE(P28,1) -> 46807 | Q29: {=_xlfn.IFS(O29>AC$8,0,'Deal Details'!#REF!="Yes",0/12,'Deal Details'!#REF!="No",'Mezz Amort'!I$8/12)} -> 0 | U29: Investment Date | V29: =T24 -> 46105 | W29: Accrued Income | X29: =AF24 -> #REF! | AC29: =if((Revenues-points-principalRepaid)>Misc. fees,misc fees,Revenue-Principal-points)
A30: =A29+1 -> 46120 | B30: 16 | C30: =H29 -> 35000 | D30: =(($C$6/360))*C30 -> 23.333333 | E30: 0 | F30: =IFERROR(-VLOOKUP(A30,$P$4:$R$12,2,FALSE),0) -> 0 | G30: =IF(G29-D30-E30>0,G29-D30-E30,0) -> 8026.6667 | H30: =IF(G30>0,C30+F30+I30,SUM(C30:F30)-G29) -> 35000 | I30: 0 | J30: =H30-IF(I$8-G30<Q$42,I$8-Q$42,G30) -> 29400 | K30: =$L$3/($C$11-$C$8) -> 70 | L30: =L29+D30 -> 373.33333 | M30: =IF($I$8>L30,L30,$I$8) -> 373.33333 | N30: =N29+D30+K30+I30 -> 1493.3333 | O30: 24 | P30: =EDATE(P29,1) -> 46836 | Q30: {=_xlfn.IFS(O30>AC$8,0,'Deal Details'!#REF!="Yes",0/12,'Deal Details'!#REF!="No",'Mezz Amort'!I$8/12)} -> 0 | U30: Principal | V30: =Z24 -> 35000 | W30: Current Balance | X30: =Q38 -> 29400
A31: =A30+1 -> 46121 | B31: 17 | C31: =H30 -> 35000 | D31: =(($C$6/360))*C31 -> 23.333333 | E31: 0 | F31: =IFERROR(-VLOOKUP(A31,$P$4:$R$12,2,FALSE),0) -> 0 | G31: =IF(G30-D31-E31>0,G30-D31-E31,0) -> 8003.3333 | H31: =IF(G31>0,C31+F31+I31,SUM(C31:F31)-G30) -> 35000 | I31: 0 | J31: =H31-IF(I$8-G31<Q$42,I$8-Q$42,G31) -> 29400 | K31: =$L$3/($C$11-$C$8) -> 70 | L31: =L30+D31 -> 396.66667 | M31: =IF($I$8>L31,L31,$I$8) -> 396.66667 | N31: =N30+D31+K31+I31 -> 1586.6667 | P31: =AC13 -> 46470 | Q31: =I2+(_xlfn.XLOOKUP(C11,A:A,N:N)) -> 34860.234 | R31: Payoff | U31: Origination Fee | V31: =AC24 -> 1050 | W31: Days of project | X31: =Q40 -> 1
A32: =A31+1 -> 46122 | B32: 18 | C32: =H31 -> 35000 | D32: =(($C$6/360))*C32 -> 23.333333 | E32: 0 | F32: =IFERROR(-VLOOKUP(A32,$P$4:$R$12,2,FALSE),0) -> 0 | G32: =IF(G31-D32-E32>0,G31-D32-E32,0) -> 7980 | H32: =IF(G32>0,C32+F32+I32,SUM(C32:F32)-G31) -> 35000 | I32: 0 | J32: =H32-IF(I$8-G32<Q$42,I$8-Q$42,G32) -> 29400 | K32: =$L$3/($C$11-$C$8) -> 70 | L32: =L31+D32 -> 420 | M32: =IF($I$8>L32,L32,$I$8) -> 420 | N32: =N31+D32+K32+I32 -> 1680 | P32: Total | Q32: =SUM(Q5:Q31) -> #REF! | R32: =SUM(R6:R31) -> 0 | U32: Interest/Day | V32: =Q39 -> 23.333333
A33: =A32+1 -> 46123 | B33: 19 | C33: =H32 -> 35000 | D33: =(($C$6/360))*C33 -> 23.333333 | E33: 0 | F33: =IFERROR(-VLOOKUP(A33,$P$4:$R$12,2,FALSE),0) -> 0 | G33: =IF(G32-D33-E33>0,G32-D33-E33,0) -> 7956.6667 | H33: =IF(G33>0,C33+F33+I33,SUM(C33:F33)-G32) -> 35000 | I33: 0 | J33: =H33-IF(I$8-G33<Q$42,I$8-Q$42,G33) -> 29400 | K33: =$L$3/($C$11-$C$8) -> 70 | L33: =L32+D33 -> 443.33333 | M33: =IF($I$8>L33,L33,$I$8) -> 443.33333 | N33: =N32+D33+K33+I33 -> 1773.3333 | P33: IRR | Q33: =XIRR(Q4:Q31,P4:P31) -> #REF!
A34: =A33+1 -> 46124 | B34: 20 | C34: =H33 -> 35000 | D34: =(($C$6/360))*C34 -> 23.333333 | E34: 0 | F34: =IFERROR(-VLOOKUP(A34,$P$4:$R$12,2,FALSE),0) -> 0 | G34: =IF(G33-D34-E34>0,G33-D34-E34,0) -> 7933.3333 | H34: =IF(G34>0,C34+F34+I34,SUM(C34:F34)-G33) -> 35000 | I34: 0 | J34: =H34-IF(I$8-G34<Q$42,I$8-Q$42,G34) -> 29400 | K34: =$L$3/($C$11-$C$8) -> 70 | L34: =L33+D34 -> 466.66667 | M34: =IF($I$8>L34,L34,$I$8) -> 466.66667 | N34: =N33+D34+K34+I34 -> 1866.6667 | P34: Term | Q34: =AC8 -> 12
A35: =A34+1 -> 46125 | B35: 21 | C35: =H34 -> 35000 | D35: =(($C$6/360))*C35 -> 23.333333 | E35: 0 | F35: =IFERROR(-VLOOKUP(A35,$P$4:$R$12,2,FALSE),0) -> 0 | G35: =IF(G34-D35-E35>0,G34-D35-E35,0) -> 7910 | H35: =IF(G35>0,C35+F35+I35,SUM(C35:F35)-G34) -> 35000 | I35: 0 | J35: =H35-IF(I$8-G35<Q$42,I$8-Q$42,G35) -> 29400 | K35: =$L$3/($C$11-$C$8) -> 70 | L35: =L34+D35 -> 490 | M35: =IF($I$8>L35,L35,$I$8) -> 490 | N35: =N34+D35+K35+I35 -> 1960
A36: =A35+1 -> 46126 | B36: 22 | C36: =H35 -> 35000 | D36: =(($C$6/360))*C36 -> 23.333333 | E36: 0 | F36: =IFERROR(-VLOOKUP(A36,$P$4:$R$12,2,FALSE),0) -> 0 | G36: =IF(G35-D36-E36>0,G35-D36-E36,0) -> 7886.6667 | H36: =IF(G36>0,C36+F36+I36,SUM(C36:F36)-G35) -> 35000 | I36: 0 | J36: =H36-IF(I$8-G36<Q$42,I$8-Q$42,G36) -> 29400 | K36: =$L$3/($C$11-$C$8) -> 70 | L36: =L35+D36 -> 513.33333 | M36: =IF($I$8>L36,L36,$I$8) -> 513.33333 | N36: =N35+D36+K36+I36 -> 2053.3333 | P36: Today | Q36: =C8 -> 46105
A37: =A36+1 -> 46127 | B37: 23 | C37: =H36 -> 35000 | D37: =(($C$6/360))*C37 -> 23.333333 | E37: 0 | F37: =IFERROR(-VLOOKUP(A37,$P$4:$R$12,2,FALSE),0) -> 0 | G37: =IF(G36-D37-E37>0,G36-D37-E37,0) -> 7863.3333 | H37: =IF(G37>0,C37+F37+I37,SUM(C37:F37)-G36) -> 35000 | I37: 0 | J37: =H37-IF(I$8-G37<Q$42,I$8-Q$42,G37) -> 29400 | K37: =$L$3/($C$11-$C$8) -> 70 | L37: =L36+D37 -> 536.66667 | M37: =IF($I$8>L37,L37,$I$8) -> 536.66667 | N37: =N36+D37+K37+I37 -> 2146.6667 | P37: Principal | Q37: =Q4 -> -35000
A38: =A37+1 -> 46128 | B38: 24 | C38: =H37 -> 35000 | D38: =(($C$6/360))*C38 -> 23.333333 | E38: 0 | F38: =IFERROR(-VLOOKUP(A38,$P$4:$R$12,2,FALSE),0) -> 0 | G38: =IF(G37-D38-E38>0,G37-D38-E38,0) -> 7840 | H38: =IF(G38>0,C38+F38+I38,SUM(C38:F38)-G37) -> 35000 | I38: 0 | J38: =H38-IF(I$8-G38<Q$42,I$8-Q$42,G38) -> 29400 | K38: =$L$3/($C$11-$C$8) -> 70 | L38: =L37+D38 -> 560 | M38: =IF($I$8>L38,L38,$I$8) -> 560 | N38: =N37+D38+K38+I38 -> 2240 | P38: Balance | Q38: =VLOOKUP(Q36,$A$15:$J$853,10,FALSE) -> 29400
A39: =A38+1 -> 46129 | B39: 25 | C39: =H38 -> 35000 | D39: =(($C$6/360))*C39 -> 23.333333 | E39: 0 | F39: =IFERROR(-VLOOKUP(A39,$P$4:$R$12,2,FALSE),0) -> 0 | G39: =IF(G38-D39-E39>0,G38-D39-E39,0) -> 7816.6667 | H39: =IF(G39>0,C39+F39+I39,SUM(C39:F39)-G38) -> 35000 | I39: 0 | J39: =H39-IF(I$8-G39<Q$42,I$8-Q$42,G39) -> 29400 | K39: =$L$3/($C$11-$C$8) -> 70 | L39: =L38+D39 -> 583.33333 | M39: =IF($I$8>L39,L39,$I$8) -> 583.33333 | N39: =N38+D39+K39+I39 -> 2333.3333 | P39: Daily Interest | Q39: =VLOOKUP(Q36,$A$15:$I$493,4,FALSE)+VLOOKUP(Q36,$A$15:$I$493,5,FALSE) -> 23.333333
A40: =A39+1 -> 46130 | B40: 26 | C40: =H39 -> 35000 | D40: =(($C$6/360))*C40 -> 23.333333 | E40: 0 | F40: =IFERROR(-VLOOKUP(A40,$P$4:$R$12,2,FALSE),0) -> 0 | G40: =IF(G39-D40-E40>0,G39-D40-E40,0) -> 7793.3333 | H40: =IF(G40>0,C40+F40+I40,SUM(C40:F40)-G39) -> 35000 | I40: 0 | J40: =H40-IF(I$8-G40<Q$42,I$8-Q$42,G40) -> 29400 | K40: =$L$3/($C$11-$C$8) -> 70 | L40: =L39+D40 -> 606.66667 | M40: =IF($I$8>L40,L40,$I$8) -> 606.66667 | N40: =N39+D40+K40+I40 -> 2426.6667 | P40: Days of Project | Q40: =Q36-A15+1 -> 1
A41: =A40+1 -> 46131 | B41: 27 | C41: =H40 -> 35000 | D41: =(($C$6/360))*C41 -> 23.333333 | E41: 0 | F41: =IFERROR(-VLOOKUP(A41,$P$4:$R$12,2,FALSE),0) -> 0 | G41: =IF(G40-D41-E41>0,G40-D41-E41,0) -> 7770 | H41: =IF(G41>0,C41+F41+I41,SUM(C41:F41)-G40) -> 35000 | I41: 0 | J41: =H41-IF(I$8-G41<Q$42,I$8-Q$42,G41) -> 29400 | K41: =$L$3/($C$11-$C$8) -> 70 | L41: =L40+D41 -> 630 | M41: =IF($I$8>L41,L41,$I$8) -> 630 | N41: =N40+D41+K41+I41 -> 2520 | P41: Interest | Q41: =SUM(D14:OFFSET(D14,Q40,1)) -> 23.333333
A42: =A41+1 -> 46132 | B42: 28 | C42: =H41 -> 35000 | D42: =(($C$6/360))*C42 -> 23.333333 | E42: 0 | F42: =IFERROR(-VLOOKUP(A42,$P$4:$R$12,2,FALSE),0) -> 0 | G42: =IF(G41-D42-E42>0,G41-D42-E42,0) -> 7746.6667 | H42: =IF(G42>0,C42+F42+I42,SUM(C42:F42)-G41) -> 35000 | I42: 0 | J42: =H42-IF(I$8-G42<Q$42,I$8-Q$42,G42) -> 29400 | K42: =$L$3/($C$11-$C$8) -> 70 | L42: =L41+D42 -> 653.33333 | M42: =IF($I$8>L42,L42,$I$8) -> 653.33333 | N42: =N41+D42+K42+I42 -> 2613.3333 | P42: Minimum Return | Q42: =(I10*C6/3) -> 2800
A43: =A42+1 -> 46133 | B43: 29 | C43: =H42 -> 35000 | D43: =(($C$6/360))*C43 -> 23.333333 | E43: 0 | F43: =IFERROR(-VLOOKUP(A43,$P$4:$R$12,2,FALSE),0) -> 0 | G43: =IF(G42-D43-E43>0,G42-D43-E43,0) -> 7723.3333 | H43: =IF(G43>0,C43+F43+I43,SUM(C43:F43)-G42) -> 35000 | I43: 0 | J43: =H43-IF(I$8-G43<Q$42,I$8-Q$42,G43) -> 29400 | K43: =$L$3/($C$11-$C$8) -> 70 | L43: =L42+D43 -> 676.66667 | M43: =IF($I$8>L43,L43,$I$8) -> 676.66667 | N43: =N42+D43+K43+I43 -> 2706.6667 | P43: Payments | Q43: =SUM(Q5:Q32)-Q32 -> #REF!
A44: =A43+1 -> 46134 | B44: 30 | C44: =H43 -> 35000 | D44: =(($C$6/360))*C44 -> 23.333333 | E44: 0 | F44: =IFERROR(-VLOOKUP(A44,$P$4:$R$12,2,FALSE),0) -> 0 | G44: =IF(G43-D44-E44>0,G43-D44-E44,0) -> 7700 | H44: =IF(G44>0,C44+F44+I44,SUM(C44:F44)-G43) -> 35000 | I44: 0 | J44: =H44-IF(I$8-G44<Q$42,I$8-Q$42,G44) -> 29400 | K44: =$L$3/($C$11-$C$8) -> 70 | L44: =L43+D44 -> 700 | M44: =IF($I$8>L44,L44,$I$8) -> 700 | N44: =N43+D44+K44+I44 -> 2800 | P44: principal Outstanding | Q44: =IF(-Q37-Q43>0,-Q37-Q43,0) -> #REF!
A45: =A44+1 -> 46135 | B45: 31 | C45: =H44 -> 35000 | D45: =(($C$6/360))*C45 -> 23.333333 | E45: 0 | F45: =IFERROR(-VLOOKUP(A45,$P$4:$R$12,2,FALSE),0) -> 0 | G45: =IF(G44-D45-E45>0,G44-D45-E45,0) -> 7676.6667 | H45: =IF(G45>0,C45+F45+I45,SUM(C45:F45)-G44) -> 35000 | I45: 0 | J45: =H45-IF(I$8-G45<Q$42,I$8-Q$42,G45) -> 29400 | K45: =$L$3/($C$11-$C$8) -> 70 | L45: =L44+D45 -> 723.33333 | M45: =IF($I$8>L45,L45,$I$8) -> 723.33333 | N45: =N44+D45+K45+I45 -> 2893.3333 | P45: Return on Invesment | Q45: =IF(Q32>C4,(Q32-C4)/C4,"NA") -> #REF!
A46: =A45+1 -> 46136 | B46: 32 | C46: =H45 -> 35000 | D46: =(($C$6/360))*C46 -> 23.333333 | E46: 0 | F46: =IFERROR(-VLOOKUP(A46,$P$4:$R$12,2,FALSE),0) -> 0 | G46: =IF(G45-D46-E46>0,G45-D46-E46,0) -> 7653.3333 | H46: =IF(G46>0,C46+F46+I46,SUM(C46:F46)-G45) -> 35000 | I46: 0 | J46: =H46-IF(I$8-G46<Q$42,I$8-Q$42,G46) -> 29400 | K46: =$L$3/($C$11-$C$8) -> 70 | L46: =L45+D46 -> 746.66667 | M46: =IF($I$8>L46,L46,$I$8) -> 746.66667 | N46: =N45+D46+K46+I46 -> 2986.6667 | P46: Annualized ROI | Q46: =IF(Q32>C4,Q45/(Q40/360),"NA") -> #REF!
A47: =A46+1 -> 46137 | B47: 33 | C47: =H46 -> 35000 | D47: =(($C$6/360))*C47 -> 23.333333 | E47: 0 | F47: =IFERROR(-VLOOKUP(A47,$P$4:$R$12,2,FALSE),0) -> 0 | G47: =IF(G46-D47-E47>0,G46-D47-E47,0) -> 7630 | H47: =IF(G47>0,C47+F47+I47,SUM(C47:F47)-G46) -> 35000 | I47: 0 | J47: =H47-IF(I$8-G47<Q$42,I$8-Q$42,G47) -> 29400 | K47: =$L$3/($C$11-$C$8) -> 70 | L47: =L46+D47 -> 770 | M47: =IF($I$8>L47,L47,$I$8) -> 770 | N47: =N46+D47+K47+I47 -> 3080 | P47: Int. Reserve Balance | Q47: =VLOOKUP(Q36,$A$15:$H$853,7,FALSE) -> 8376.6667
A48: =A47+1 -> 46138 | B48: 34 | C48: =H47 -> 35000 | D48: =(($C$6/360))*C48 -> 23.333333 | E48: 0 | F48: =IFERROR(-VLOOKUP(A48,$P$4:$R$12,2,FALSE),0) -> 0 | G48: =IF(G47-D48-E48>0,G47-D48-E48,0) -> 7606.6667 | H48: =IF(G48>0,C48+F48+I48,SUM(C48:F48)-G47) -> 35000 | I48: 0 | J48: =H48-IF(I$8-G48<Q$42,I$8-Q$42,G48) -> 29400 | K48: =$L$3/($C$11-$C$8) -> 70 | L48: =L47+D48 -> 793.33333 | M48: =IF($I$8>L48,L48,$I$8) -> 793.33333 | N48: =N47+D48+K48+I48 -> 3173.3333 | P48: Inside 4 Month Min. | Q48: =IF(Q36<(C8+120),1,0) -> 1
A49: =A48+1 -> 46139 | B49: 35 | C49: =H48 -> 35000 | D49: =(($C$6/360))*C49 -> 23.333333 | E49: 0 | F49: =IFERROR(-VLOOKUP(A49,$P$4:$R$12,2,FALSE),0) -> 0 | G49: =IF(G48-D49-E49>0,G48-D49-E49,0) -> 7583.3333 | H49: =IF(G49>0,C49+F49+I49,SUM(C49:F49)-G48) -> 35000 | I49: 0 | J49: =H49-IF(I$8-G49<Q$42,I$8-Q$42,G49) -> 29400 | K49: =$L$3/($C$11-$C$8) -> 70 | L49: =L48+D49 -> 816.66667 | M49: =IF($I$8>L49,L49,$I$8) -> 816.66667 | N49: =N48+D49+K49+I49 -> 3266.6667 | P49: Today | Q49: Maturity | R49: Maturity + 90 | S49: Maturity + 180 | T49: Maturity + 270
A50: =A49+1 -> 46140 | B50: 36 | C50: =H49 -> 35000 | D50: =(($C$6/360))*C50 -> 23.333333 | E50: 0 | F50: =IFERROR(-VLOOKUP(A50,$P$4:$R$12,2,FALSE),0) -> 0 | G50: =IF(G49-D50-E50>0,G49-D50-E50,0) -> 7560 | H50: =IF(G50>0,C50+F50+I50,SUM(C50:F50)-G49) -> 35000 | I50: 0 | J50: =H50-IF(I$8-G50<Q$42,I$8-Q$42,G50) -> 29400 | K50: =$L$3/($C$11-$C$8) -> 70 | L50: =L49+D50 -> 840 | M50: =IF($I$8>L50,L50,$I$8) -> 840 | N50: =N49+D50+K50+I50 -> 3360 | P50: =Q36 -> 46105 | Q50: =U24 -> 46470 | R50: =Q50+90 -> 46560 | S50: =R50+90 -> 46650 | T50: =S50+90 -> 46740 | U50: =Q39 -> 23.333333
A51: =A50+1 -> 46141 | B51: 37 | C51: =H50 -> 35000 | D51: =(($C$6/360))*C51 -> 23.333333 | E51: 0 | F51: =IFERROR(-VLOOKUP(A51,$P$4:$R$12,2,FALSE),0) -> 0 | G51: =IF(G50-D51-E51>0,G50-D51-E51,0) -> 7536.6667 | H51: =IF(G51>0,C51+F51+I51,SUM(C51:F51)-G50) -> 35000 | I51: 0 | J51: =H51-IF(I$8-G51<Q$42,I$8-Q$42,G51) -> 29400 | K51: =$L$3/($C$11-$C$8) -> 70 | L51: =L50+D51 -> 863.33333 | M51: =IF($I$8>L51,L51,$I$8) -> 863.33333 | N51: =N50+D51+K51+I51 -> 3453.3333 | P51: =Q38 -> 29400 | Q51: =Y17 -> 35140.234 | R51: =VLOOKUP(R50,$A$15:$H$553,8,TRUE) -> 37312.438 | S51: =VLOOKUP(S50,$A$15:$H$850,8,TRUE) -> 39618.919 | T51: =VLOOKUP(T50,$A$15:$H$950,8,TRUE) -> 42067.975 | U51: 0
A52: =A51+1 -> 46142 | B52: 38 | C52: =H51 -> 35000 | D52: =(($C$6/360))*C52 -> 23.333333 | E52: 0 | F52: =IFERROR(-VLOOKUP(A52,$P$4:$R$12,2,FALSE),0) -> 0 | G52: =IF(G51-D52-E52>0,G51-D52-E52,0) -> 7513.3333 | H52: =IF(G52>0,C52+F52+I52,SUM(C52:F52)-G51) -> 35000 | I52: 0 | J52: =H52-IF(I$8-G52<Q$42,I$8-Q$42,G52) -> 29400 | K52: =$L$3/($C$11-$C$8) -> 70 | L52: =L51+D52 -> 886.66667 | M52: =IF($I$8>L52,L52,$I$8) -> 886.66667 | N52: =N51+D52+K52+I52 -> 3546.6667
A53: =A52+1 -> 46143 | B53: 39 | C53: =H52 -> 35000 | D53: =(($C$6/360))*C53 -> 23.333333 | E53: 0 | F53: =IFERROR(-VLOOKUP(A53,$P$4:$R$12,2,FALSE),0) -> 0 | G53: =IF(G52-D53-E53>0,G52-D53-E53,0) -> 7490 | H53: =IF(G53>0,C53+F53+I53,SUM(C53:F53)-G52) -> 35000 | I53: 0 | J53: =H53-IF(I$8-G53<Q$42,I$8-Q$42,G53) -> 29400 | K53: =$L$3/($C$11-$C$8) -> 70 | L53: =L52+D53 -> 910 | M53: =IF($I$8>L53,L53,$I$8) -> 910 | N53: =N52+D53+K53+I53 -> 3640
A54: =A53+1 -> 46144 | B54: 40 | C54: =H53 -> 35000 | D54: =(($C$6/360))*C54 -> 23.333333 | E54: 0 | F54: =IFERROR(-VLOOKUP(A54,$P$4:$R$12,2,FALSE),0) -> 0 | G54: =IF(G53-D54-E54>0,G53-D54-E54,0) -> 7466.6667 | H54: =IF(G54>0,C54+F54+I54,SUM(C54:F54)-G53) -> 35000 | I54: 0 | J54: =H54-IF(I$8-G54<Q$42,I$8-Q$42,G54) -> 29400 | K54: =$L$3/($C$11-$C$8) -> 70 | L54: =L53+D54 -> 933.33333 | M54: =IF($I$8>L54,L54,$I$8) -> 933.33333 | N54: =N53+D54+K54+I54 -> 3733.3333
A55: =A54+1 -> 46145 | B55: 41 | C55: =H54 -> 35000 | D55: =(($C$6/360))*C55 -> 23.333333 | E55: 0 | F55: =IFERROR(-VLOOKUP(A55,$P$4:$R$12,2,FALSE),0) -> 0 | G55: =IF(G54-D55-E55>0,G54-D55-E55,0) -> 7443.3333 | H55: =IF(G55>0,C55+F55+I55,SUM(C55:F55)-G54) -> 35000 | I55: 0 | J55: =H55-IF(I$8-G55<Q$42,I$8-Q$42,G55) -> 29400 | K55: =$L$3/($C$11-$C$8) -> 70 | L55: =L54+D55 -> 956.66667 | M55: =IF($I$8>L55,L55,$I$8) -> 956.66667 | N55: =N54+D55+K55+I55 -> 3826.6667
A56: =A55+1 -> 46146 | B56: 42 | C56: =H55 -> 35000 | D56: =(($C$6/360))*C56 -> 23.333333 | E56: 0 | F56: =IFERROR(-VLOOKUP(A56,$P$4:$R$12,2,FALSE),0) -> 0 | G56: =IF(G55-D56-E56>0,G55-D56-E56,0) -> 7420 | H56: =IF(G56>0,C56+F56+I56,SUM(C56:F56)-G55) -> 35000 | I56: 0 | J56: =H56-IF(I$8-G56<Q$42,I$8-Q$42,G56) -> 29400 | K56: =$L$3/($C$11-$C$8) -> 70 | L56: =L55+D56 -> 980 | M56: =IF($I$8>L56,L56,$I$8) -> 980 | N56: =N55+D56+K56+I56 -> 3920
A57: =A56+1 -> 46147 | B57: 43 | C57: =H56 -> 35000 | D57: =(($C$6/360))*C57 -> 23.333333 | E57: 0 | F57: =IFERROR(-VLOOKUP(A57,$P$4:$R$12,2,FALSE),0) -> 0 | G57: =IF(G56-D57-E57>0,G56-D57-E57,0) -> 7396.6667 | H57: =IF(G57>0,C57+F57+I57,SUM(C57:F57)-G56) -> 35000 | I57: 0 | J57: =H57-IF(I$8-G57<Q$42,I$8-Q$42,G57) -> 29400 | K57: =$L$3/($C$11-$C$8) -> 70 | L57: =L56+D57 -> 1003.3333 | M57: =IF($I$8>L57,L57,$I$8) -> 1003.3333 | N57: =N56+D57+K57+I57 -> 4013.3333
A58: =A57+1 -> 46148 | B58: 44 | C58: =H57 -> 35000 | D58: =(($C$6/360))*C58 -> 23.333333 | E58: 0 | F58: =IFERROR(-VLOOKUP(A58,$P$4:$R$12,2,FALSE),0) -> 0 | G58: =IF(G57-D58-E58>0,G57-D58-E58,0) -> 7373.3333 | H58: =IF(G58>0,C58+F58+I58,SUM(C58:F58)-G57) -> 35000 | I58: 0 | J58: =H58-IF(I$8-G58<Q$42,I$8-Q$42,G58) -> 29400 | K58: =$L$3/($C$11-$C$8) -> 70 | L58: =L57+D58 -> 1026.6667 | M58: =IF($I$8>L58,L58,$I$8) -> 1026.6667 | N58: =N57+D58+K58+I58 -> 4106.6667
A59: =A58+1 -> 46149 | B59: 45 | C59: =H58 -> 35000 | D59: =(($C$6/360))*C59 -> 23.333333 | E59: 0 | F59: =IFERROR(-VLOOKUP(A59,$P$4:$R$12,2,FALSE),0) -> 0 | G59: =IF(G58-D59-E59>0,G58-D59-E59,0) -> 7350 | H59: =IF(G59>0,C59+F59+I59,SUM(C59:F59)-G58) -> 35000 | I59: 0 | J59: =H59-IF(I$8-G59<Q$42,I$8-Q$42,G59) -> 29400 | K59: =$L$3/($C$11-$C$8) -> 70 | L59: =L58+D59 -> 1050 | M59: =IF($I$8>L59,L59,$I$8) -> 1050 | N59: =N58+D59+K59+I59 -> 4200
A60: =A59+1 -> 46150 | B60: 46 | C60: =H59 -> 35000 | D60: =(($C$6/360))*C60 -> 23.333333 | E60: 0 | F60: =IFERROR(-VLOOKUP(A60,$P$4:$R$12,2,FALSE),0) -> 0 | G60: =IF(G59-D60-E60>0,G59-D60-E60,0) -> 7326.6667 | H60: =IF(G60>0,C60+F60+I60,SUM(C60:F60)-G59) -> 35000 | I60: 0 | J60: =H60-IF(I$8-G60<Q$42,I$8-Q$42,G60) -> 29400 | K60: =$L$3/($C$11-$C$8) -> 70 | L60: =L59+D60 -> 1073.3333 | M60: =IF($I$8>L60,L60,$I$8) -> 1073.3333 | N60: =N59+D60+K60+I60 -> 4293.3333
A61: =A60+1 -> 46151 | B61: 47 | C61: =H60 -> 35000 | D61: =(($C$6/360))*C61 -> 23.333333 | E61: 0 | F61: =IFERROR(-VLOOKUP(A61,$P$4:$R$12,2,FALSE),0) -> 0 | G61: =IF(G60-D61-E61>0,G60-D61-E61,0) -> 7303.3333 | H61: =IF(G61>0,C61+F61+I61,SUM(C61:F61)-G60) -> 35000 | I61: 0 | J61: =H61-IF(I$8-G61<Q$42,I$8-Q$42,G61) -> 29400 | K61: =$L$3/($C$11-$C$8) -> 70 | L61: =L60+D61 -> 1096.6667 | M61: =IF($I$8>L61,L61,$I$8) -> 1096.6667 | N61: =N60+D61+K61+I61 -> 4386.6667
A62: =A61+1 -> 46152 | B62: 48 | C62: =H61 -> 35000 | D62: =(($C$6/360))*C62 -> 23.333333 | E62: 0 | F62: =IFERROR(-VLOOKUP(A62,$P$4:$R$12,2,FALSE),0) -> 0 | G62: =IF(G61-D62-E62>0,G61-D62-E62,0) -> 7280 | H62: =IF(G62>0,C62+F62+I62,SUM(C62:F62)-G61) -> 35000 | I62: 0 | J62: =H62-IF(I$8-G62<Q$42,I$8-Q$42,G62) -> 29400 | K62: =$L$3/($C$11-$C$8) -> 70 | L62: =L61+D62 -> 1120 | M62: =IF($I$8>L62,L62,$I$8) -> 1120 | N62: =N61+D62+K62+I62 -> 4480
A63: =A62+1 -> 46153 | B63: 49 | C63: =H62 -> 35000 | D63: =(($C$6/360))*C63 -> 23.333333 | E63: 0 | F63: =IFERROR(-VLOOKUP(A63,$P$4:$R$12,2,FALSE),0) -> 0 | G63: =IF(G62-D63-E63>0,G62-D63-E63,0) -> 7256.6667 | H63: =IF(G63>0,C63+F63+I63,SUM(C63:F63)-G62) -> 35000 | I63: 0 | J63: =H63-IF(I$8-G63<Q$42,I$8-Q$42,G63) -> 29400 | K63: =$L$3/($C$11-$C$8) -> 70 | L63: =L62+D63 -> 1143.3333 | M63: =IF($I$8>L63,L63,$I$8) -> 1143.3333 | N63: =N62+D63+K63+I63 -> 4573.3333
... A147: =A146+1 -> 46237 | B147: 133 | C147: =H146 -> 35000 | D147: =(($C$6/360))*C147 -> 23.333333 | E147: 0 | F147: =IFERROR(-VLOOKUP(A147,$P$4:$R$12,2,FALSE),0) -> 0 | G147: =IF(G146-D147-E147>0,G146-D147-E147,0) -> 5296.6667 | H147: =IF(G147>0,C147+F147+I147,SUM(C147:F147)-G146) -> 35000 | I147: 0 | J147: =H147-IF(I$8-G147<Q$42,I$8-Q$42,G147) -> 29703.333 | K147: =$L$3/($C$11-$C$8) -> 70 | L147: =L146+D147 -> 3103.3333 | M147: =IF($I$8>L147,L147,$I$8) -> 3103.3333 | N147: =N146+D147+K147+I147 -> 12413.333
A148: =A147+1 -> 46238 | B148: 134 | C148: =H147 -> 35000 | D148: =(($C$6/360))*C148 -> 23.333333 | E148: 0 | F148: =IFERROR(-VLOOKUP(A148,$P$4:$R$12,2,FALSE),0) -> 0 | G148: =IF(G147-D148-E148>0,G147-D148-E148,0) -> 5273.3333 | H148: =IF(G148>0,C148+F148+I148,SUM(C148:F148)-G147) -> 35000 | I148: 0 | J148: =H148-IF(I$8-G148<Q$42,I$8-Q$42,G148) -> 29726.667 | K148: =$L$3/($C$11-$C$8) -> 70 | L148: =L147+D148 -> 3126.6667 | M148: =IF($I$8>L148,L148,$I$8) -> 3126.6667 | N148: =N147+D148+K148+I148 -> 12506.667 | Q148: =SUM(Q4:Q5) -> -33950
A149: =A148+1 -> 46239 | B149: 135 | C149: =H148 -> 35000 | D149: =(($C$6/360))*C149 -> 23.333333 | E149: 0 | F149: =IFERROR(-VLOOKUP(A149,$P$4:$R$12,2,FALSE),0) -> 0 | G149: =IF(G148-D149-E149>0,G148-D149-E149,0) -> 5250 | H149: =IF(G149>0,C149+F149+I149,SUM(C149:F149)-G148) -> 35000 | I149: 0 | J149: =H149-IF(I$8-G149<Q$42,I$8-Q$42,G149) -> 29750 | K149: =$L$3/($C$11-$C$8) -> 70 | L149: =L148+D149 -> 3150 | M149: =IF($I$8>L149,L149,$I$8) -> 3150 | N149: =N148+D149+K149+I149 -> 12600 | Q149: =Q148+H137 -> 1050
A150: =A149+1 -> 46240 | B150: 136 | C150: =H149 -> 35000 | D150: =(($C$6/360))*C150 -> 23.333333 | E150: 0 | F150: =IFERROR(-VLOOKUP(A150,$P$4:$R$12,2,FALSE),0) -> 0 | G150: =IF(G149-D150-E150>0,G149-D150-E150,0) -> 5226.6667 | H150: =IF(G150>0,C150+F150+I150,SUM(C150:F150)-G149) -> 35000 | I150: 0 | J150: =H150-IF(I$8-G150<Q$42,I$8-Q$42,G150) -> 29773.333 | K150: =$L$3/($C$11-$C$8) -> 70 | L150: =L149+D150 -> 3173.3333 | M150: =IF($I$8>L150,L150,$I$8) -> 3173.3333 | N150: =N149+D150+K150+I150 -> 12693.333
A151: =A150+1 -> 46241 | B151: 137 | C151: =H150 -> 35000 | D151: =(($C$6/360))*C151 -> 23.333333 | E151: 0 | F151: =IFERROR(-VLOOKUP(A151,$P$4:$R$12,2,FALSE),0) -> 0 | G151: =IF(G150-D151-E151>0,G150-D151-E151,0) -> 5203.3333 | H151: =IF(G151>0,C151+F151+I151,SUM(C151:F151)-G150) -> 35000 | I151: 0 | J151: =H151-IF(I$8-G151<Q$42,I$8-Q$42,G151) -> 29796.667 | K151: =$L$3/($C$11-$C$8) -> 70 | L151: =L150+D151 -> 3196.6667 | M151: =IF($I$8>L151,L151,$I$8) -> 3196.6667 | N151: =N150+D151+K151+I151 -> 12786.667
A152: =A151+1 -> 46242 | B152: 138 | C152: =H151 -> 35000 | D152: =(($C$6/360))*C152 -> 23.333333 | E152: 0 | F152: =IFERROR(-VLOOKUP(A152,$P$4:$R$12,2,FALSE),0) -> 0 | G152: =IF(G151-D152-E152>0,G151-D152-E152,0) -> 5180 | H152: =IF(G152>0,C152+F152+I152,SUM(C152:F152)-G151) -> 35000 | I152: 0 | J152: =H152-IF(I$8-G152<Q$42,I$8-Q$42,G152) -> 29820 | K152: =$L$3/($C$11-$C$8) -> 70 | L152: =L151+D152 -> 3220 | M152: =IF($I$8>L152,L152,$I$8) -> 3220 | N152: =N151+D152+K152+I152 -> 12880
A153: =A152+1 -> 46243 | B153: 139 | C153: =H152 -> 35000 | D153: =(($C$6/360))*C153 -> 23.333333 | E153: 0 | F153: =IFERROR(-VLOOKUP(A153,$P$4:$R$12,2,FALSE),0) -> 0 | G153: =IF(G152-D153-E153>0,G152-D153-E153,0) -> 5156.6667 | H153: =IF(G153>0,C153+F153+I153,SUM(C153:F153)-G152) -> 35000 | I153: 0 | J153: =H153-IF(I$8-G153<Q$42,I$8-Q$42,G153) -> 29843.333 | K153: =$L$3/($C$11-$C$8) -> 70 | L153: =L152+D153 -> 3243.3333 | M153: =IF($I$8>L153,L153,$I$8) -> 3243.3333 | N153: =N152+D153+K153+I153 -> 12973.333
A154: =A153+1 -> 46244 | B154: 140 | C154: =H153 -> 35000 | D154: =(($C$6/360))*C154 -> 23.333333 | E154: 0 | F154: =IFERROR(-VLOOKUP(A154,$P$4:$R$12,2,FALSE),0) -> 0 | G154: =IF(G153-D154-E154>0,G153-D154-E154,0) -> 5133.3333 | H154: =IF(G154>0,C154+F154+I154,SUM(C154:F154)-G153) -> 35000 | I154: 0 | J154: =H154-IF(I$8-G154<Q$42,I$8-Q$42,G154) -> 29866.667 | K154: =$L$3/($C$11-$C$8) -> 70 | L154: =L153+D154 -> 3266.6667 | M154: =IF($I$8>L154,L154,$I$8) -> 3266.6667 | N154: =N153+D154+K154+I154 -> 13066.667
A155: =A154+1 -> 46245 | B155: 141 | C155: =H154 -> 35000 | D155: =(($C$6/360))*C155 -> 23.333333 | E155: 0 | F155: =IFERROR(-VLOOKUP(A155,$P$4:$R$12,2,FALSE),0) -> 0 | G155: =IF(G154-D155-E155>0,G154-D155-E155,0) -> 5110 | H155: =IF(G155>0,C155+F155+I155,SUM(C155:F155)-G154) -> 35000 | I155: 0 | J155: =H155-IF(I$8-G155<Q$42,I$8-Q$42,G155) -> 29890 | K155: =$L$3/($C$11-$C$8) -> 70 | L155: =L154+D155 -> 3290 | M155: =IF($I$8>L155,L155,$I$8) -> 3290 | N155: =N154+D155+K155+I155 -> 13160
A156: =A155+1 -> 46246 | B156: 142 | C156: =H155 -> 35000 | D156: =(($C$6/360))*C156 -> 23.333333 | E156: 0 | F156: =IFERROR(-VLOOKUP(A156,$P$4:$R$12,2,FALSE),0) -> 0 | G156: =IF(G155-D156-E156>0,G155-D156-E156,0) -> 5086.6667 | H156: =IF(G156>0,C156+F156+I156,SUM(C156:F156)-G155) -> 35000 | I156: 0 | J156: =H156-IF(I$8-G156<Q$42,I$8-Q$42,G156) -> 29913.333 | K156: =$L$3/($C$11-$C$8) -> 70 | L156: =L155+D156 -> 3313.3333 | M156: =IF($I$8>L156,L156,$I$8) -> 3313.3333 | N156: =N155+D156+K156+I156 -> 13253.333
A157: =A156+1 -> 46247 | B157: 143 | C157: =H156 -> 35000 | D157: =(($C$6/360))*C157 -> 23.333333 | E157: 0 | F157: =IFERROR(-VLOOKUP(A157,$P$4:$R$12,2,FALSE),0) -> 0 | G157: =IF(G156-D157-E157>0,G156-D157-E157,0) -> 5063.3333 | H157: =IF(G157>0,C157+F157+I157,SUM(C157:F157)-G156) -> 35000 | I157: 0 | J157: =H157-IF(I$8-G157<Q$42,I$8-Q$42,G157) -> 29936.667 | K157: =$L$3/($C$11-$C$8) -> 70 | L157: =L156+D157 -> 3336.6667 | M157: =IF($I$8>L157,L157,$I$8) -> 3336.6667 | N157: =N156+D157+K157+I157 -> 13346.667
A158: =A157+1 -> 46248 | B158: 144 | C158: =H157 -> 35000 | D158: =(($C$6/360))*C158 -> 23.333333 | E158: 0 | F158: =IFERROR(-VLOOKUP(A158,$P$4:$R$12,2,FALSE),0) -> 0 | G158: =IF(G157-D158-E158>0,G157-D158-E158,0) -> 5040 | H158: =IF(G158>0,C158+F158+I158,SUM(C158:F158)-G157) -> 35000 | I158: 0 | J158: =H158-IF(I$8-G158<Q$42,I$8-Q$42,G158) -> 29960 | K158: =$L$3/($C$11-$C$8) -> 70 | L158: =L157+D158 -> 3360 | M158: =IF($I$8>L158,L158,$I$8) -> 3360 | N158: =N157+D158+K158+I158 -> 13440
A159: =A158+1 -> 46249 | B159: 145 | C159: =H158 -> 35000 | D159: =(($C$6/360))*C159 -> 23.333333 | E159: 0 | F159: =IFERROR(-VLOOKUP(A159,$P$4:$R$12,2,FALSE),0) -> 0 | G159: =IF(G158-D159-E159>0,G158-D159-E159,0) -> 5016.6667 | H159: =IF(G159>0,C159+F159+I159,SUM(C159:F159)-G158) -> 35000 | I159: 0 | J159: =H159-IF(I$8-G159<Q$42,I$8-Q$42,G159) -> 29983.333 | K159: =$L$3/($C$11-$C$8) -> 70 | L159: =L158+D159 -> 3383.3333 | M159: =IF($I$8>L159,L159,$I$8) -> 3383.3333 | N159: =N158+D159+K159+I159 -> 13533.333
A160: =A159+1 -> 46250 | B160: 146 | C160: =H159 -> 35000 | D160: =(($C$6/360))*C160 -> 23.333333 | E160: 0 | F160: =IFERROR(-VLOOKUP(A160,$P$4:$R$12,2,FALSE),0) -> 0 | G160: =IF(G159-D160-E160>0,G159-D160-E160,0) -> 4993.3333 | H160: =IF(G160>0,C160+F160+I160,SUM(C160:F160)-G159) -> 35000 | I160: 0 | J160: =H160-IF(I$8-G160<Q$42,I$8-Q$42,G160) -> 30006.667 | K160: =$L$3/($C$11-$C$8) -> 70 | L160: =L159+D160 -> 3406.6667 | M160: =IF($I$8>L160,L160,$I$8) -> 3406.6667 | N160: =N159+D160+K160+I160 -> 13626.667
A161: =A160+1 -> 46251 | B161: 147 | C161: =H160 -> 35000 | D161: =(($C$6/360))*C161 -> 23.333333 | E161: 0 | F161: =IFERROR(-VLOOKUP(A161,$P$4:$R$12,2,FALSE),0) -> 0 | G161: =IF(G160-D161-E161>0,G160-D161-E161,0) -> 4970 | H161: =IF(G161>0,C161+F161+I161,SUM(C161:F161)-G160) -> 35000 | I161: 0 | J161: =H161-IF(I$8-G161<Q$42,I$8-Q$42,G161) -> 30030 | K161: =$L$3/($C$11-$C$8) -> 70 | L161: =L160+D161 -> 3430 | M161: =IF($I$8>L161,L161,$I$8) -> 3430 | N161: =N160+D161+K161+I161 -> 13720
... A491: =A490+1 -> 46581 | B491: 477 | C491: =H490 -> 37813.101 | D491: =(($C$6/360))*C491 -> 25.208734 | E491: 0 | F491: =IFERROR(-VLOOKUP(A491,$P$4:$R$12,2,FALSE),0) -> 0 | G491: =IF(G490-D491-E491>0,G490-D491-E491,0) -> 0 | H491: =IF(G491>0,C491+F491+I491,SUM(C491:F491)-G490) -> 37838.31 | I491: 0 | J491: =H491-IF(I$8-G491<Q$42,I$8-Q$42,G491) -> 37838.31 | K491: =$L$3/($C$11-$C$8) -> 70 | L491: =L490+D491 -> 11238.31 | M491: =IF($I$8>L491,L491,$I$8) -> 8400 | N491: =N490+D491+K491+I491 -> 44628.31
A492: =A491+1 -> 46582 | B492: 478 | C492: =H491 -> 37838.31 | D492: =(($C$6/360))*C492 -> 25.22554 | E492: 0 | F492: =IFERROR(-VLOOKUP(A492,$P$4:$R$31,2,FALSE),0) -> 0 | G492: =IF(G491-D492-E492>0,G491-D492-E492,0) -> 0 | H492: =IF(G492>0,C492+F492+I492,SUM(C492:F492)-G491) -> 37863.535 | I492: 0 | J492: =H492-IF(I$8-G492<Q$42,I$8-Q$42,G492) -> 37863.535 | K492: =$L$3/($C$11-$C$8) -> 70 | L492: =L491+D492 -> 11263.535 | M492: =IF($I$8>L492,L492,$I$8) -> 8400 | N492: =N491+D492+K492+I492 -> 44723.535
A493: =A492+1 -> 46583 | B493: 479 | C493: =H492 -> 37863.535 | D493: =(($C$6/360))*C493 -> 25.242357 | E493: 0 | F493: =IFERROR(-VLOOKUP(A493,$P$4:$R$31,2,FALSE),0) -> 0 | G493: =IF(G492-D493-E493>0,G492-D493-E493,0) -> 0 | H493: =IF(G493>0,C493+F493+I493,SUM(C493:F493)-G492) -> 37888.778 | I493: 0 | J493: =H493-IF(I$8-G493<Q$42,I$8-Q$42,G493) -> 37888.778 | K493: =$L$3/($C$11-$C$8) -> 70 | L493: =L492+D493 -> 11288.778 | M493: =IF($I$8>L493,L493,$I$8) -> 8400 | N493: =N492+D493+K493+I493 -> 44818.778
A494: =A493+1 -> 46584 | B494: 480 | C494: =H493 -> 37888.778 | D494: =(($C$6/360))*C494 -> 25.259185 | E494: 0 | F494: =IFERROR(-VLOOKUP(A494,$P$4:$R$31,2,FALSE),0) -> 0 | G494: =IF(G493-D494-E494>0,G493-D494-E494,0) -> 0 | H494: =IF(G494>0,C494+F494+I494,SUM(C494:F494)-G493) -> 37914.037 | I494: 0 | J494: =H494-IF(I$8-G494<Q$42,I$8-Q$42,G494) -> 37914.037 | K494: =$L$3/($C$11-$C$8) -> 70 | L494: =L493+D494 -> 11314.037 | M494: =IF($I$8>L494,L494,$I$8) -> 8400 | N494: =N493+D494+K494+I494 -> 44914.037
A495: =A494+1 -> 46585 | B495: 481 | C495: =H494 -> 37914.037 | D495: =(($C$6/360))*C495 -> 25.276025 | E495: 0 | F495: =IFERROR(-VLOOKUP(A495,$P$4:$R$31,2,FALSE),0) -> 0 | G495: =IF(G494-D495-E495>0,G494-D495-E495,0) -> 0 | H495: =IF(G495>0,C495+F495+I495,SUM(C495:F495)-G494) -> 37939.313 | I495: 0 | J495: =H495-IF(I$8-G495<Q$42,I$8-Q$42,G495) -> 37939.313 | K495: =$L$3/($C$11-$C$8) -> 70 | L495: =L494+D495 -> 11339.313 | M495: =IF($I$8>L495,L495,$I$8) -> 8400 | N495: =N494+D495+K495+I495 -> 45009.313
A496: =A495+1 -> 46586 | B496: 482 | C496: =H495 -> 37939.313 | D496: =(($C$6/360))*C496 -> 25.292875 | E496: 0 | F496: =IFERROR(-VLOOKUP(A496,$P$4:$R$31,2,FALSE),0) -> 0 | G496: =IF(G495-D496-E496>0,G495-D496-E496,0) -> 0 | H496: =IF(G496>0,C496+F496+I496,SUM(C496:F496)-G495) -> 37964.606 | I496: 0 | J496: =H496-IF(I$8-G496<Q$42,I$8-Q$42,G496) -> 37964.606 | K496: =$L$3/($C$11-$C$8) -> 70 | L496: =L495+D496 -> 11364.606 | M496: =IF($I$8>L496,L496,$I$8) -> 8400 | N496: =N495+D496+K496+I496 -> 45104.606
A497: =A496+1 -> 46587 | B497: 483 | C497: =H496 -> 37964.606 | D497: =(($C$6/360))*C497 -> 25.309737 | E497: 0 | F497: =IFERROR(-VLOOKUP(A497,$P$4:$R$31,2,FALSE),0) -> 0 | G497: =IF(G496-D497-E497>0,G496-D497-E497,0) -> 0 | H497: =IF(G497>0,C497+F497+I497,SUM(C497:F497)-G496) -> 37989.915 | I497: 0 | J497: =H497-IF(I$8-G497<Q$42,I$8-Q$42,G497) -> 37989.915 | K497: =$L$3/($C$11-$C$8) -> 70 | L497: =L496+D497 -> 11389.915 | M497: =IF($I$8>L497,L497,$I$8) -> 8400 | N497: =N496+D497+K497+I497 -> 45199.915
A498: =A497+1 -> 46588 | B498: 484 | C498: =H497 -> 37989.915 | D498: =(($C$6/360))*C498 -> 25.32661 | E498: 0 | F498: =IFERROR(-VLOOKUP(A498,$P$4:$R$31,2,FALSE),0) -> 0 | G498: =IF(G497-D498-E498>0,G497-D498-E498,0) -> 0 | H498: =IF(G498>0,C498+F498+I498,SUM(C498:F498)-G497) -> 38015.242 | I498: 0 | J498: =H498-IF(I$8-G498<Q$42,I$8-Q$42,G498) -> 38015.242 | K498: =$L$3/($C$11-$C$8) -> 70 | L498: =L497+D498 -> 11415.242 | M498: =IF($I$8>L498,L498,$I$8) -> 8400 | N498: =N497+D498+K498+I498 -> 45295.242
A499: =A498+1 -> 46589 | B499: 485 | C499: =H498 -> 38015.242 | D499: =(($C$6/360))*C499 -> 25.343495 | E499: 0 | F499: =IFERROR(-VLOOKUP(A499,$P$4:$R$31,2,FALSE),0) -> 0 | G499: =IF(G498-D499-E499>0,G498-D499-E499,0) -> 0 | H499: =IF(G499>0,C499+F499+I499,SUM(C499:F499)-G498) -> 38040.586 | I499: 0 | J499: =H499-IF(I$8-G499<Q$42,I$8-Q$42,G499) -> 38040.586 | K499: =$L$3/($C$11-$C$8) -> 70 | L499: =L498+D499 -> 11440.586 | M499: =IF($I$8>L499,L499,$I$8) -> 8400 | N499: =N498+D499+K499+I499 -> 45390.586
A500: =A499+1 -> 46590 | B500: 486 | C500: =H499 -> 38040.586 | D500: =(($C$6/360))*C500 -> 25.36039 | E500: 0 | F500: =IFERROR(-VLOOKUP(A500,$P$4:$R$31,2,FALSE),0) -> 0 | G500: =IF(G499-D500-E500>0,G499-D500-E500,0) -> 0 | H500: =IF(G500>0,C500+F500+I500,SUM(C500:F500)-G499) -> 38065.946 | I500: 0 | J500: =H500-IF(I$8-G500<Q$42,I$8-Q$42,G500) -> 38065.946 | K500: =$L$3/($C$11-$C$8) -> 70 | L500: =L499+D500 -> 11465.946 | M500: =IF($I$8>L500,L500,$I$8) -> 8400 | N500: =N499+D500+K500+I500 -> 45485.946
A501: =A500+1 -> 46591 | B501: 487 | C501: =H500 -> 38065.946 | D501: =(($C$6/360))*C501 -> 25.377297 | E501: 0 | F501: =IFERROR(-VLOOKUP(A501,$P$4:$R$31,2,FALSE),0) -> 0 | G501: =IF(G500-D501-E501>0,G500-D501-E501,0) -> 0 | H501: =IF(G501>0,C501+F501+I501,SUM(C501:F501)-G500) -> 38091.323 | I501: 0 | J501: =H501-IF(I$8-G501<Q$42,I$8-Q$42,G501) -> 38091.323 | K501: =$L$3/($C$11-$C$8) -> 70 | L501: =L500+D501 -> 11491.323 | M501: =IF($I$8>L501,L501,$I$8) -> 8400 | N501: =N500+D501+K501+I501 -> 45581.323
A502: =A501+1 -> 46592 | B502: 488 | C502: =H501 -> 38091.323 | D502: =(($C$6/360))*C502 -> 25.394215 | E502: 0 | F502: =IFERROR(-VLOOKUP(A502,$P$4:$R$31,2,FALSE),0) -> 0 | G502: =IF(G501-D502-E502>0,G501-D502-E502,0) -> 0 | H502: =IF(G502>0,C502+F502+I502,SUM(C502:F502)-G501) -> 38116.717 | I502: 0 | J502: =H502-IF(I$8-G502<Q$42,I$8-Q$42,G502) -> 38116.717 | K502: =$L$3/($C$11-$C$8) -> 70 | L502: =L501+D502 -> 11516.717 | M502: =IF($I$8>L502,L502,$I$8) -> 8400 | N502: =N501+D502+K502+I502 -> 45676.717
A503: =A502+1 -> 46593 | B503: 489 | C503: =H502 -> 38116.717 | D503: =(($C$6/360))*C503 -> 25.411145 | E503: 0 | F503: =IFERROR(-VLOOKUP(A503,$P$4:$R$31,2,FALSE),0) -> 0 | G503: =IF(G502-D503-E503>0,G502-D503-E503,0) -> 0 | H503: =IF(G503>0,C503+F503+I503,SUM(C503:F503)-G502) -> 38142.129 | I503: 0 | J503: =H503-IF(I$8-G503<Q$42,I$8-Q$42,G503) -> 38142.129 | K503: =$L$3/($C$11-$C$8) -> 70 | L503: =L502+D503 -> 11542.129 | M503: =IF($I$8>L503,L503,$I$8) -> 8400 | N503: =N502+D503+K503+I503 -> 45772.129
... A977: =A976+1 -> 47067 | B977: 963 | C977: =H976 -> 52276.539 | D977: =(($C$6/360))*C977 -> 34.851026 | E977: 0 | F977: =IFERROR(-VLOOKUP(A977,$P$4:$R$31,2,FALSE),0) -> 0 | G977: =IF(G976-D977-E977>0,G976-D977-E977,0) -> 0 | H977: =IF(G977>0,C977+F977+I977,SUM(C977:F977)-G976) -> 52311.39 | I977: 0 | J977: =H977-IF(I$8-G977<Q$42,I$8-Q$42,G977) -> 52311.39 | K977: =$L$3/($C$11-$C$8) -> 70 | L977: =L976+D977 -> 25711.39 | M977: =IF($I$8>L977,L977,$I$8) -> 8400 | N977: =N976+D977+K977+I977 -> 93121.39
A978: =A977+1 -> 47068 | B978: 964 | C978: =H977 -> 52311.39 | D978: =(($C$6/360))*C978 -> 34.87426 | E978: 0 | F978: =IFERROR(-VLOOKUP(A978,$P$4:$R$31,2,FALSE),0) -> 0 | G978: =IF(G977-D978-E978>0,G977-D978-E978,0) -> 0 | H978: =IF(G978>0,C978+F978+I978,SUM(C978:F978)-G977) -> 52346.264 | I978: 0 | J978: =H978-IF(I$8-G978<Q$42,I$8-Q$42,G978) -> 52346.264 | K978: =$L$3/($C$11-$C$8) -> 70 | M978: =IF($I$8>L978,L978,$I$8) -> 0 | N978: =N977+D978+K978+I978 -> 93226.264
A979: =A978+1 -> 47069 | B979: 965 | C979: =H978 -> 52346.264 | D979: =(($C$6/360))*C979 -> 34.897509 | E979: 0 | F979: =IFERROR(-VLOOKUP(A979,$P$4:$R$31,2,FALSE),0) -> 0 | G979: =IF(G978-D979-E979>0,G978-D979-E979,0) -> 0 | H979: =IF(G979>0,C979+F979+I979,SUM(C979:F979)-G978) -> 52381.161 | I979: 0 | J979: =H979-IF(I$8-G979<Q$42,I$8-Q$42,G979) -> 52381.161 | K979: =$L$3/($C$11-$C$8) -> 70 | M979: =IF($I$8>L979,L979,$I$8) -> 0 | N979: =N978+D979+K979+I979 -> 93331.161
A980: =A979+1 -> 47070 | B980: 966 | C980: =H979 -> 52381.161 | D980: =(($C$6/360))*C980 -> 34.920774 | E980: 0 | F980: =IFERROR(-VLOOKUP(A980,$P$4:$R$31,2,FALSE),0) -> 0 | G980: =IF(G979-D980-E980>0,G979-D980-E980,0) -> 0 | H980: =IF(G980>0,C980+F980+I980,SUM(C980:F980)-G979) -> 52416.082 | I980: 0 | J980: =H980-IF(I$8-G980<Q$42,I$8-Q$42,G980) -> 52416.082 | K980: =$L$3/($C$11-$C$8) -> 70 | M980: =IF($I$8>L980,L980,$I$8) -> 0 | N980: =N979+D980+K980+I980 -> 93436.082
A981: =A980+1 -> 47071 | B981: 967 | C981: =H980 -> 52416.082 | D981: =(($C$6/360))*C981 -> 34.944055 | E981: 0 | F981: =IFERROR(-VLOOKUP(A981,$P$4:$R$31,2,FALSE),0) -> 0 | G981: =IF(G980-D981-E981>0,G980-D981-E981,0) -> 0 | H981: =IF(G981>0,C981+F981+I981,SUM(C981:F981)-G980) -> 52451.026 | I981: 0 | J981: =H981-IF(I$8-G981<Q$42,I$8-Q$42,G981) -> 52451.026 | K981: =$L$3/($C$11-$C$8) -> 70 | M981: =IF($I$8>L981,L981,$I$8) -> 0 | N981: =N980+D981+K981+I981 -> 93541.026
A982: =A981+1 -> 47072 | B982: 968 | C982: =H981 -> 52451.026 | D982: =(($C$6/360))*C982 -> 34.967351 | E982: 0 | F982: =IFERROR(-VLOOKUP(A982,$P$4:$R$31,2,FALSE),0) -> 0 | G982: =IF(G981-D982-E982>0,G981-D982-E982,0) -> 0 | H982: =IF(G982>0,C982+F982+I982,SUM(C982:F982)-G981) -> 52485.994 | I982: 0 | J982: =H982-IF(I$8-G982<Q$42,I$8-Q$42,G982) -> 52485.994 | K982: =$L$3/($C$11-$C$8) -> 70 | M982: =IF($I$8>L982,L982,$I$8) -> 0 | N982: =N981+D982+K982+I982 -> 93645.994
A983: =A982+1 -> 47073 | B983: 969 | C983: =H982 -> 52485.994 | D983: =(($C$6/360))*C983 -> 34.990662 | E983: 0 | F983: =IFERROR(-VLOOKUP(A983,$P$4:$R$31,2,FALSE),0) -> 0 | G983: =IF(G982-D983-E983>0,G982-D983-E983,0) -> 0 | H983: =IF(G983>0,C983+F983+I983,SUM(C983:F983)-G982) -> 52520.984 | I983: 0 | J983: =H983-IF(I$8-G983<Q$42,I$8-Q$42,G983) -> 52520.984 | K983: =$L$3/($C$11-$C$8) -> 70 | M983: =IF($I$8>L983,L983,$I$8) -> 0 | N983: =N982+D983+K983+I983 -> 93750.984
A984: =A983+1 -> 47074 | B984: 970 | C984: =H983 -> 52520.984 | D984: =(($C$6/360))*C984 -> 35.013989 | E984: 0 | F984: =IFERROR(-VLOOKUP(A984,$P$4:$R$31,2,FALSE),0) -> 0 | G984: =IF(G983-D984-E984>0,G983-D984-E984,0) -> 0 | H984: =IF(G984>0,C984+F984+I984,SUM(C984:F984)-G983) -> 52555.998 | I984: 0 | J984: =H984-IF(I$8-G984<Q$42,I$8-Q$42,G984) -> 52555.998 | K984: =$L$3/($C$11-$C$8) -> 70 | M984: =IF($I$8>L984,L984,$I$8) -> 0 | N984: =N983+D984+K984+I984 -> 93855.998
A985: =A984+1 -> 47075 | B985: 971 | C985: =H984 -> 52555.998 | D985: =(($C$6/360))*C985 -> 35.037332 | E985: 0 | F985: =IFERROR(-VLOOKUP(A985,$P$4:$R$31,2,FALSE),0) -> 0 | G985: =IF(G984-D985-E985>0,G984-D985-E985,0) -> 0 | H985: =IF(G985>0,C985+F985+I985,SUM(C985:F985)-G984) -> 52591.035 | I985: 0 | J985: =H985-IF(I$8-G985<Q$42,I$8-Q$42,G985) -> 52591.035 | K985: =$L$3/($C$11-$C$8) -> 70 | M985: =IF($I$8>L985,L985,$I$8) -> 0 | N985: =N984+D985+K985+I985 -> 93961.035
...

Sheet Summary
B2: =ProForma!B1 -> 0
B4: Project Summary | F4: Sponsor Information | I4: Strengths
B5: Product Type: | C5: ='Deal Details'!C11 -> 0 | F5: ='Deal Details'!C15 -> 0
B6: Current State: | C6: ='Deal Details'!C12 -> 0
B7: Location: | C7: ='Deal Details'!C6 -> 0 | F7: Project Entity | G7: ='Deal Details'!C16 -> 0
B8: Cross Streets: | C8: ='Deal Details'!C7 -> 0
B10: Units: | C10: ='Deal Details'!C10 -> 0
B12: Summary
I14: Red Flags
B20: Loan Basics | F20: Impairment and Maturity
B21: Length of Loan | C21: ='Deal Details'!C27&" Months" -> 12 Months | F21: Start Date | G21: ='Deal Details'!C31 -> 46105
B22: Requested Cambia Capital | C22: =ProForma!H54 -> $0 | F22: Length of Impairment | G22: =G44 -> 867
B23: Gross First Position Debt | C23: =C50 -> 0 | F23: Impairment Date | G23: {=INDEX('Senior Amort'!A33:A2180,MATCH(TRUE, ('Senior Amort'!I33:I2180+'Mezz Amort'!J15:J2187)>'Deal Details'!F26,0))} -> #N/A
B24: Sponsor Participation | C24: =ProForma!H53 -> 0 | F24: 95% LTV Date | G24: =G51 -> 46876
B25: Sponsor Participation/Unit | C25: =IFERROR(C24/C10,"") | F25: 90% LTV Date | G25: =G59 -> 46397
B26: Project LTV | C26: =ProForma!H65 | F26: Maturity Date | G26: =G21+G27 -> 46470
B27: Project LTV at Maturity | C27: =ProForma!H66 | F27: Project Length (Days) | G27: 365
B29: Exit Revenues | F29: Mezzanine Loan Analysis
C30: Per Unit | D30: Total | F30: Projected IRR at Maturity | G30: =IFERROR('Mezz Amort'!Y18,"")
B31: Sales Price | C31: =ProForma!D28 -> 0 | D31: =ProForma!C28 -> 0 | F31: Cambia Points | G31: =IFERROR('Mezz Amort'!I6,"") -> 350
B32: Size (Sq. Ft) | C32: 3333 | D32: =C32*C10 -> 0 | F32: Due Diligence | G32: 3000
B33: Price/Sq Ft | C33: =C31/C32 -> 0 | D33: =IFERROR(D31/D32,"") | F33: Processing | G33: 1500
B34: Sales Commission % | C34: =ProForma!E37 -> 0 | F34: Cambia Interest | G34: =IFERROR('Mezz Amort'!Y17+'Mezz Amort'!Y4-SUM('Mezz Amort'!I4:I5),"") -> -17359.766
B35: Sales Commission $ | C35: =-C31*$C$34 -> 0 | D35: =-D31*$C$34 -> 0 | F35: Total Cambia Profit | G35: =SUM(G31:G34) -> -12509.766
B36: Net Revenues | C36: =C31+C35 -> 0 | D36: =D31+D35 -> 0 | F36: Senior Loan Profits | G36: =D43 -> 0
F37: Sponsor Profits* | G37: =ProForma!H47 -> -9490.1625
B38: Project Costs | F38: Cambia Loan % | G38: =IFERROR(C22/SUM($C$22:$C$23),"")
C39: Per Unit | D39: Total | F39: Senior Loan % | G39: =IFERROR(C23/SUM($C$22:$C$23),"")
B40: Acquisition Cost | C40: =ProForma!D33 | D40: =ProForma!C33 -> 0
B41: Development Cost Per Unit | C41: =ProForma!D34 | D41: =ProForma!C34 -> 0
B42: Soft Cost Per Unit | C42: =ProForma!D35 | D42: =ProForma!C35 -> 0 | F42: Impairment Calculations
B43: Senior Debt Per Unit | C43: =ProForma!D36 | D43: =ProForma!C36 -> 0 | F43: Impairment Date | G43: =G23 -> #N/A
B44: Sales Cost | C44: =ProForma!D37 | D44: =ProForma!C37 -> 0 | F44: Length of Impairment | G44: 867
B45: Total Cost | C45: =SUM(C40:C44) -> 0 | D45: =ProForma!C41 -> 0 | F45: Cambia Loan at Impairment | G45: =IFERROR(VLOOKUP(G23,'Mezz Amort'!$A$15:$I$1810,7,FALSE),"")
B46: Cost/Sq Ft | C46: =C45/C32 -> 0 | D46: =D45/D32 -> #DIV/0! | F46: Senior Loan at Impairment | G46: =IFERROR(VLOOKUP(G23,'Senior Amort'!$A$33:$I$1835,9,FALSE),"")
F47: Total Loan | G47: =SUM(G45:G46) -> 0
B48: ='Senior Amort'!K7 -> Senior Loan Information | D48: Notes | F48: Net Realizable Value | G48: =D31-D44 -> 0
B49: ='Senior Amort'!K8 -> Institution | C49: ='Deal Details'!C16 -> 0
B50: ='Senior Amort'!K9 -> Total Amount | C50: ='Senior Amort'!L9 -> 0 | F50: 95% CLTV
B51: ='Senior Amort'!K10 -> Rate | C51: ='Senior Amort'!L10 -> 0.12 | F51: Date | G51: =$G$21+G52 -> 46876
B52: ='Senior Amort'!K11 -> Points | C52: ='Senior Amort'!L11 -> 0.03 | F52: Length of Impairment | G52: 771
B53: ='Senior Amort'!K12 -> Origination Fee | C53: ='Senior Amort'!L12 -> 0 | F53: Cambia Loan at Impairment | G53: =IFERROR(VLOOKUP(G51,'Mezz Amort'!$A$15:$I$1810,7,FALSE),"") -> 0
B54: ='Senior Amort'!K13 -> Reserves | C54: ='Senior Amort'!L13 -> 0 | F54: Senior Loan at Impairment | G54: =IFERROR(VLOOKUP(G51,'Senior Amort'!$A$33:$I$1835,9,FALSE),"")
B55: ='Senior Amort'!K14 -> Orig. Maturity Date | C55: ='Senior Amort'!L14 -> 46470 | F55: Total Loan | G55: =SUM(G53:G54) -> 0
B56: ='Senior Amort'!K15 -> Extended Maturity | C56: ='Senior Amort'!L15 -> NA | F56: 95% Net Realizable Value | G56: =G48*0.95 -> 0
B57: ='Senior Amort'!K16 -> Default Interest | C57: ='Senior Amort'!L16 -> 0.24
B58: ='Senior Amort'!K17 -> Extension Fees | C58: ='Senior Amort'!L17 -> 0 | D58: ='Senior Amort'!M17 -> Current LTV | F58: 90% CLTV
B59: ='Senior Amort'!K18 -> Balance | C59: ='Senior Amort'!L18 -> 0 | D59: ='Senior Amort'!M18 -> #DIV/0! | F59: Date | G59: =G21+G60 -> 46397
B60: ='Senior Amort'!K19 -> Left to Draw | C60: ='Senior Amort'!L19 -> #REF! | D60: ='Senior Amort'!M19 -> 0 | F60: Length of Impairment | G60: 292
B61: ='Senior Amort'!K20 -> Valuation | C61: ='Senior Amort'!L20 -> 0 | D61: ='Senior Amort'!M20 -> 0 | F61: Cambia Loan at Impairment | G61: =IFERROR(VLOOKUP(G59,'Mezz Amort'!$A$15:$I$1810,7,FALSE),"") -> 1563.3333
B62: ='Senior Amort'!K21 -> Valuation Date | C62: ='Senior Amort'!L21 -> 43125 | D62: ='Senior Amort'!M21 -> Total Debt + Liabilities | F62: Senior Loan at Impairment | G62: =IFERROR(VLOOKUP(G59,'Senior Amort'!$A$33:$I$1835,9,FALSE),"")
B63: ='Senior Amort'!K22 -> Method | C63: ='Senior Amort'!L22 -> Comparable Sales | D63: ='Senior Amort'!M22 -> 29400 | F63: Total Loan | G63: =SUM(G61:G62) -> 1563.3333
B64: ='Senior Amort'!K24 -> Senior Cost/Day | C64: ='Senior Amort'!L23 -> 23.333333 | D64: ='Senior Amort'!M23 -> Left to Draw | F64: 90% Net Realizable Value | G64: =G48*0.9 -> 0
B65: ='Senior Amort'!K23 -> Cambia Cost/Day | C65: ='Senior Amort'!L24 -> 0 | D65: ='Senior Amort'!M24 -> #REF!
B66: ='Senior Amort'!K25 -> Finance cost/Day | C66: ='Senior Amort'!L25 -> 0 | D66: Senior Note

Sheet Release Price
A2: Name: | B2: ='Deal Details'!C3 -> 0 | C2: Date of Valuation: | D2: ='Deal Details'!C31 -> 46105 | E2: LTV: | F2: ='Deal Details'!F36
G3: Deal as a whole | H3: Par Plus | L3: Per Lot | M3: Par Plus
A4: Unit Mix | B4: Value/Lot | C4: Lots | D4: Total Value | E4: % of total Value | G4: Par | H4: 0.2 | I4: 0.25 | J4: 0.3 | L4: Par/Lot | M4: 0.2 | N4: 0.25 | O4: 0.3
A6: =Valuation!A2 -> 0 | B6: =Valuation!B2 -> 0 | C6: =Valuation!C2 -> 0 | D6: =Valuation!D2 -> 0 | E6: =D6/$D$13 -> #DIV/0! | G6: ='Deal Details'!$C$29*'Release Price'!E6 -> #DIV/0! | H6: =G6*(1+$H$4) -> #DIV/0! | I6: =G6*(1+$I$4) -> #DIV/0! | J6: =I6*(1+$J$4) -> #DIV/0! | L6: =G6/C6 -> #DIV/0! | M6: =L6*(1+$M$4) -> #DIV/0! | N6: =L6*(1+$N$4) -> #DIV/0! | O6: =L6*(1+$O$4) -> #DIV/0!
A7: =Valuation!A3 -> 0 | B7: =Valuation!B3 -> 0 | C7: =Valuation!C3 -> 0 | D7: =Valuation!D3 -> 0 | E7: =D7/$D$13 -> #DIV/0! | G7: ='Deal Details'!$C$29*'Release Price'!E7 -> #DIV/0! | H7: =G7*(1+$H$4) -> #DIV/0! | I7: =G7*(1+$I$4) -> #DIV/0! | J7: =I7*(1+$J$4) -> #DIV/0! | L7: =IF($B$7>0,G7/$C$7,0) -> 0 | M7: =IF($B$7>0,H7/$C$7,0) -> 0 | N7: =IF($B$7>0,I7/$C$7,0) -> 0 | O7: =IF($B$7>0,J7/$C$7,0) -> 0
A8: =Valuation!A4 -> 0 | B8: =Valuation!B4 -> 0 | C8: =Valuation!C4 -> 0 | D8: =Valuation!D4 -> 0 | E8: =D8/$D$13 -> #DIV/0! | G8: ='Deal Details'!$C$29*'Release Price'!E8 -> #DIV/0! | H8: =G8*(1+$H$4) -> #DIV/0! | I8: =G8*(1+$I$4) -> #DIV/0! | J8: =I8*(1+$J$4) -> #DIV/0! | L8: =IF($B$8>0,G8/$C$8,0) -> 0 | M8: =IF($B$8>0,H8/$C$8,0) -> 0 | N8: =IF($B$8>0,I8/$C$8,0) -> 0 | O8: =IF($B$8>0,J8/$C$8,0) -> 0
A9: Units Total | C9: =SUM(C6:C8) -> 0 | D9: =SUM(D6:D8) -> 0 | E9: =D9/$D$13 -> #DIV/0! | G9: =SUM(G6:G8) -> #DIV/0! | H9: =G9*(1+$H$4) -> #DIV/0! | I9: =G9*(1+$I$4) -> #DIV/0! | J9: =I9*(1+$J$4) -> #DIV/0! | L9: =G9/C9 -> #DIV/0! | M9: =L9*(1+$M$4) -> #DIV/0! | N9: =L9*(1+$N$4) -> #DIV/0! | O9: =L9*(1+$O$4) -> #DIV/0!
A11: Additional Collateral | B11: =Valuation!B5 -> 0 | C11: =Valuation!C5 -> 0 | D11: =Valuation!D5 -> 0 | E11: =D11/D13 -> #DIV/0! | G11: =D11 -> 0 | H11: =G11*(1+$H$4) -> 0 | I11: =G11*(1+$I$4) -> 0 | J11: =I11*(1+$J$4) -> 0 | L11: =IF($B$11>0,G11/$C$11,0) -> 0 | M11: =IF($B$11>0,H11/$C$11,0) -> 0 | N11: =IF($B$11>0,I11/$C$11,0) -> 0 | O11: =IF($B$11>0,J11/$C$11,0) -> 0
A13: Total Value | C13: =SUM(C11,C9) -> 0 | D13: =SUM(D9,D11) -> 0 | E13: =SUM(E9,E11) -> #DIV/0! | G13: =SUM(G9,G11) -> #DIV/0! | H13: =SUM(H9,H11) -> #DIV/0! | I13: =SUM(I9,I11) -> #DIV/0! | J13: =SUM(J9,J11) -> #DIV/0! | L13: =IF($B$13>0,SUM(L9+L11),L9) -> #DIV/0! | M13: =IF($B$13>0,SUM(M9+M11),M9) -> #DIV/0! | N13: =IF($B$13>0,SUM(N9+N11),N9) -> #DIV/0! | O13: =IF($B$13>0,SUM(O9+O11),O9) -> #DIV/0!

Sheet Process Checklist
C3: Phase 1
C4: 1 | D4: Pro Forma/Budgets Sponsor(s) financial (Partnership)
C5: 2 | D5: Sponsor(s) resume - past Projects
C6: 3 | D6: Sponsor(s) Current projects
C7: 4 | D7: Executing Team
C8: 5 | D8: Title report
C9: 6 | D9: Appraisal/CMA/BPO
C10: 7 | D10: Project documents
D11: A) | E11: Engineering
D12: B) | E12: Architecture and floor Plans
D13: C) | E13: Surveys and reports
D14: D) | E14: Site plan, plat
D15: E) | E15: Certificates, approvals, permits
D16: F) | E16: Insurance and Bonds
D17: G) | E17: Marketing Material (if available)
D18: H) Property/Development agreements
D19: I) | E19: GC contact information including license, bond, and insurance
D20: J) | E20: Organizational documents of any entities that will be members of the borrower and pledging its interest in borrower or such other documents providing reasonable evidence for authority to pledge interest in borrower
C21: 8 | D21: Exit Plan
C22: 9 | D22: Purchase and sale agreement (Acquisition)
C23: 10 | D23: 1st Position lender commitment letters/Loan Docs
C25: Phase 2
C26: 1 | D26: Collect Signed LOI and non-refundable check
C27: 2 | D27: Site visit
C28: 3 | D28: Face to face meeting with sponsor
C29: 4 | D29: Sponsor Entity Information
D30: A) | E30: Good Standing with Department of Revenue (see state website)
D31: B) | E31: Good standing with Labor and Industries (if the sponsor is a builder see state website)
D32: C) | E32: EIN
D33: D) | E33: Certificate of Formation
D34: E) | E34: Master Business License
C35: 5 | D35: Order/Collect Appraisal
C36: 6 | D36: Sponsor(s) tax returns (Most Recent)
D37: A) | E37: Include all k-1's and 1065's on all partnerships
C38: 7 | D38: Final pro-forma and budgets
C39: 8 | D39: Closing Settlement Statement (Acquistion)
